Workbook
Name AttritionReasonCategories: tblAttritionReasonCategory[Attrition Reason Category]
Name AttritionReasons: tblAttritionReasons[Attrition Reasons]
Name AttritionTypes: tblAttritionTypes[Attrition Types]
Name CandidateSources: tblCandidateSources[Candidate Sources]
Name CostTypes: tblCostType[Cost Type]
Name Departments: tblDepartments[Departments]
Name EmployeeStatuses: tblEmployeeStatuses[Employee Statuses]
Name EmploymentTypes: tblEmploymentTypes[Employment Types]
Name HiringPriorities: tblHiringPriorities[Hiring Priorities]
Name JobFamilies: tblJobFamilies[Job Families]
Name OfferStatuses: tblOfferStatuses[Offer Statuses]
Name RecruitmentStages: tblRecruitmentStages[Recruitment Stages]
Name RequisitionStatuses: tblRequisitionStatuses[Requisition Statuses]
Name RiskCategories: tblRiskCategories[Risk Categories]
Name SLAStatuses: tblSLAStatuses[SLA Statuses]

Sheet 00_ReadMe
A1: HR Workforce Analytics Tracker
A2: Formula-driven, audit-ready portfolio workbook using synthetic data only.
A4: Project | B4: HR Workforce Analytics Tracker | H4: SOP Step | J4: Process Guidance | N4: Owner
A5: Company Scenario | B5: Northstar Financing Corporation | H5: 1. Update source tables | J5: Add or import new employee, requisition, recruitment, onboarding, attrition, cost, headcount, and productivity records. | N5: HR Staff
A6: Purpose | B6: Centralized HR operations and workforce analytics system for a fictional mid-sized financing company. | H6: 2. Validate data | J6: Open 18_QA_Checks and resolve any Fail/Review items before reporting. | N6: HR Staff / HR Manager
A7: Architecture | B7: Synthetic Source Tables → Calculation Layer → Analysis Summary → Dashboards → Power BI / SQL documentation. | H7: 3. Review calculation layer | J7: Confirm reporting start/end dates and review formula-driven helper outputs. | N7: HR Manager
A8: Important Rule | B8: Source/sample records and documentation are intentionally static. KPI cards, summaries, QA checks, risk scores, and chart sources are formula-driven. | H8: 4. Review dashboards | J8: Use dashboard views for HR operations, managerial review, and executive reporting. | N8: HR Manager / Executives
A9: Data Privacy | B9: Synthetic data only; no real employee or company data used. | H9: 5. Refresh BI model | J9: If using Power BI, refresh imported Excel tables and validate DAX measures. | N9: BI Analyst
A10: Primary Users | B10: HR staff, HR managers, department heads, finance/management, executives.
A11: How to Use | B11: Update source tables, review QA checks, refresh formulas/charts, and use dashboards for decisions.
A14: Sheet | B14: Type | C14: Purpose | D14: Update Frequency | F14: RACI Activity | G14: HR Staff | H14: HR Manager | I14: Department Head | J14: Finance | K14: Executive
A15: 00_ReadMe | B15: Documentation/Output | C15: See sheet title and data dictionary for details. | D15: As needed | F15: Maintain employee data | G15: R | H15: A | I15: C | J15: I | K15: I
A16: 01_Data_Dictionary | B16: Documentation/Output | C16: See sheet title and data dictionary for details. | D16: As needed | F16: Approve manpower request | G16: C | H16: A | I16: R | J16: C | K16: I
A17: 02_Lookup_Lists | B17: Documentation/Output | C17: See sheet title and data dictionary for details. | D17: As needed | F17: Track candidates | G17: R | H17: A | I17: I | J17: I | K17: I
A18: 03_Employee_Master | B18: Source | C18: See sheet title and data dictionary for details. | D18: As needed | F18: Validate hiring costs | G18: C | H18: I | I18: I | J18: A/R | K18: I
A19: 04_Department_Position_Master | B19: Source | C19: See sheet title and data dictionary for details. | D19: As needed | F19: Review dashboards | G19: I | H19: R | I19: R | J19: C | K19: A
A20: 05_Requisitions_MRF | B20: Source | C20: See sheet title and data dictionary for details. | D20: As needed | F20: Act on attrition risk | G20: C | H20: R | I20: A/R | J20: I | K20: I
A21: 06_Recruitment_Pipeline | B21: Source | C21: See sheet title and data dictionary for details. | D21: As needed
A22: 07_Hiring_Costs | B22: Source | C22: See sheet title and data dictionary for details. | D22: As needed | F22: This workbook uses synthetic data only and is intended as a portfolio project to demonstrate HR analytics, workforce planning, Excel systems design, SQL-readiness, Power BI-readiness, and dashboard reporting. | J22: Legends: R = Responsible A = Accountable C = Consulted I = Informed
A23: 08_Onboarding_Tracker | B23: Source | C23: See sheet title and data dictionary for details. | D23: As needed
A24: 09_Attrition_Tracker | B24: Source | C24: See sheet title and data dictionary for details. | D24: As needed
A25: 10_Productivity_Inputs | B25: Source | C25: See sheet title and data dictionary for details. | D25: As needed
A26: 11_Headcount_Snapshot | B26: Source | C26: See sheet title and data dictionary for details. | D26: As needed
A27: 12_Calculation_Layer | B27: Documentation/Output | C27: See sheet title and data dictionary for details. | D27: As needed
A28: 13_Analysis_Summary | B28: Documentation/Output | C28: See sheet title and data dictionary for details. | D28: As needed
A29: 14_Dashboard_HR_Ops | B29: Dashboard | C29: See sheet title and data dictionary for details. | D29: Auto-updates from formulas
A30: 15_Dashboard_Managerial | B30: Dashboard | C30: See sheet title and data dictionary for details. | D30: Auto-updates from formulas
A31: 16_Dashboard_Executive | B31: Dashboard | C31: See sheet title and data dictionary for details. | D31: Auto-updates from formulas
A32: 17_Change_Log | B32: Documentation/Output | C32: See sheet title and data dictionary for details. | D32: As needed
A33: 18_QA_Checks | B33: Documentation/Output | C33: See sheet title and data dictionary for details. | D33: As needed
A34: 19_SQL_Schema | B34: Documentation/Output | C34: See sheet title and data dictionary for details. | D34: As needed
... A36: 21_Portfolio_Case_Study | B36: Documentation/Output | C36: See sheet title and data dictionary for details. | D36: As needed

Sheet 01_Data_Dictionary
A1: Data Dictionary
A2: Field definitions, data types, required flags, examples, allowed values, and source notes.
A4: Sheet/Table | B4: Table Name | C4: Field Name | D4: Description | E4: Data Type | F4: Required? | G4: Example Value | H4: Allowed Values / Notes
A5: 03_Employee_Master | B5: tblEmployeeMaster | C5: EMPLOYEE_ID | D5: Stable unique identifier for employee. | E5: Text | F5: Yes | G5: EMP-0001 | H5: Free text / calculated / source record
A6: 03_Employee_Master | B6: tblEmployeeMaster | C6: EMPLOYEE_NAME | D6: Employee Name field used by the HR workforce analytics tracker. | E6: Text | F6: No | G6: Ethan Santos | H6: Free text / calculated / source record
A7: 03_Employee_Master | B7: tblEmployeeMaster | C7: DEPARTMENT | D7: Workforce classification field used for grouping and reporting. | E7: Text | F7: Yes | G7: Compliance | H7: Departments lookup
A8: 03_Employee_Master | B8: tblEmployeeMaster | C8: TEAM_UNIT | D8: Team Unit field used by the HR workforce analytics tracker. | E8: Text | F8: No | G8: Team C | H8: Free text / calculated / source record
A9: 03_Employee_Master | B9: tblEmployeeMaster | C9: POSITION_ID | D9: Stable unique identifier for position. | E9: Text | F9: Yes | G9: POS-026 | H9: Free text / calculated / source record
A10: 03_Employee_Master | B10: tblEmployeeMaster | C10: POSITION_TITLE | D10: Workforce classification field used for grouping and reporting. | E10: Text | F10: Yes | G10: Compliance Officer | H10: Free text / calculated / source record
A11: 03_Employee_Master | B11: tblEmployeeMaster | C11: JOB_FAMILY | D11: Workforce classification field used for grouping and reporting. | E11: Text | F11: No | G11: Compliance | H11: Job Families lookup
A12: 03_Employee_Master | B12: tblEmployeeMaster | C12: JOB_LEVEL | D12: Job Level field used by the HR workforce analytics tracker. | E12: Text | F12: No | G12: Specialist | H12: Free text / calculated / source record
A13: 03_Employee_Master | B13: tblEmployeeMaster | C13: EMPLOYMENT_TYPE | D13: Employment Type field used by the HR workforce analytics tracker. | E13: Text | F13: No | G13: Regular | H13: Employment Types lookup
A14: 03_Employee_Master | B14: tblEmployeeMaster | C14: HIRE_DATE | D14: Date field used for aging, trend, and SLA calculations. | E14: Date | F14: Yes | G14: 2024-08-18 | H14: Free text / calculated / source record
A15: 03_Employee_Master | B15: tblEmployeeMaster | C15: REGULARIZATION_DATE | D15: Date field used for aging, trend, and SLA calculations. | E15: Date | F15: Yes | G15: 2025-02-14 | H15: Free text / calculated / source record
A16: 03_Employee_Master | B16: tblEmployeeMaster | C16: EMPLOYEE_STATUS | D16: Controlled status field used for process tracking and exceptions. | E16: Text | F16: Yes | G16: Active | H16: Employee Statuses lookup
A17: 03_Employee_Master | B17: tblEmployeeMaster | C17: MANAGER_ID | D17: Stable unique identifier for manager. | E17: Text | F17: Conditional | H17: Should be No/Conditional, because top-level employees may not have one
A18: 03_Employee_Master | B18: tblEmployeeMaster | C18: LOCATION | D18: Location field used by the HR workforce analytics tracker. | E18: Text | F18: No | G18: Baguio Branch | H18: Free text / calculated / source record
A19: 03_Employee_Master | B19: tblEmployeeMaster | C19: SALARY_BAND | D19: Salary Band field used by the HR workforce analytics tracker. | E19: Text | F19: No | G19: Band B | H19: Free text / calculated / source record
A20: 03_Employee_Master | B20: tblEmployeeMaster | C20: TENURE_MONTHS | D20: Tenure Months field used by the HR workforce analytics tracker. | E20: Number | F20: No | H20: Free text / calculated / source record
A21: 03_Employee_Master | B21: tblEmployeeMaster | C21: TENURE_BUCKET | D21: Tenure Bucket field used by the HR workforce analytics tracker. | E21: Text | F21: No | H21: Free text / calculated / source record
A22: 03_Employee_Master | B22: tblEmployeeMaster | C22: IS_ACTIVE | D22: Is Active field used by the HR workforce analytics tracker. | E22: Text | F22: No | H22: Free text / calculated / source record
A23: 03_Employee_Master | B23: tblEmployeeMaster | C23: REPLACEMENT_REQUIRED | D23: Replacement Required field used by the HR workforce analytics tracker. | E23: Text | F23: No | G23: No | H23: Yes/No
A24: 04_Department_Position_Master | B24: tblDepartmentPosition | C24: POSITION_ID | D24: Stable unique identifier for position. | E24: Text | F24: Yes | G24: POS-001 | H24: Free text / calculated / source record
A25: 04_Department_Position_Master | B25: tblDepartmentPosition | C25: DEPARTMENT | D25: Workforce classification field used for grouping and reporting. | E25: Text | F25: Yes | G25: Branch Operations | H25: Departments lookup
A26: 04_Department_Position_Master | B26: tblDepartmentPosition | C26: POSITION_TITLE | D26: Workforce classification field used for grouping and reporting. | E26: Text | F26: Yes | G26: Branch Associate | H26: Free text / calculated / source record
A27: 04_Department_Position_Master | B27: tblDepartmentPosition | C27: JOB_FAMILY | D27: Workforce classification field used for grouping and reporting. | E27: Text | F27: No | G27: Operations | H27: Job Families lookup
A28: 04_Department_Position_Master | B28: tblDepartmentPosition | C28: APPROVED_HEADCOUNT | D28: Numeric count used in workforce capacity calculations. | E28: Number | F28: No | G28: 15 | H28: Free text / calculated / source record
A29: 04_Department_Position_Master | B29: tblDepartmentPosition | C29: CRITICAL_ROLE_FLAG | D29: Critical Role Flag field used by the HR workforce analytics tracker. | E29: Text | F29: No | G29: Yes | H29: Free text / calculated / source record
A30: 04_Department_Position_Master | B30: tblDepartmentPosition | C30: SLA_TARGET_DAYS_TO_FILL | D30: Sla Target Days To Fill field used by the HR workforce analytics tracker. | E30: Number | F30: No | G30: 20 | H30: Free text / calculated / source record
A31: 04_Department_Position_Master | B31: tblDepartmentPosition | C31: HIRING_PRIORITY | D31: Hiring Priority field used by the HR workforce analytics tracker. | E31: Text | F31: No | G31: Critical | H31: Free text / calculated / source record
A32: 04_Department_Position_Master | B32: tblDepartmentPosition | C32: BUSINESS_OWNER | D32: Business Owner field used by the HR workforce analytics tracker. | E32: Text | F32: No | G32: Branch Operations Head | H32: Free text / calculated / source record
A33: 05_Requisitions_MRF | B33: tblRequisitions | C33: REQ_ID | D33: Stable unique identifier for req. | E33: Text | F33: Yes | G33: REQ-0001 | H33: Free text / calculated / source record
A34: 05_Requisitions_MRF | B34: tblRequisitions | C34: REQUEST_DATE | D34: Date field used for aging, trend, and SLA calculations. | E34: Date | F34: Yes | G34: 2026-03-30 | H34: Free text / calculated / source record
A35: 05_Requisitions_MRF | B35: tblRequisitions | C35: APPROVAL_DATE | D35: Date field used for aging, trend, and SLA calculations. | E35: Date | F35: Yes | G35: 2026-04-06 | H35: Free text / calculated / source record
A36: 05_Requisitions_MRF | B36: tblRequisitions | C36: DEPARTMENT | D36: Workforce classification field used for grouping and reporting. | E36: Text | F36: Yes | G36: Loan Processing | H36: Departments lookup
A37: 05_Requisitions_MRF | B37: tblRequisitions | C37: POSITION_ID | D37: Stable unique identifier for position. | E37: Text | F37: Yes | G37: POS-008 | H37: Free text / calculated / source record
A38: 05_Requisitions_MRF | B38: tblRequisitions | C38: POSITION_TITLE | D38: Workforce classification field used for grouping and reporting. | E38: Text | F38: Yes | G38: Processing Specialist | H38: Free text / calculated / source record
A39: 05_Requisitions_MRF | B39: tblRequisitions | C39: REQUEST_TYPE | D39: Request Type field used by the HR workforce analytics tracker. | E39: Text | F39: No | G39: Replacement | H39: Free text / calculated / source record
A40: 05_Requisitions_MRF | B40: tblRequisitions | C40: APPROVED_HEADCOUNT | D40: Numeric count used in workforce capacity calculations. | E40: Number | F40: No | G40: 1 | H40: Free text / calculated / source record
A41: 05_Requisitions_MRF | B41: tblRequisitions | C41: PRIORITY | D41: Priority field used by the HR workforce analytics tracker. | E41: Text | F41: No | G41: Critical | H41: Hiring Priorities lookup
A42: 05_Requisitions_MRF | B42: tblRequisitions | C42: TARGET_START_DATE | D42: Date field used for aging, trend, and SLA calculations. | E42: Date | F42: Yes | G42: 2026-05-12 | H42: Free text / calculated / source record
A43: 05_Requisitions_MRF | B43: tblRequisitions | C43: REQ_STATUS | D43: Controlled status field used for process tracking and exceptions. | E43: Text | F43: Yes | G43: Filled | H43: Requisition Statuses lookup
A44: 05_Requisitions_MRF | B44: tblRequisitions | C44: ASSIGNED_RECRUITER | D44: Assigned Recruiter field used by the HR workforce analytics tracker. | E44: Text | F44: No | G44: RCR-003 Leah Cruz | H44: Free text / calculated / source record
A45: 05_Requisitions_MRF | B45: tblRequisitions | C45: SLA_TARGET_DAYS | D45: Sla Target Days field used by the HR workforce analytics tracker. | E45: Number | F45: No | G45: 45 | H45: Free text / calculated / source record
A46: 05_Requisitions_MRF | B46: tblRequisitions | C46: DAYS_OPEN | D46: Days Open field used by the HR workforce analytics tracker. | E46: Number | F46: No | H46: Free text / calculated / source record
A47: 05_Requisitions_MRF | B47: tblRequisitions | C47: SLA_STATUS | D47: Controlled status field used for process tracking and exceptions. | E47: Text | F47: Yes | H47: SLA Statuses lookup
A48: 05_Requisitions_MRF | B48: tblRequisitions | C48: FILLED_COUNT | D48: Numeric count used in workforce capacity calculations. | E48: Number | F48: No | H48: Free text / calculated / source record
A49: 05_Requisitions_MRF | B49: tblRequisitions | C49: VACANCY_REMAINING | D49: Vacancy Remaining field used by the HR workforce analytics tracker. | E49: Number | F49: No | H49: Free text / calculated / source record
A50: 05_Requisitions_MRF | B50: tblRequisitions | C50: FILLED_DATE | D50: Date when the requisition was successfully filled or closed with a hired candidate. | E50: Date | F50: Conditional | G50: 46165 | H50: Required if REQ_STATUS = Filled
A51: 05_Requisitions_MRF | B51: tblRequisitions | C51: TIME_TO_FILL_DAYS | D51: Number of calendar days from requisition approval date to filled date. Used to measure recruitment turnaround time. | E51: Number | F51: No | G51: 47 | H51: Formula-driven; FILLED_DATE - APPROVAL_DATE
A52: 05_Requisitions_MRF | B52: tblRequisitions | C52: TIME_TO_FILL_STATUS | D52: Formula-driven SLA classification showing whether the requisition was filled within the target time-to-fill. | E52: Text | F52: No | G52: On Track | H52: Formula-driven; compare TIME_TO_FILL_DAYS against SLA_TARGET_DAYS
A53: 06_Recruitment_Pipeline | B53: tblRecruitmentPipeline | C53: APPLICATION_ID | D53: Stable unique identifier for application. | E53: Text | F53: Yes | G53: APP-00001 | H53: Free text / calculated / source record
A54: 06_Recruitment_Pipeline | B54: tblRecruitmentPipeline | C54: REQ_ID | D54: Stable unique identifier for req. | E54: Text | F54: Yes | G54: REQ-0001 | H54: Free text / calculated / source record
A55: 06_Recruitment_Pipeline | B55: tblRecruitmentPipeline | C55: CANDIDATE_ID | D55: Stable unique identifier for candidate. | E55: Text | F55: Yes | G55: CAND-00001 | H55: Free text / calculated / source record
A56: 06_Recruitment_Pipeline | B56: tblRecruitmentPipeline | C56: CANDIDATE_NAME | D56: Date field used for aging, trend, and SLA calculations. | E56: Text | F56: Yes | G56: Camille Navarro | H56: Free text / calculated / source record
A57: 06_Recruitment_Pipeline | B57: tblRecruitmentPipeline | C57: SOURCE | D57: Source field used by the HR workforce analytics tracker. | E57: Text | F57: No | G57: Agency | H57: Candidate Sources lookup
A58: 06_Recruitment_Pipeline | B58: tblRecruitmentPipeline | C58: APPLICATION_DATE | D58: Date field used for aging, trend, and SLA calculations. | E58: Date | F58: Yes | G58: 2026-04-13 | H58: Free text / calculated / source record
A59: 06_Recruitment_Pipeline | B59: tblRecruitmentPipeline | C59: CURRENT_STAGE | D59: Current Stage field used by the HR workforce analytics tracker. | E59: Text | F59: No | G59: Hired | H59: Recruitment Stages lookup
A60: 06_Recruitment_Pipeline | B60: tblRecruitmentPipeline | C60: STAGE_DATE | D60: Date field used for aging, trend, and SLA calculations. | E60: Date | F60: Yes | G60: 2026-05-19 | H60: Free text / calculated / source record
A61: 06_Recruitment_Pipeline | B61: tblRecruitmentPipeline | C61: RECRUITER | D61: Recruiter field used by the HR workforce analytics tracker. | E61: Text | F61: No | G61: RCR-003 Leah Cruz | H61: Free text / calculated / source record
A62: 06_Recruitment_Pipeline | B62: tblRecruitmentPipeline | C62: INTERVIEWER | D62: Interviewer field used by the HR workforce analytics tracker. | E62: Text | F62: No | G62: Panel Interview | H62: Free text / calculated / source record
A63: 06_Recruitment_Pipeline | B63: tblRecruitmentPipeline | C63: OFFER_DATE | D63: Date field used for aging, trend, and SLA calculations. | E63: Date | F63: Conditional | G63: 2026-05-16 | H63: Required only if OFFER_STATUS is Accepted/Declined/Pending
... A65: 06_Recruitment_Pipeline | B65: tblRecruitmentPipeline | C65: HIRE_DATE | D65: Date field used for aging, trend, and SLA calculations. | E65: Date | F65: Conditional | G65: 2026-05-23 | H65: Required only if CURRENT_STAGE = Hired
A66: 06_Recruitment_Pipeline | B66: tblRecruitmentPipeline | C66: REJECTION_REASON | D66: Rejection Reason field used by the HR workforce analytics tracker. | E66: Text | F66: Conditional | H66: Required only if CURRENT_STAGE = Rejected
A67: 06_Recruitment_Pipeline | B67: tblRecruitmentPipeline | C67: WITHDRAWAL_REASON | D67: Withdrawal Reason field used by the HR workforce analytics tracker. | E67: Text | F67: Conditional | H67: Required only if CURRENT_STAGE = Withdrawn
A68: 06_Recruitment_Pipeline | B68: tblRecruitmentPipeline | C68: DAYS_IN_PIPELINE | D68: Days In Pipeline field used by the HR workforce analytics tracker. | E68: Number | F68: No | H68: Free text / calculated / source record
A69: 06_Recruitment_Pipeline | B69: tblRecruitmentPipeline | C69: PIPELINE_STATUS | D69: Controlled status field used for process tracking and exceptions. | E69: Text | F69: Yes | H69: Free text / calculated / source record
A70: 06_Recruitment_Pipeline | B70: tblRecruitmentPipeline | C70: STAGE_AGING_FLAG | D70: Stage Aging Flag field used by the HR workforce analytics tracker. | E70: Text | F70: No | H70: Free text / calculated / source record
A71: 06_Recruitment_Pipeline | B71: tblRecruitmentPipeline | C71: TIME_TO_HIRE_DAYS | D71: Time To Hire Days field used by the HR workforce analytics tracker. | E71: Number | F71: No | H71: Free text / calculated / source record
A72: 06_Recruitment_Pipeline | B72: tblRecruitmentPipeline | C72: REQ_DEPARTMENT | D72: Department linked to the requisition based on REQ_ID. Used for department-level recruitment reporting and analysis. | E72: Text | F72: No | G72: Loan Processing | H72: Formula-driven lookup from tblRequisitions using REQ_ID
A73: 07_Hiring_Costs | B73: tblHiringCosts | C73: COST_ID | D73: Stable unique identifier for cost. | E73: Text | F73: Yes | G73: COST-0001 | H73: Free text / calculated / source record
A74: 07_Hiring_Costs | B74: tblHiringCosts | C74: REQ_ID | D74: Stable unique identifier for req. | E74: Text | F74: Yes | G74: REQ-0079 | H74: Free text / calculated / source record
A75: 07_Hiring_Costs | B75: tblHiringCosts | C75: COST_DATE | D75: Date field used for aging, trend, and SLA calculations. | E75: Date | F75: Yes | G75: 2025-08-23 | H75: Free text / calculated / source record
A76: 07_Hiring_Costs | B76: tblHiringCosts | C76: COST_TYPE | D76: Cost Type field used by the HR workforce analytics tracker. | E76: Text | F76: No | G76: Agency Fee | H76: Free text / calculated / source record
A77: 07_Hiring_Costs | B77: tblHiringCosts | C77: VENDOR | D77: Vendor field used by the HR workforce analytics tracker. | E77: Text | F77: No | G77: Clinic Partner | H77: Free text / calculated / source record
A78: 07_Hiring_Costs | B78: tblHiringCosts | C78: AMOUNT | D78: Amount field used by the HR workforce analytics tracker. | E78: Number | F78: No | G78: 9063.56 | H78: Free text / calculated / source record
A79: 07_Hiring_Costs | B79: tblHiringCosts | C79: DEPARTMENT | D79: Workforce classification field used for grouping and reporting. | E79: Text | F79: Yes | G79: Finance | H79: Departments lookup
A80: 07_Hiring_Costs | B80: tblHiringCosts | C80: POSITION_TITLE | D80: Workforce classification field used for grouping and reporting. | E80: Text | F80: Yes | G80: Finance Analyst | H80: Free text / calculated / source record
A81: 07_Hiring_Costs | B81: tblHiringCosts | C81: SOURCE | D81: Source field used by the HR workforce analytics tracker. | E81: Text | F81: No | G81: Employee Referral | H81: Candidate Sources lookup
A82: 07_Hiring_Costs | B82: tblHiringCosts | C82: NOTES | D82: Notes field used by the HR workforce analytics tracker. | E82: Text | F82: No | G82: Synthetic recruitment cost | H82: Free text / calculated / source record
A83: 08_Onboarding_Tracker | B83: tblOnboarding | C83: ONBOARDING_ID | D83: Stable unique identifier for onboarding. | E83: Text | F83: Yes | G83: ONB-0001 | H83: Free text / calculated / source record
A84: 08_Onboarding_Tracker | B84: tblOnboarding | C84: EMPLOYEE_ID | D84: Stable unique identifier for employee. | E84: Text | F84: Yes | G84: EMP-0193 | H84: Free text / calculated / source record
A85: 08_Onboarding_Tracker | B85: tblOnboarding | C85: HIRE_DATE | D85: Date field used for aging, trend, and SLA calculations. | E85: Date | F85: Yes | G85: 2024-03-08 | H85: Free text / calculated / source record
A86: 08_Onboarding_Tracker | B86: tblOnboarding | C86: DEPARTMENT | D86: Workforce classification field used for grouping and reporting. | E86: Text | F86: Yes | G86: Human Resources | H86: Departments lookup
A87: 08_Onboarding_Tracker | B87: tblOnboarding | C87: POSITION_TITLE | D87: Workforce classification field used for grouping and reporting. | E87: Text | F87: Yes | G87: HR Manager | H87: Free text / calculated / source record
A88: 08_Onboarding_Tracker | B88: tblOnboarding | C88: CONTRACT_SIGNED | D88: Contract Signed field used by the HR workforce analytics tracker. | E88: Text | F88: No | G88: Yes | H88: Free text / calculated / source record
A89: 08_Onboarding_Tracker | B89: tblOnboarding | C89: PRE_EMPLOYMENT_DOCS | D89: Pre Employment Docs field used by the HR workforce analytics tracker. | E89: Text | F89: No | G89: Yes | H89: Free text / calculated / source record
A90: 08_Onboarding_Tracker | B90: tblOnboarding | C90: IT_ACCOUNT_CREATED | D90: Numeric count used in workforce capacity calculations. | E90: Yes-No | F90: No | G90: Yes | H90: Free text / calculated / source record
... A96: 08_Onboarding_Tracker | B96: tblOnboarding | C96: ONBOARDING_STATUS | D96: Controlled status field used for process tracking and exceptions. | E96: Text | F96: Yes | G96: Complete | H96: Not Started/In Progress/Complete/Delayed
A97: 08_Onboarding_Tracker | B97: tblOnboarding | C97: ONBOARDING_COMPLETION_RATE | D97: Calculated percentage used for KPI and dashboard reporting. | E97: Number | F97: No | H97: Free text / calculated / source record
A98: 08_Onboarding_Tracker | B98: tblOnboarding | C98: COMPLETION_DATE | D98: Date field used for aging, trend, and SLA calculations. | E98: Date | F98: Conditional | G98: 2024-04-18 | H98: Required only if ONBOARDING_STATUS = Complete
A99: 08_Onboarding_Tracker | B99: tblOnboarding | C99: DAYS_TO_COMPLETE | D99: Days To Complete field used by the HR workforce analytics tracker. | E99: Number | F99: No | G99: 12 | H99: Free text / calculated / source record
A100: 08_Onboarding_Tracker | B100: tblOnboarding | C100: RETAINED_90D | D100: Retained 90D field used by the HR workforce analytics tracker. | E100: Text | F100: No | H100: Free text / calculated / source record
A101: 09_Attrition_Tracker | B101: tblAttrition | C101: ATTRITION_ID | D101: Stable unique identifier for attrition. | E101: Text | F101: Yes | G101: ATR-0001 | H101: Free text / calculated / source record
A102: 09_Attrition_Tracker | B102: tblAttrition | C102: EMPLOYEE_ID | D102: Stable unique identifier for employee. | E102: Text | F102: Yes | G102: EMP-0006 | H102: Free text / calculated / source record
A103: 09_Attrition_Tracker | B103: tblAttrition | C103: EMPLOYEE_NAME | D103: Employee Name field used by the HR workforce analytics tracker. | E103: Text | F103: No | G103: Jose Torres | H103: Free text / calculated / source record
A104: 09_Attrition_Tracker | B104: tblAttrition | C104: DEPARTMENT | D104: Workforce classification field used for grouping and reporting. | E104: Text | F104: Yes | G104: Compliance | H104: Departments lookup
A105: 09_Attrition_Tracker | B105: tblAttrition | C105: POSITION_TITLE | D105: Workforce classification field used for grouping and reporting. | E105: Text | F105: Yes | G105: Compliance Officer | H105: Free text / calculated / source record
A106: 09_Attrition_Tracker | B106: tblAttrition | C106: HIRE_DATE | D106: Date field used for aging, trend, and SLA calculations. | E106: Date | F106: Yes | G106: 2019-07-10 | H106: Free text / calculated / source record
A107: 09_Attrition_Tracker | B107: tblAttrition | C107: SEPARATION_DATE | D107: Date field used for aging, trend, and SLA calculations. | E107: Date | F107: Yes | G107: 2025-02-23 | H107: Free text / calculated / source record
...

Sheet 02_Lookup_Lists
A1: Lookup Lists
A2: Controlled values for dropdowns and validation rules.
A4: Departments | C4: Job Families | E4: Employment Types | G4: Employee Statuses | I4: Recruitment Stages | K4: Requisition Statuses | M4: Hiring Priorities | O4: Candidate Sources | Q4: Offer Statuses | S4: Attrition Types | U4: Attrition Reasons | W4: Risk Categories | Y4: SLA Statuses | AA4: Cost Type | AC4: Attrition Reason Category
A5: Branch Operations | C5: Collections | E5: Regular | G5: Active | I5: Applied | K5: Open | M5: Low | O5: JobStreet | Q5: Accepted | S5: Voluntary | U5: Compensation | W5: Low Risk | Y5: On Track | AA5: Job Ad | AC5: Compensation
A6: Credit Evaluation | C6: Compliance | E6: Probationary | G6: Resigned | I6: Screened | K6: Filled | M6: Medium | O6: LinkedIn | Q6: Declined | S6: Involuntary | U6: Career Growth | W6: Moderate Risk | Y6: At Risk | AA6: Agency Fee | AC6: Career Growth
A7: Loan Processing | C7: Credit & Risk | E7: Contractual | G7: Terminated | I7: Interview | K7: On Hold | M7: High | O7: Employee Referral | Q7: Pending | U7: Management | W7: High Risk | Y7: Delayed | AA7: Referral Bonus | AC7: Management
A8: Collections | C8: Finance | E8: Project-based | G8: On Leave | I8: Final Interview | K8: Cancelled | M8: Critical | O8: Facebook | Q8: Not Offered | U8: Workload | W8: Critical Risk | AA8: Medical | AC8: Workload
A9: Sales & Marketing | C9: HR | I9: Offer | O9: Agency | U9: Performance | AA9: Background Check | AC9: Performance
A10: Finance | C10: IT | I10: Hired | O10: Company Website | U10: Personal | AA10: Assessment | AC10: Relocation
A11: Human Resources | C11: Operations | I11: Rejected | O11: Walk-in | U11: Relocation | AA11: Interview Logistics | AC11: Policy Violation
A12: Information Technology | C12: Sales | I12: Withdrawn | U12: Redundancy | AC12: Personal
A13: Compliance | C13: Service | AC13: Redundancy
A14: Customer Service

Sheet 03_Employee_Master
A1: Employee Master
A2: Core synthetic workforce database. Calculated columns update dynamically.
A4: EMPLOYEE_ID | B4: EMPLOYEE_NAME | C4: DEPARTMENT | D4: TEAM_UNIT | E4: POSITION_ID | F4: POSITION_TITLE | G4: JOB_FAMILY | H4: JOB_LEVEL | I4: EMPLOYMENT_TYPE | J4: HIRE_DATE | K4: REGULARIZATION_DATE | L4: EMPLOYEE_STATUS | M4: MANAGER_ID | N4: LOCATION | O4: SALARY_BAND | P4: TENURE_MONTHS | Q4: TENURE_BUCKET | R4: IS_ACTIVE | S4: REPLACEMENT_REQUIRED
A5: EMP-0001 | B5: Ethan Santos | C5: Compliance | D5: Team C | E5: POS-026 | F5: Compliance Officer | G5: Compliance | H5: Specialist | I5: Regular | J5: 45522 | K5: 45702 | L5: Active | N5: Baguio Branch | O5: Band B | P5: =IF($J5="","",MAX(0,INT((IF(OR($L5="Active",$L5="On Leave"),TODAY(),IFERROR(VLOOKUP($A5,'09_Attrition_Tracker'!$B:$G,6,FALSE),TODAY()))-$J5)/30))) -> 20 | Q5: =IF($P5="","",IF($P5<4,"0-3 mos",IF($P5<7,"4-6 mos",IF($P5<13,"7-12 mos",IF($P5<25,"1-2 yrs",IF($P5<61,"2-5 yrs","5+ yrs")))))) -> 1-2 yrs | R5: =IF(OR($L5="Active",$L5="On Leave"),"Yes","No") -> Yes | S5: =IFERROR(VLOOKUP($A5,'09_Attrition_Tracker'!$B:$M,12,FALSE),"No") -> No
A6: EMP-0002 | B6: Patrick Aquino | C6: Branch Operations | D6: Team A | E6: POS-003 | F6: Branch Manager | G6: Operations | H6: Manager | I6: Probationary | J6: 44786 | K6: 44966 | L6: Active | N6: Cebu Branch | O6: Band E | P6: =IF($J6="","",MAX(0,INT((IF(OR($L6="Active",$L6="On Leave"),TODAY(),IFERROR(VLOOKUP($A6,'09_Attrition_Tracker'!$B:$G,6,FALSE),TODAY()))-$J6)/30))) -> 45 | Q6: =IF($P6="","",IF($P6<4,"0-3 mos",IF($P6<7,"4-6 mos",IF($P6<13,"7-12 mos",IF($P6<25,"1-2 yrs",IF($P6<61,"2-5 yrs","5+ yrs")))))) -> 2-5 yrs | R6: =IF(OR($L6="Active",$L6="On Leave"),"Yes","No") -> Yes | S6: =IFERROR(VLOOKUP($A6,'09_Attrition_Tracker'!$B:$M,12,FALSE),"No") -> No
A7: EMP-0003 | B7: Paolo Santos | C7: Loan Processing | D7: Team C | E7: POS-008 | F7: Processing Specialist | G7: Operations | H7: Rank and File | I7: Probationary | J7: 45189 | K7: 45369 | L7: Active | N7: Cebu Branch | O7: Band B | P7: =IF($J7="","",MAX(0,INT((IF(OR($L7="Active",$L7="On Leave"),TODAY(),IFERROR(VLOOKUP($A7,'09_Attrition_Tracker'!$B:$G,6,FALSE),TODAY()))-$J7)/30))) -> 31 | Q7: =IF($P7="","",IF($P7<4,"0-3 mos",IF($P7<7,"4-6 mos",IF($P7<13,"7-12 mos",IF($P7<25,"1-2 yrs",IF($P7<61,"2-5 yrs","5+ yrs")))))) -> 2-5 yrs | R7: =IF(OR($L7="Active",$L7="On Leave"),"Yes","No") -> Yes | S7: =IFERROR(VLOOKUP($A7,'09_Attrition_Tracker'!$B:$M,12,FALSE),"No") -> No
A8: EMP-0004 | B8: Andrea Cruz | C8: Collections | D8: Team B | E8: POS-012 | F8: Collections Supervisor | G8: Collections | H8: Supervisor | I8: Regular | J8: 45733 | K8: 45913 | L8: Active | N8: Iloilo Branch | O8: Band E | P8: =IF($J8="","",MAX(0,INT((IF(OR($L8="Active",$L8="On Leave"),TODAY(),IFERROR(VLOOKUP($A8,'09_Attrition_Tracker'!$B:$G,6,FALSE),TODAY()))-$J8)/30))) -> 13 | Q8: =IF($P8="","",IF($P8<4,"0-3 mos",IF($P8<7,"4-6 mos",IF($P8<13,"7-12 mos",IF($P8<25,"1-2 yrs",IF($P8<61,"2-5 yrs","5+ yrs")))))) -> 1-2 yrs | R8: =IF(OR($L8="Active",$L8="On Leave"),"Yes","No") -> Yes | S8: =IFERROR(VLOOKUP($A8,'09_Attrition_Tracker'!$B:$M,12,FALSE),"No") -> No
A9: EMP-0005 | B9: Gabriel Gonzales | C9: Sales & Marketing | D9: Team B | E9: POS-015 | F9: Sales Manager | G9: Sales | H9: Manager | I9: Regular | J9: 43603 | K9: 43783 | L9: Active | N9: Baguio Branch | O9: Band C | P9: =IF($J9="","",MAX(0,INT((IF(OR($L9="Active",$L9="On Leave"),TODAY(),IFERROR(VLOOKUP($A9,'09_Attrition_Tracker'!$B:$G,6,FALSE),TODAY()))-$J9)/30))) -> 84 | Q9: =IF($P9="","",IF($P9<4,"0-3 mos",IF($P9<7,"4-6 mos",IF($P9<13,"7-12 mos",IF($P9<25,"1-2 yrs",IF($P9<61,"2-5 yrs","5+ yrs")))))) -> 5+ yrs | R9: =IF(OR($L9="Active",$L9="On Leave"),"Yes","No") -> Yes | S9: =IFERROR(VLOOKUP($A9,'09_Attrition_Tracker'!$B:$M,12,FALSE),"No") -> No
A10: EMP-0006 | B10: Jose Torres | C10: Compliance | D10: Team B | E10: POS-026 | F10: Compliance Officer | G10: Compliance | H10: Rank and File | I10: Regular | J10: 43656 | K10: 43836 | L10: Resigned | M10: EMP-0002 | N10: Head Office | O10: Band B | P10: =IF($J10="","",MAX(0,INT((IF(OR($L10="Active",$L10="On Leave"),TODAY(),IFERROR(VLOOKUP($A10,'09_Attrition_Tracker'!$B:$G,6,FALSE),TODAY()))-$J10)/30))) -> 68 | Q10: =IF($P10="","",IF($P10<4,"0-3 mos",IF($P10<7,"4-6 mos",IF($P10<13,"7-12 mos",IF($P10<25,"1-2 yrs",IF($P10<61,"2-5 yrs","5+ yrs")))))) -> 5+ yrs | R10: =IF(OR($L10="Active",$L10="On Leave"),"Yes","No") -> No | S10: =IFERROR(VLOOKUP($A10,'09_Attrition_Tracker'!$B:$M,12,FALSE),"No") -> No
A11: EMP-0007 | B11: Andrea Torres | C11: Branch Operations | D11: Team D | E11: POS-002 | F11: Branch Supervisor | G11: Operations | H11: Supervisor | I11: Regular | J11: 43876 | K11: 44056 | L11: Active | M11: EMP-0002 | N11: Iloilo Branch | O11: Band D | P11: =IF($J11="","",MAX(0,INT((IF(OR($L11="Active",$L11="On Leave"),TODAY(),IFERROR(VLOOKUP($A11,'09_Attrition_Tracker'!$B:$G,6,FALSE),TODAY()))-$J11)/30))) -> 75 | Q11: =IF($P11="","",IF($P11<4,"0-3 mos",IF($P11<7,"4-6 mos",IF($P11<13,"7-12 mos",IF($P11<25,"1-2 yrs",IF($P11<61,"2-5 yrs","5+ yrs")))))) -> 5+ yrs | R11: =IF(OR($L11="Active",$L11="On Leave"),"Yes","No") -> Yes | S11: =IFERROR(VLOOKUP($A11,'09_Attrition_Tracker'!$B:$M,12,FALSE),"No") -> No
A12: EMP-0008 | B12: Martin Gonzales | C12: Credit Evaluation | D12: Team A | E12: POS-004 | F12: Credit Analyst | G12: Credit & Risk | H12: Specialist | I12: Regular | J12: 44187 | L12: Active | M12: EMP-0001 | N12: Davao Branch | O12: Band A | P12: =IF($J12="","",MAX(0,INT((IF(OR($L12="Active",$L12="On Leave"),TODAY(),IFERROR(VLOOKUP($A12,'09_Attrition_Tracker'!$B:$G,6,FALSE),TODAY()))-$J12)/30))) -> 65 | Q12: =IF($P12="","",IF($P12<4,"0-3 mos",IF($P12<7,"4-6 mos",IF($P12<13,"7-12 mos",IF($P12<25,"1-2 yrs",IF($P12<61,"2-5 yrs","5+ yrs")))))) -> 5+ yrs | R12: =IF(OR($L12="Active",$L12="On Leave"),"Yes","No") -> Yes | S12: =IFERROR(VLOOKUP($A12,'09_Attrition_Tracker'!$B:$M,12,FALSE),"No") -> No
A13: EMP-0009 | B13: Ethan Villanueva | C13: Collections | D13: Team D | E13: POS-010 | F13: Collections Associate | G13: Collections | H13: Specialist | I13: Probationary | J13: 43310 | K13: 43490 | L13: Active | M13: EMP-0002 | N13: Manila Branch | O13: Band A | P13: =IF($J13="","",MAX(0,INT((IF(OR($L13="Active",$L13="On Leave"),TODAY(),IFERROR(VLOOKUP($A13,'09_Attrition_Tracker'!$B:$G,6,FALSE),TODAY()))-$J13)/30))) -> 94 | Q13: =IF($P13="","",IF($P13<4,"0-3 mos",IF($P13<7,"4-6 mos",IF($P13<13,"7-12 mos",IF($P13<25,"1-2 yrs",IF($P13<61,"2-5 yrs","5+ yrs")))))) -> 5+ yrs | R13: =IF(OR($L13="Active",$L13="On Leave"),"Yes","No") -> Yes | S13: =IFERROR(VLOOKUP($A13,'09_Attrition_Tracker'!$B:$M,12,FALSE),"No") -> No
A14: EMP-0010 | B14: Paolo Gonzales | C14: Credit Evaluation | D14: Team D | E14: POS-004 | F14: Credit Analyst | G14: Credit & Risk | H14: Specialist | I14: Regular | J14: 44725 | L14: Active | M14: EMP-0003 | N14: Baguio Branch | O14: Band C | P14: =IF($J14="","",MAX(0,INT((IF(OR($L14="Active",$L14="On Leave"),TODAY(),IFERROR(VLOOKUP($A14,'09_Attrition_Tracker'!$B:$G,6,FALSE),TODAY()))-$J14)/30))) -> 47 | Q14: =IF($P14="","",IF($P14<4,"0-3 mos",IF($P14<7,"4-6 mos",IF($P14<13,"7-12 mos",IF($P14<25,"1-2 yrs",IF($P14<61,"2-5 yrs","5+ yrs")))))) -> 2-5 yrs | R14: =IF(OR($L14="Active",$L14="On Leave"),"Yes","No") -> Yes | S14: =IFERROR(VLOOKUP($A14,'09_Attrition_Tracker'!$B:$M,12,FALSE),"No") -> No
A15: EMP-0011 | B15: Ivy Lopez | C15: Sales & Marketing | D15: Team A | E15: POS-014 | F15: Marketing Associate | G15: Sales | H15: Rank and File | I15: Regular | J15: 43370 | L15: On Leave | M15: EMP-0010 | N15: Head Office | O15: Band A | P15: =IF($J15="","",MAX(0,INT((IF(OR($L15="Active",$L15="On Leave"),TODAY(),IFERROR(VLOOKUP($A15,'09_Attrition_Tracker'!$B:$G,6,FALSE),TODAY()))-$J15)/30))) -> 92 | Q15: =IF($P15="","",IF($P15<4,"0-3 mos",IF($P15<7,"4-6 mos",IF($P15<13,"7-12 mos",IF($P15<25,"1-2 yrs",IF($P15<61,"2-5 yrs","5+ yrs")))))) -> 5+ yrs | R15: =IF(OR($L15="Active",$L15="On Leave"),"Yes","No") -> Yes | S15: =IFERROR(VLOOKUP($A15,'09_Attrition_Tracker'!$B:$M,12,FALSE),"No") -> No
A16: EMP-0012 | B16: Paolo Reyes | C16: Compliance | D16: Team A | E16: POS-027 | F16: Compliance Manager | G16: Compliance | H16: Manager | I16: Regular | J16: 44816 | K16: 44996 | L16: Resigned | N16: Makati Branch | O16: Band D | P16: =IF($J16="","",MAX(0,INT((IF(OR($L16="Active",$L16="On Leave"),TODAY(),IFERROR(VLOOKUP($A16,'09_Attrition_Tracker'!$B:$G,6,FALSE),TODAY()))-$J16)/30))) -> 30 | Q16: =IF($P16="","",IF($P16<4,"0-3 mos",IF($P16<7,"4-6 mos",IF($P16<13,"7-12 mos",IF($P16<25,"1-2 yrs",IF($P16<61,"2-5 yrs","5+ yrs")))))) -> 2-5 yrs | R16: =IF(OR($L16="Active",$L16="On Leave"),"Yes","No") -> No | S16: =IFERROR(VLOOKUP($A16,'09_Attrition_Tracker'!$B:$M,12,FALSE),"No") -> Yes
A17: EMP-0013 | B17: Rhea Reyes | C17: Customer Service | D17: Team C | E17: POS-028 | F17: Customer Support Associate | G17: Service | H17: Specialist | I17: Regular | J17: 45272 | L17: Resigned | M17: EMP-0004 | N17: Baguio Branch | O17: Band B | P17: =IF($J17="","",MAX(0,INT((IF(OR($L17="Active",$L17="On Leave"),TODAY(),IFERROR(VLOOKUP($A17,'09_Attrition_Tracker'!$B:$G,6,FALSE),TODAY()))-$J17)/30))) -> 20 | Q17: =IF($P17="","",IF($P17<4,"0-3 mos",IF($P17<7,"4-6 mos",IF($P17<13,"7-12 mos",IF($P17<25,"1-2 yrs",IF($P17<61,"2-5 yrs","5+ yrs")))))) -> 1-2 yrs | R17: =IF(OR($L17="Active",$L17="On Leave"),"Yes","No") -> No | S17: =IFERROR(VLOOKUP($A17,'09_Attrition_Tracker'!$B:$M,12,FALSE),"No") -> No
A18: EMP-0014 | B18: Andrea Santos | C18: Information Technology | D18: Team C | E18: POS-023 | F18: Systems Analyst | G18: IT | H18: Rank and File | I18: Regular | J18: 44613 | K18: 44793 | L18: Active | M18: EMP-0004 | N18: Davao Branch | O18: Band A | P18: =IF($J18="","",MAX(0,INT((IF(OR($L18="Active",$L18="On Leave"),TODAY(),IFERROR(VLOOKUP($A18,'09_Attrition_Tracker'!$B:$G,6,FALSE),TODAY()))-$J18)/30))) -> 51 | Q18: =IF($P18="","",IF($P18<4,"0-3 mos",IF($P18<7,"4-6 mos",IF($P18<13,"7-12 mos",IF($P18<25,"1-2 yrs",IF($P18<61,"2-5 yrs","5+ yrs")))))) -> 2-5 yrs | R18: =IF(OR($L18="Active",$L18="On Leave"),"Yes","No") -> Yes | S18: =IFERROR(VLOOKUP($A18,'09_Attrition_Tracker'!$B:$M,12,FALSE),"No") -> No
A19: EMP-0015 | B19: Paolo Villanueva | C19: Finance | D19: Team C | E19: POS-017 | F19: Finance Analyst | G19: Finance | H19: Rank and File | I19: Contractual | J19: 44961 | K19: 45141 | L19: Active | M19: EMP-0009 | N19: Manila Branch | O19: Band B | P19: =IF($J19="","",MAX(0,INT((IF(OR($L19="Active",$L19="On Leave"),TODAY(),IFERROR(VLOOKUP($A19,'09_Attrition_Tracker'!$B:$G,6,FALSE),TODAY()))-$J19)/30))) -> 39 | Q19: =IF($P19="","",IF($P19<4,"0-3 mos",IF($P19<7,"4-6 mos",IF($P19<13,"7-12 mos",IF($P19<25,"1-2 yrs",IF($P19<61,"2-5 yrs","5+ yrs")))))) -> 2-5 yrs | R19: =IF(OR($L19="Active",$L19="On Leave"),"Yes","No") -> Yes | S19: =IFERROR(VLOOKUP($A19,'09_Attrition_Tracker'!$B:$M,12,FALSE),"No") -> No
A20: EMP-0016 | B20: Patrick Lim | C20: Credit Evaluation | D20: Team C | E20: POS-004 | F20: Credit Analyst | G20: Credit & Risk | H20: Rank and File | I20: Regular | J20: 43851 | K20: 44031 | L20: Active | M20: EMP-0007 | N20: Cebu Branch | O20: Band A | P20: =IF($J20="","",MAX(0,INT((IF(OR($L20="Active",$L20="On Leave"),TODAY(),IFERROR(VLOOKUP($A20,'09_Attrition_Tracker'!$B:$G,6,FALSE),TODAY()))-$J20)/30))) -> 76 | Q20: =IF($P20="","",IF($P20<4,"0-3 mos",IF($P20<7,"4-6 mos",IF($P20<13,"7-12 mos",IF($P20<25,"1-2 yrs",IF($P20<61,"2-5 yrs","5+ yrs")))))) -> 5+ yrs | R20: =IF(OR($L20="Active",$L20="On Leave"),"Yes","No") -> Yes | S20: =IFERROR(VLOOKUP($A20,'09_Attrition_Tracker'!$B:$M,12,FALSE),"No") -> No
A21: EMP-0017 | B21: Carlo Santos | C21: Human Resources | D21: Team D | E21: POS-020 | F21: HR Specialist | G21: HR | H21: Specialist | I21: Regular | J21: 44102 | K21: 44282 | L21: Active | M21: EMP-0015 | N21: Manila Branch | O21: Band A | P21: =IF($J21="","",MAX(0,INT((IF(OR($L21="Active",$L21="On Leave"),TODAY(),IFERROR(VLOOKUP($A21,'09_Attrition_Tracker'!$B:$G,6,FALSE),TODAY()))-$J21)/30))) -> 68 | Q21: =IF($P21="","",IF($P21<4,"0-3 mos",IF($P21<7,"4-6 mos",IF($P21<13,"7-12 mos",IF($P21<25,"1-2 yrs",IF($P21<61,"2-5 yrs","5+ yrs")))))) -> 5+ yrs | R21: =IF(OR($L21="Active",$L21="On Leave"),"Yes","No") -> Yes | S21: =IFERROR(VLOOKUP($A21,'09_Attrition_Tracker'!$B:$M,12,FALSE),"No") -> No
A22: EMP-0018 | B22: Rafael Lim | C22: Compliance | D22: Team C | E22: POS-025 | F22: Compliance Analyst | G22: Compliance | H22: Specialist | I22: Regular | J22: 44496 | K22: 44676 | L22: Resigned | M22: EMP-0002 | N22: Makati Branch | O22: Band A | P22: =IF($J22="","",MAX(0,INT((IF(OR($L22="Active",$L22="On Leave"),TODAY(),IFERROR(VLOOKUP($A22,'09_Attrition_Tracker'!$B:$G,6,FALSE),TODAY()))-$J22)/30))) -> 47 | Q22: =IF($P22="","",IF($P22<4,"0-3 mos",IF($P22<7,"4-6 mos",IF($P22<13,"7-12 mos",IF($P22<25,"1-2 yrs",IF($P22<61,"2-5 yrs","5+ yrs")))))) -> 2-5 yrs | R22: =IF(OR($L22="Active",$L22="On Leave"),"Yes","No") -> No | S22: =IFERROR(VLOOKUP($A22,'09_Attrition_Tracker'!$B:$M,12,FALSE),"No") -> No
A23: EMP-0019 | B23: Gabriel Lim | C23: Compliance | D23: Team B | E23: POS-026 | F23: Compliance Officer | G23: Compliance | H23: Rank and File | I23: Regular | J23: 43705 | L23: Active | M23: EMP-0001 | N23: Davao Branch | O23: Band D | P23: =IF($J23="","",MAX(0,INT((IF(OR($L23="Active",$L23="On Leave"),TODAY(),IFERROR(VLOOKUP($A23,'09_Attrition_Tracker'!$B:$G,6,FALSE),TODAY()))-$J23)/30))) -> 81 | Q23: =IF($P23="","",IF($P23<4,"0-3 mos",IF($P23<7,"4-6 mos",IF($P23<13,"7-12 mos",IF($P23<25,"1-2 yrs",IF($P23<61,"2-5 yrs","5+ yrs")))))) -> 5+ yrs | R23: =IF(OR($L23="Active",$L23="On Leave"),"Yes","No") -> Yes | S23: =IFERROR(VLOOKUP($A23,'09_Attrition_Tracker'!$B:$M,12,FALSE),"No") -> No
A24: EMP-0020 | B24: Ivy Garcia | C24: Sales & Marketing | D24: Team C | E24: POS-013 | F24: Account Officer | G24: Sales | H24: Specialist | I24: Regular | J24: 44302 | K24: 44482 | L24: Active | M24: EMP-0015 | N24: Makati Branch | O24: Band B | P24: =IF($J24="","",MAX(0,INT((IF(OR($L24="Active",$L24="On Leave"),TODAY(),IFERROR(VLOOKUP($A24,'09_Attrition_Tracker'!$B:$G,6,FALSE),TODAY()))-$J24)/30))) -> 61 | Q24: =IF($P24="","",IF($P24<4,"0-3 mos",IF($P24<7,"4-6 mos",IF($P24<13,"7-12 mos",IF($P24<25,"1-2 yrs",IF($P24<61,"2-5 yrs","5+ yrs")))))) -> 5+ yrs | R24: =IF(OR($L24="Active",$L24="On Leave"),"Yes","No") -> Yes | S24: =IFERROR(VLOOKUP($A24,'09_Attrition_Tracker'!$B:$M,12,FALSE),"No") -> No
A25: EMP-0021 | B25: Angela Aquino | C25: Collections | D25: Team D | E25: POS-011 | F25: Collections Officer | G25: Collections | H25: Specialist | I25: Regular | J25: 43020 | K25: 43200 | L25: Active | M25: EMP-0017 | N25: Davao Branch | O25: Band A | P25: =IF($J25="","",MAX(0,INT((IF(OR($L25="Active",$L25="On Leave"),TODAY(),IFERROR(VLOOKUP($A25,'09_Attrition_Tracker'!$B:$G,6,FALSE),TODAY()))-$J25)/30))) -> 104 | Q25: =IF($P25="","",IF($P25<4,"0-3 mos",IF($P25<7,"4-6 mos",IF($P25<13,"7-12 mos",IF($P25<25,"1-2 yrs",IF($P25<61,"2-5 yrs","5+ yrs")))))) -> 5+ yrs | R25: =IF(OR($L25="Active",$L25="On Leave"),"Yes","No") -> Yes | S25: =IFERROR(VLOOKUP($A25,'09_Attrition_Tracker'!$B:$M,12,FALSE),"No") -> No
A26: EMP-0022 | B26: Rhea Aquino | C26: Sales & Marketing | D26: Team D | E26: POS-013 | F26: Account Officer | G26: Sales | H26: Specialist | I26: Regular | J26: 42892 | K26: 43072 | L26: Resigned | M26: EMP-0011 | N26: Manila Branch | O26: Band D | P26: =IF($J26="","",MAX(0,INT((IF(OR($L26="Active",$L26="On Leave"),TODAY(),IFERROR(VLOOKUP($A26,'09_Attrition_Tracker'!$B:$G,6,FALSE),TODAY()))-$J26)/30))) -> 100 | Q26: =IF($P26="","",IF($P26<4,"0-3 mos",IF($P26<7,"4-6 mos",IF($P26<13,"7-12 mos",IF($P26<25,"1-2 yrs",IF($P26<61,"2-5 yrs","5+ yrs")))))) -> 5+ yrs | R26: =IF(OR($L26="Active",$L26="On Leave"),"Yes","No") -> No | S26: =IFERROR(VLOOKUP($A26,'09_Attrition_Tracker'!$B:$M,12,FALSE),"No") -> Yes
A27: EMP-0023 | B27: Ivy Gonzales | C27: Sales & Marketing | D27: Team C | E27: POS-013 | F27: Account Officer | G27: Sales | H27: Rank and File | I27: Regular | J27: 42742 | K27: 42922 | L27: Active | M27: EMP-0003 | N27: Manila Branch | O27: Band C | P27: =IF($J27="","",MAX(0,INT((IF(OR($L27="Active",$L27="On Leave"),TODAY(),IFERROR(VLOOKUP($A27,'09_Attrition_Tracker'!$B:$G,6,FALSE),TODAY()))-$J27)/30))) -> 113 | Q27: =IF($P27="","",IF($P27<4,"0-3 mos",IF($P27<7,"4-6 mos",IF($P27<13,"7-12 mos",IF($P27<25,"1-2 yrs",IF($P27<61,"2-5 yrs","5+ yrs")))))) -> 5+ yrs | R27: =IF(OR($L27="Active",$L27="On Leave"),"Yes","No") -> Yes | S27: =IFERROR(VLOOKUP($A27,'09_Attrition_Tracker'!$B:$M,12,FALSE),"No") -> No
A28: EMP-0024 | B28: Bea Mendoza | C28: Human Resources | D28: Team B | E28: POS-020 | F28: HR Specialist | G28: HR | H28: Specialist | I28: Regular | J28: 45006 | K28: 45186 | L28: Resigned | M28: EMP-0013 | N28: Cebu Branch | O28: Band D | P28: =IF($J28="","",MAX(0,INT((IF(OR($L28="Active",$L28="On Leave"),TODAY(),IFERROR(VLOOKUP($A28,'09_Attrition_Tracker'!$B:$G,6,FALSE),TODAY()))-$J28)/30))) -> 29 | Q28: =IF($P28="","",IF($P28<4,"0-3 mos",IF($P28<7,"4-6 mos",IF($P28<13,"7-12 mos",IF($P28<25,"1-2 yrs",IF($P28<61,"2-5 yrs","5+ yrs")))))) -> 2-5 yrs | R28: =IF(OR($L28="Active",$L28="On Leave"),"Yes","No") -> No | S28: =IFERROR(VLOOKUP($A28,'09_Attrition_Tracker'!$B:$M,12,FALSE),"No") -> Yes
A29: EMP-0025 | B29: Lara Gonzales | C29: Sales & Marketing | D29: Team B | E29: POS-014 | F29: Marketing Associate | G29: Sales | H29: Specialist | I29: Regular | J29: 45954 | K29: 46134 | L29: Active | M29: EMP-0015 | N29: Quezon City Branch | O29: Band A | P29: =IF($J29="","",MAX(0,INT((IF(OR($L29="Active",$L29="On Leave"),TODAY(),IFERROR(VLOOKUP($A29,'09_Attrition_Tracker'!$B:$G,6,FALSE),TODAY()))-$J29)/30))) -> 6 | Q29: =IF($P29="","",IF($P29<4,"0-3 mos",IF($P29<7,"4-6 mos",IF($P29<13,"7-12 mos",IF($P29<25,"1-2 yrs",IF($P29<61,"2-5 yrs","5+ yrs")))))) -> 4-6 mos | R29: =IF(OR($L29="Active",$L29="On Leave"),"Yes","No") -> Yes | S29: =IFERROR(VLOOKUP($A29,'09_Attrition_Tracker'!$B:$M,12,FALSE),"No") -> No
A30: EMP-0026 | B30: Janine Bautista | C30: Compliance | D30: Team C | E30: POS-027 | F30: Compliance Manager | G30: Compliance | H30: Manager | I30: Regular | J30: 43118 | K30: 43298 | L30: Active | N30: Makati Branch | O30: Band B | P30: =IF($J30="","",MAX(0,INT((IF(OR($L30="Active",$L30="On Leave"),TODAY(),IFERROR(VLOOKUP($A30,'09_Attrition_Tracker'!$B:$G,6,FALSE),TODAY()))-$J30)/30))) -> 100 | Q30: =IF($P30="","",IF($P30<4,"0-3 mos",IF($P30<7,"4-6 mos",IF($P30<13,"7-12 mos",IF($P30<25,"1-2 yrs",IF($P30<61,"2-5 yrs","5+ yrs")))))) -> 5+ yrs | R30: =IF(OR($L30="Active",$L30="On Leave"),"Yes","No") -> Yes | S30: =IFERROR(VLOOKUP($A30,'09_Attrition_Tracker'!$B:$M,12,FALSE),"No") -> No
A31: EMP-0027 | B31: Julius Cruz | C31: Branch Operations | D31: Team D | E31: POS-001 | F31: Branch Associate | G31: Operations | H31: Rank and File | I31: Regular | J31: 44601 | K31: 44781 | L31: Active | M31: EMP-0013 | N31: Quezon City Branch | O31: Band A | P31: =IF($J31="","",MAX(0,INT((IF(OR($L31="Active",$L31="On Leave"),TODAY(),IFERROR(VLOOKUP($A31,'09_Attrition_Tracker'!$B:$G,6,FALSE),TODAY()))-$J31)/30))) -> 51 | Q31: =IF($P31="","",IF($P31<4,"0-3 mos",IF($P31<7,"4-6 mos",IF($P31<13,"7-12 mos",IF($P31<25,"1-2 yrs",IF($P31<61,"2-5 yrs","5+ yrs")))))) -> 2-5 yrs | R31: =IF(OR($L31="Active",$L31="On Leave"),"Yes","No") -> Yes | S31: =IFERROR(VLOOKUP($A31,'09_Attrition_Tracker'!$B:$M,12,FALSE),"No") -> No
A32: EMP-0028 | B32: Paolo Villanueva | C32: Human Resources | D32: Team D | E32: POS-019 | F32: HR Assistant | G32: HR | H32: Rank and File | I32: Regular | J32: 42941 | K32: 43121 | L32: Active | M32: EMP-0026 | N32: Davao Branch | O32: Band D | P32: =IF($J32="","",MAX(0,INT((IF(OR($L32="Active",$L32="On Leave"),TODAY(),IFERROR(VLOOKUP($A32,'09_Attrition_Tracker'!$B:$G,6,FALSE),TODAY()))-$J32)/30))) -> 106 | Q32: =IF($P32="","",IF($P32<4,"0-3 mos",IF($P32<7,"4-6 mos",IF($P32<13,"7-12 mos",IF($P32<25,"1-2 yrs",IF($P32<61,"2-5 yrs","5+ yrs")))))) -> 5+ yrs | R32: =IF(OR($L32="Active",$L32="On Leave"),"Yes","No") -> Yes | S32: =IFERROR(VLOOKUP($A32,'09_Attrition_Tracker'!$B:$M,12,FALSE),"No") -> No
A33: EMP-0029 | B33: Paolo Lopez | C33: Compliance | D33: Team D | E33: POS-026 | F33: Compliance Officer | G33: Compliance | H33: Rank and File | I33: Regular | J33: 44579 | K33: 44759 | L33: Active | M33: EMP-0009 | N33: Cebu Branch | O33: Band D | P33: =IF($J33="","",MAX(0,INT((IF(OR($L33="Active",$L33="On Leave"),TODAY(),IFERROR(VLOOKUP($A33,'09_Attrition_Tracker'!$B:$G,6,FALSE),TODAY()))-$J33)/30))) -> 52 | Q33: =IF($P33="","",IF($P33<4,"0-3 mos",IF($P33<7,"4-6 mos",IF($P33<13,"7-12 mos",IF($P33<25,"1-2 yrs",IF($P33<61,"2-5 yrs","5+ yrs")))))) -> 2-5 yrs | R33: =IF(OR($L33="Active",$L33="On Leave"),"Yes","No") -> Yes | S33: =IFERROR(VLOOKUP($A33,'09_Attrition_Tracker'!$B:$M,12,FALSE),"No") -> No
A34: EMP-0030 | B34: Diana Bautista | C34: Sales & Marketing | D34: Team D | E34: POS-013 | F34: Account Officer | G34: Sales | H34: Rank and File | I34: Regular | J34: 44045 | K34: 44225 | L34: Active | M34: EMP-0008 | N34: Makati Branch | O34: Band A | P34: =IF($J34="","",MAX(0,INT((IF(OR($L34="Active",$L34="On Leave"),TODAY(),IFERROR(VLOOKUP($A34,'09_Attrition_Tracker'!$B:$G,6,FALSE),TODAY()))-$J34)/30))) -> 70 | Q34: =IF($P34="","",IF($P34<4,"0-3 mos",IF($P34<7,"4-6 mos",IF($P34<13,"7-12 mos",IF($P34<25,"1-2 yrs",IF($P34<61,"2-5 yrs","5+ yrs")))))) -> 5+ yrs | R34: =IF(OR($L34="Active",$L34="On Leave"),"Yes","No") -> Yes | S34: =IFERROR(VLOOKUP($A34,'09_Attrition_Tracker'!$B:$M,12,FALSE),"No") -> No
A35: EMP-0031 | B35: Ethan Villanueva | C35: Human Resources | D35: Team A | E35: POS-020 | F35: HR Specialist | G35: HR | H35: Specialist | I35: Probationary | J35: 44439 | K35: 44619 | L35: Resigned | M35: EMP-0025 | N35: Baguio Branch | O35: Band D | P35: =IF($J35="","",MAX(0,INT((IF(OR($L35="Active",$L35="On Leave"),TODAY(),IFERROR(VLOOKUP($A35,'09_Attrition_Tracker'!$B:$G,6,FALSE),TODAY()))-$J35)/30))) -> 48 | Q35: =IF($P35="","",IF($P35<4,"0-3 mos",IF($P35<7,"4-6 mos",IF($P35<13,"7-12 mos",IF($P35<25,"1-2 yrs",IF($P35<61,"2-5 yrs","5+ yrs")))))) -> 2-5 yrs | R35: =IF(OR($L35="Active",$L35="On Leave"),"Yes","No") -> No | S35: =IFERROR(VLOOKUP($A35,'09_Attrition_Tracker'!$B:$M,12,FALSE),"No") -> No
A36: EMP-0032 | B36: Bea Gonzales | C36: Finance | D36: Team D | E36: POS-017 | F36: Finance Analyst | G36: Finance | H36: Rank and File | I36: Regular | J36: 44940 | K36: 45120 | L36: Active | M36: EMP-0018 | N36: Baguio Branch | O36: Band C | P36: =IF($J36="","",MAX(0,INT((IF(OR($L36="Active",$L36="On Leave"),TODAY(),IFERROR(VLOOKUP($A36,'09_Attrition_Tracker'!$B:$G,6,FALSE),TODAY()))-$J36)/30))) -> 40 | Q36: =IF($P36="","",IF($P36<4,"0-3 mos",IF($P36<7,"4-6 mos",IF($P36<13,"7-12 mos",IF($P36<25,"1-2 yrs",IF($P36<61,"2-5 yrs","5+ yrs")))))) -> 2-5 yrs | R36: =IF(OR($L36="Active",$L36="On Leave"),"Yes","No") -> Yes | S36: =IFERROR(VLOOKUP($A36,'09_Attrition_Tracker'!$B:$M,12,FALSE),"No") -> No
A37: EMP-0033 | B37: Maria Santos | C37: Loan Processing | D37: Team B | E37: POS-008 | F37: Processing Specialist | G37: Operations | H37: Rank and File | I37: Probationary | J37: 44349 | K37: 44529 | L37: Active | M37: EMP-0028 | N37: Quezon City Branch | O37: Band A | P37: =IF($J37="","",MAX(0,INT((IF(OR($L37="Active",$L37="On Leave"),TODAY(),IFERROR(VLOOKUP($A37,'09_Attrition_Tracker'!$B:$G,6,FALSE),TODAY()))-$J37)/30))) -> 59 | Q37: =IF($P37="","",IF($P37<4,"0-3 mos",IF($P37<7,"4-6 mos",IF($P37<13,"7-12 mos",IF($P37<25,"1-2 yrs",IF($P37<61,"2-5 yrs","5+ yrs")))))) -> 2-5 yrs | R37: =IF(OR($L37="Active",$L37="On Leave"),"Yes","No") -> Yes | S37: =IFERROR(VLOOKUP($A37,'09_Attrition_Tracker'!$B:$M,12,FALSE),"No") -> No
A38: EMP-0034 | B38: Lara Villanueva | C38: Human Resources | D38: Team C | E38: POS-020 | F38: HR Specialist | G38: HR | H38: Specialist | I38: Probationary | J38: 44074 | K38: 44254 | L38: Active | M38: EMP-0027 | N38: Iloilo Branch | O38: Band A | P38: =IF($J38="","",MAX(0,INT((IF(OR($L38="Active",$L38="On Leave"),TODAY(),IFERROR(VLOOKUP($A38,'09_Attrition_Tracker'!$B:$G,6,FALSE),TODAY()))-$J38)/30))) -> 69 | Q38: =IF($P38="","",IF($P38<4,"0-3 mos",IF($P38<7,"4-6 mos",IF($P38<13,"7-12 mos",IF($P38<25,"1-2 yrs",IF($P38<61,"2-5 yrs","5+ yrs")))))) -> 5+ yrs | R38: =IF(OR($L38="Active",$L38="On Leave"),"Yes","No") -> Yes | S38: =IFERROR(VLOOKUP($A38,'09_Attrition_Tracker'!$B:$M,12,FALSE),"No") -> No
A39: EMP-0035 | B39: Janine Cruz | C39: Finance | D39: Team B | E39: POS-016 | F39: Accounting Associate | G39: Finance | H39: Rank and File | I39: Probationary | J39: 45935 | K39: 46115 | L39: Active | M39: EMP-0016 | N39: Quezon City Branch | O39: Band B | P39: =IF($J39="","",MAX(0,INT((IF(OR($L39="Active",$L39="On Leave"),TODAY(),IFERROR(VLOOKUP($A39,'09_Attrition_Tracker'!$B:$G,6,FALSE),TODAY()))-$J39)/30))) -> 7 | Q39: =IF($P39="","",IF($P39<4,"0-3 mos",IF($P39<7,"4-6 mos",IF($P39<13,"7-12 mos",IF($P39<25,"1-2 yrs",IF($P39<61,"2-5 yrs","5+ yrs")))))) -> 7-12 mos | R39: =IF(OR($L39="Active",$L39="On Leave"),"Yes","No") -> Yes | S39: =IFERROR(VLOOKUP($A39,'09_Attrition_Tracker'!$B:$M,12,FALSE),"No") -> No
A40: EMP-0036 | B40: Jose Ramos | C40: Information Technology | D40: Team B | E40: POS-024 | F40: IT Manager | G40: IT | H40: Manager | I40: Regular | J40: 44640 | K40: 44820 | L40: Active | N40: Manila Branch | O40: Band B | P40: =IF($J40="","",MAX(0,INT((IF(OR($L40="Active",$L40="On Leave"),TODAY(),IFERROR(VLOOKUP($A40,'09_Attrition_Tracker'!$B:$G,6,FALSE),TODAY()))-$J40)/30))) -> 50 | Q40: =IF($P40="","",IF($P40<4,"0-3 mos",IF($P40<7,"4-6 mos",IF($P40<13,"7-12 mos",IF($P40<25,"1-2 yrs",IF($P40<61,"2-5 yrs","5+ yrs")))))) -> 2-5 yrs | R40: =IF(OR($L40="Active",$L40="On Leave"),"Yes","No") -> Yes | S40: =IFERROR(VLOOKUP($A40,'09_Attrition_Tracker'!$B:$M,12,FALSE),"No") -> No
A41: EMP-0037 | B41: Mika Mendoza | C41: Credit Evaluation | D41: Team B | E41: POS-006 | F41: Credit Supervisor | G41: Credit & Risk | H41: Supervisor | I41: Regular | J41: 45094 | L41: Active | M41: EMP-0026 | N41: Makati Branch | O41: Band A | P41: =IF($J41="","",MAX(0,INT((IF(OR($L41="Active",$L41="On Leave"),TODAY(),IFERROR(VLOOKUP($A41,'09_Attrition_Tracker'!$B:$G,6,FALSE),TODAY()))-$J41)/30))) -> 35 | Q41: =IF($P41="","",IF($P41<4,"0-3 mos",IF($P41<7,"4-6 mos",IF($P41<13,"7-12 mos",IF($P41<25,"1-2 yrs",IF($P41<61,"2-5 yrs","5+ yrs")))))) -> 2-5 yrs | R41: =IF(OR($L41="Active",$L41="On Leave"),"Yes","No") -> Yes | S41: =IFERROR(VLOOKUP($A41,'09_Attrition_Tracker'!$B:$M,12,FALSE),"No") -> No
A42: EMP-0038 | B42: Rhea Reyes | C42: Customer Service | D42: Team A | E42: POS-028 | F42: Customer Support Associate | G42: Service | H42: Specialist | I42: Probationary | J42: 44158 | K42: 44338 | L42: Active | M42: EMP-0022 | N42: Iloilo Branch | O42: Band A | P42: =IF($J42="","",MAX(0,INT((IF(OR($L42="Active",$L42="On Leave"),TODAY(),IFERROR(VLOOKUP($A42,'09_Attrition_Tracker'!$B:$G,6,FALSE),TODAY()))-$J42)/30))) -> 66 | Q42: =IF($P42="","",IF($P42<4,"0-3 mos",IF($P42<7,"4-6 mos",IF($P42<13,"7-12 mos",IF($P42<25,"1-2 yrs",IF($P42<61,"2-5 yrs","5+ yrs")))))) -> 5+ yrs | R42: =IF(OR($L42="Active",$L42="On Leave"),"Yes","No") -> Yes | S42: =IFERROR(VLOOKUP($A42,'09_Attrition_Tracker'!$B:$M,12,FALSE),"No") -> No
A43: EMP-0039 | B43: Sofia Lim | C43: Finance | D43: Team C | E43: POS-018 | F43: Finance Manager | G43: Finance | H43: Manager | I43: Regular | J43: 44519 | K43: 44699 | L43: On Leave | N43: Iloilo Branch | O43: Band D | P43: =IF($J43="","",MAX(0,INT((IF(OR($L43="Active",$L43="On Leave"),TODAY(),IFERROR(VLOOKUP($A43,'09_Attrition_Tracker'!$B:$G,6,FALSE),TODAY()))-$J43)/30))) -> 54 | Q43: =IF($P43="","",IF($P43<4,"0-3 mos",IF($P43<7,"4-6 mos",IF($P43<13,"7-12 mos",IF($P43<25,"1-2 yrs",IF($P43<61,"2-5 yrs","5+ yrs")))))) -> 2-5 yrs | R43: =IF(OR($L43="Active",$L43="On Leave"),"Yes","No") -> Yes | S43: =IFERROR(VLOOKUP($A43,'09_Attrition_Tracker'!$B:$M,12,FALSE),"No") -> No
A44: EMP-0040 | B44: Angela Torres | C44: Customer Service | D44: Team D | E44: POS-029 | F44: Customer Care Officer | G44: Service | H44: Specialist | I44: Regular | J44: 43090 | K44: 43270 | L44: Active | M44: EMP-0030 | N44: Iloilo Branch | O44: Band C | P44: =IF($J44="","",MAX(0,INT((IF(OR($L44="Active",$L44="On Leave"),TODAY(),IFERROR(VLOOKUP($A44,'09_Attrition_Tracker'!$B:$G,6,FALSE),TODAY()))-$J44)/30))) -> 101 | Q44: =IF($P44="","",IF($P44<4,"0-3 mos",IF($P44<7,"4-6 mos",IF($P44<13,"7-12 mos",IF($P44<25,"1-2 yrs",IF($P44<61,"2-5 yrs","5+ yrs")))))) -> 5+ yrs | R44: =IF(OR($L44="Active",$L44="On Leave"),"Yes","No") -> Yes | S44: =IFERROR(VLOOKUP($A44,'09_Attrition_Tracker'!$B:$M,12,FALSE),"No") -> No
A45: EMP-0041 | B45: Rafael Aquino | C45: Information Technology | D45: Team B | E45: POS-022 | F45: IT Support Specialist | G45: IT | H45: Specialist | I45: Regular | J45: 44130 | K45: 44310 | L45: Active | M45: EMP-0034 | N45: Baguio Branch | O45: Band D | P45: =IF($J45="","",MAX(0,INT((IF(OR($L45="Active",$L45="On Leave"),TODAY(),IFERROR(VLOOKUP($A45,'09_Attrition_Tracker'!$B:$G,6,FALSE),TODAY()))-$J45)/30))) -> 67 | Q45: =IF($P45="","",IF($P45<4,"0-3 mos",IF($P45<7,"4-6 mos",IF($P45<13,"7-12 mos",IF($P45<25,"1-2 yrs",IF($P45<61,"2-5 yrs","5+ yrs")))))) -> 5+ yrs | R45: =IF(OR($L45="Active",$L45="On Leave"),"Yes","No") -> Yes | S45: =IFERROR(VLOOKUP($A45,'09_Attrition_Tracker'!$B:$M,12,FALSE),"No") -> No
A46: EMP-0042 | B46: Ivy Lopez | C46: Information Technology | D46: Team B | E46: POS-024 | F46: IT Manager | G46: IT | H46: Manager | I46: Regular | J46: 44571 | K46: 44751 | L46: Active | N46: Makati Branch | O46: Band C | P46: =IF($J46="","",MAX(0,INT((IF(OR($L46="Active",$L46="On Leave"),TODAY(),IFERROR(VLOOKUP($A46,'09_Attrition_Tracker'!$B:$G,6,FALSE),TODAY()))-$J46)/30))) -> 52 | Q46: =IF($P46="","",IF($P46<4,"0-3 mos",IF($P46<7,"4-6 mos",IF($P46<13,"7-12 mos",IF($P46<25,"1-2 yrs",IF($P46<61,"2-5 yrs","5+ yrs")))))) -> 2-5 yrs | R46: =IF(OR($L46="Active",$L46="On Leave"),"Yes","No") -> Yes | S46: =IFERROR(VLOOKUP($A46,'09_Attrition_Tracker'!$B:$M,12,FALSE),"No") -> No
A47: EMP-0043 | B47: Camille Navarro | C47: Information Technology | D47: Team C | E47: POS-024 | F47: IT Manager | G47: IT | H47: Manager | I47: Regular | J47: 44478 | K47: 44658 | L47: Active | N47: Cebu Branch | O47: Band C | P47: =IF($J47="","",MAX(0,INT((IF(OR($L47="Active",$L47="On Leave"),TODAY(),IFERROR(VLOOKUP($A47,'09_Attrition_Tracker'!$B:$G,6,FALSE),TODAY()))-$J47)/30))) -> 55 | Q47: =IF($P47="","",IF($P47<4,"0-3 mos",IF($P47<7,"4-6 mos",IF($P47<13,"7-12 mos",IF($P47<25,"1-2 yrs",IF($P47<61,"2-5 yrs","5+ yrs")))))) -> 2-5 yrs | R47: =IF(OR($L47="Active",$L47="On Leave"),"Yes","No") -> Yes | S47: =IFERROR(VLOOKUP($A47,'09_Attrition_Tracker'!$B:$M,12,FALSE),"No") -> No
A48: EMP-0044 | B48: Patrick Ramos | C48: Collections | D48: Team C | E48: POS-010 | F48: Collections Associate | G48: Collections | H48: Rank and File | I48: Regular | J48: 44028 | K48: 44208 | L48: Resigned | M48: EMP-0031 | N48: Cebu Branch | O48: Band A | P48: =IF($J48="","",MAX(0,INT((IF(OR($L48="Active",$L48="On Leave"),TODAY(),IFERROR(VLOOKUP($A48,'09_Attrition_Tracker'!$B:$G,6,FALSE),TODAY()))-$J48)/30))) -> 68 | Q48: =IF($P48="","",IF($P48<4,"0-3 mos",IF($P48<7,"4-6 mos",IF($P48<13,"7-12 mos",IF($P48<25,"1-2 yrs",IF($P48<61,"2-5 yrs","5+ yrs")))))) -> 5+ yrs | R48: =IF(OR($L48="Active",$L48="On Leave"),"Yes","No") -> No | S48: =IFERROR(VLOOKUP($A48,'09_Attrition_Tracker'!$B:$M,12,FALSE),"No") -> No
A49: EMP-0045 | B49: Rafael Dela Cruz | C49: Sales & Marketing | D49: Team C | E49: POS-013 | F49: Account Officer | G49: Sales | H49: Rank and File | I49: Regular | J49: 43974 | K49: 44154 | L49: Resigned | M49: EMP-0004 | N49: Quezon City Branch | O49: Band D | P49: =IF($J49="","",MAX(0,INT((IF(OR($L49="Active",$L49="On Leave"),TODAY(),IFERROR(VLOOKUP($A49,'09_Attrition_Tracker'!$B:$G,6,FALSE),TODAY()))-$J49)/30))) -> 58 | Q49: =IF($P49="","",IF($P49<4,"0-3 mos",IF($P49<7,"4-6 mos",IF($P49<13,"7-12 mos",IF($P49<25,"1-2 yrs",IF($P49<61,"2-5 yrs","5+ yrs")))))) -> 2-5 yrs | R49: =IF(OR($L49="Active",$L49="On Leave"),"Yes","No") -> No | S49: =IFERROR(VLOOKUP($A49,'09_Attrition_Tracker'!$B:$M,12,FALSE),"No") -> No
A50: EMP-0046 | B50: Luis Lopez | C50: Branch Operations | D50: Team A | E50: POS-003 | F50: Branch Manager | G50: Operations | H50: Manager | I50: Regular | J50: 44696 | K50: 44876 | L50: Active | N50: Iloilo Branch | O50: Band A | P50: =IF($J50="","",MAX(0,INT((IF(OR($L50="Active",$L50="On Leave"),TODAY(),IFERROR(VLOOKUP($A50,'09_Attrition_Tracker'!$B:$G,6,FALSE),TODAY()))-$J50)/30))) -> 48 | Q50: =IF($P50="","",IF($P50<4,"0-3 mos",IF($P50<7,"4-6 mos",IF($P50<13,"7-12 mos",IF($P50<25,"1-2 yrs",IF($P50<61,"2-5 yrs","5+ yrs")))))) -> 2-5 yrs | R50: =IF(OR($L50="Active",$L50="On Leave"),"Yes","No") -> Yes | S50: =IFERROR(VLOOKUP($A50,'09_Attrition_Tracker'!$B:$M,12,FALSE),"No") -> No
A51: EMP-0047 | B51: Andrea Reyes | C51: Human Resources | D51: Team A | E51: POS-020 | F51: HR Specialist | G51: HR | H51: Specialist | I51: Regular | J51: 43357 | K51: 43537 | L51: Terminated | M51: EMP-0016 | N51: Baguio Branch | O51: Band E | P51: =IF($J51="","",MAX(0,INT((IF(OR($L51="Active",$L51="On Leave"),TODAY(),IFERROR(VLOOKUP($A51,'09_Attrition_Tracker'!$B:$G,6,FALSE),TODAY()))-$J51)/30))) -> 84 | Q51: =IF($P51="","",IF($P51<4,"0-3 mos",IF($P51<7,"4-6 mos",IF($P51<13,"7-12 mos",IF($P51<25,"1-2 yrs",IF($P51<61,"2-5 yrs","5+ yrs")))))) -> 5+ yrs | R51: =IF(OR($L51="Active",$L51="On Leave"),"Yes","No") -> No | S51: =IFERROR(VLOOKUP($A51,'09_Attrition_Tracker'!$B:$M,12,FALSE),"No") -> Yes
A52: EMP-0048 | B52: Sofia Villanueva | C52: Compliance | D52: Team A | E52: POS-026 | F52: Compliance Officer | G52: Compliance | H52: Specialist | I52: Regular | J52: 43953 | K52: 44133 | L52: Active | M52: EMP-0040 | N52: Manila Branch | O52: Band B | P52: =IF($J52="","",MAX(0,INT((IF(OR($L52="Active",$L52="On Leave"),TODAY(),IFERROR(VLOOKUP($A52,'09_Attrition_Tracker'!$B:$G,6,FALSE),TODAY()))-$J52)/30))) -> 73 | Q52: =IF($P52="","",IF($P52<4,"0-3 mos",IF($P52<7,"4-6 mos",IF($P52<13,"7-12 mos",IF($P52<25,"1-2 yrs",IF($P52<61,"2-5 yrs","5+ yrs")))))) -> 5+ yrs | R52: =IF(OR($L52="Active",$L52="On Leave"),"Yes","No") -> Yes | S52: =IFERROR(VLOOKUP($A52,'09_Attrition_Tracker'!$B:$M,12,FALSE),"No") -> No
A53: EMP-0049 | B53: Andrea Dela Cruz | C53: Sales & Marketing | D53: Team A | E53: POS-015 | F53: Sales Manager | G53: Sales | H53: Manager | I53: Regular | J53: 43718 | K53: 43898 | L53: On Leave | N53: Iloilo Branch | O53: Band C | P53: =IF($J53="","",MAX(0,INT((IF(OR($L53="Active",$L53="On Leave"),TODAY(),IFERROR(VLOOKUP($A53,'09_Attrition_Tracker'!$B:$G,6,FALSE),TODAY()))-$J53)/30))) -> 80 | Q53: =IF($P53="","",IF($P53<4,"0-3 mos",IF($P53<7,"4-6 mos",IF($P53<13,"7-12 mos",IF($P53<25,"1-2 yrs",IF($P53<61,"2-5 yrs","5+ yrs")))))) -> 5+ yrs | R53: =IF(OR($L53="Active",$L53="On Leave"),"Yes","No") -> Yes | S53: =IFERROR(VLOOKUP($A53,'09_Attrition_Tracker'!$B:$M,12,FALSE),"No") -> No
A54: EMP-0050 | B54: Ivy Mendoza | C54: Collections | D54: Team B | E54: POS-011 | F54: Collections Officer | G54: Collections | H54: Rank and File | I54: Regular | J54: 45615 | K54: 45795 | L54: Active | M54: EMP-0017 | N54: Makati Branch | O54: Band B | P54: =IF($J54="","",MAX(0,INT((IF(OR($L54="Active",$L54="On Leave"),TODAY(),IFERROR(VLOOKUP($A54,'09_Attrition_Tracker'!$B:$G,6,FALSE),TODAY()))-$J54)/30))) -> 17 | Q54: =IF($P54="","",IF($P54<4,"0-3 mos",IF($P54<7,"4-6 mos",IF($P54<13,"7-12 mos",IF($P54<25,"1-2 yrs",IF($P54<61,"2-5 yrs","5+ yrs")))))) -> 1-2 yrs | R54: =IF(OR($L54="Active",$L54="On Leave"),"Yes","No") -> Yes | S54: =IFERROR(VLOOKUP($A54,'09_Attrition_Tracker'!$B:$M,12,FALSE),"No") -> No
A55: EMP-0051 | B55: Carlo Dela Cruz | C55: Loan Processing | D55: Team C | E55: POS-007 | F55: Loan Processor | G55: Operations | H55: Specialist | I55: Regular | J55: 45982 | K55: 46162 | L55: Active | M55: EMP-0030 | N55: Cebu Branch | O55: Band E | P55: =IF($J55="","",MAX(0,INT((IF(OR($L55="Active",$L55="On Leave"),TODAY(),IFERROR(VLOOKUP($A55,'09_Attrition_Tracker'!$B:$G,6,FALSE),TODAY()))-$J55)/30))) -> 5 | Q55: =IF($P55="","",IF($P55<4,"0-3 mos",IF($P55<7,"4-6 mos",IF($P55<13,"7-12 mos",IF($P55<25,"1-2 yrs",IF($P55<61,"2-5 yrs","5+ yrs")))))) -> 4-6 mos | R55: =IF(OR($L55="Active",$L55="On Leave"),"Yes","No") -> Yes | S55: =IFERROR(VLOOKUP($A55,'09_Attrition_Tracker'!$B:$M,12,FALSE),"No") -> No
A56: EMP-0052 | B56: Gabriel Reyes | C56: Information Technology | D56: Team A | E56: POS-022 | F56: IT Support Specialist | G56: IT | H56: Specialist | I56: Project-based | J56: 44505 | K56: 44685 | L56: Active | M56: EMP-0015 | N56: Cebu Branch | O56: Band E | P56: =IF($J56="","",MAX(0,INT((IF(OR($L56="Active",$L56="On Leave"),TODAY(),IFERROR(VLOOKUP($A56,'09_Attrition_Tracker'!$B:$G,6,FALSE),TODAY()))-$J56)/30))) -> 54 | Q56: =IF($P56="","",IF($P56<4,"0-3 mos",IF($P56<7,"4-6 mos",IF($P56<13,"7-12 mos",IF($P56<25,"1-2 yrs",IF($P56<61,"2-5 yrs","5+ yrs")))))) -> 2-5 yrs | R56: =IF(OR($L56="Active",$L56="On Leave"),"Yes","No") -> Yes | S56: =IFERROR(VLOOKUP($A56,'09_Attrition_Tracker'!$B:$M,12,FALSE),"No") -> No
A57: EMP-0053 | B57: Camille Villanueva | C57: Loan Processing | D57: Team A | E57: POS-008 | F57: Processing Specialist | G57: Operations | H57: Specialist | I57: Regular | J57: 43875 | K57: 44055 | L57: On Leave | M57: EMP-0032 | N57: Baguio Branch | O57: Band C | P57: =IF($J57="","",MAX(0,INT((IF(OR($L57="Active",$L57="On Leave"),TODAY(),IFERROR(VLOOKUP($A57,'09_Attrition_Tracker'!$B:$G,6,FALSE),TODAY()))-$J57)/30))) -> 75 | Q57: =IF($P57="","",IF($P57<4,"0-3 mos",IF($P57<7,"4-6 mos",IF($P57<13,"7-12 mos",IF($P57<25,"1-2 yrs",IF($P57<61,"2-5 yrs","5+ yrs")))))) -> 5+ yrs | R57: =IF(OR($L57="Active",$L57="On Leave"),"Yes","No") -> Yes | S57: =IFERROR(VLOOKUP($A57,'09_Attrition_Tracker'!$B:$M,12,FALSE),"No") -> No
A58: EMP-0054 | B58: Angela Gonzales | C58: Credit Evaluation | D58: Team A | E58: POS-004 | F58: Credit Analyst | G58: Credit & Risk | H58: Specialist | I58: Regular | J58: 45577 | K58: 45757 | L58: Active | M58: EMP-0036 | N58: Davao Branch | O58: Band C | P58: =IF($J58="","",MAX(0,INT((IF(OR($L58="Active",$L58="On Leave"),TODAY(),IFERROR(VLOOKUP($A58,'09_Attrition_Tracker'!$B:$G,6,FALSE),TODAY()))-$J58)/30))) -> 18 | Q58: =IF($P58="","",IF($P58<4,"0-3 mos",IF($P58<7,"4-6 mos",IF($P58<13,"7-12 mos",IF($P58<25,"1-2 yrs",IF($P58<61,"2-5 yrs","5+ yrs")))))) -> 1-2 yrs | R58: =IF(OR($L58="Active",$L58="On Leave"),"Yes","No") -> Yes | S58: =IFERROR(VLOOKUP($A58,'09_Attrition_Tracker'!$B:$M,12,FALSE),"No") -> No
A59: EMP-0055 | B59: Camille Santos | C59: Credit Evaluation | D59: Team C | E59: POS-005 | F59: Senior Credit Analyst | G59: Credit & Risk | H59: Specialist | I59: Regular | J59: 45429 | K59: 45609 | L59: Active | M59: EMP-0013 | N59: Iloilo Branch | O59: Band D | P59: =IF($J59="","",MAX(0,INT((IF(OR($L59="Active",$L59="On Leave"),TODAY(),IFERROR(VLOOKUP($A59,'09_Attrition_Tracker'!$B:$G,6,FALSE),TODAY()))-$J59)/30))) -> 23 | Q59: =IF($P59="","",IF($P59<4,"0-3 mos",IF($P59<7,"4-6 mos",IF($P59<13,"7-12 mos",IF($P59<25,"1-2 yrs",IF($P59<61,"2-5 yrs","5+ yrs")))))) -> 1-2 yrs | R59: =IF(OR($L59="Active",$L59="On Leave"),"Yes","No") -> Yes | S59: =IFERROR(VLOOKUP($A59,'09_Attrition_Tracker'!$B:$M,12,FALSE),"No") -> No
A60: EMP-0056 | B60: Ethan Lim | C60: Collections | D60: Team B | E60: POS-011 | F60: Collections Officer | G60: Collections | H60: Specialist | I60: Regular | J60: 43915 | K60: 44095 | L60: Active | M60: EMP-0041 | N60: Cebu Branch | O60: Band E | P60: =IF($J60="","",MAX(0,INT((IF(OR($L60="Active",$L60="On Leave"),TODAY(),IFERROR(VLOOKUP($A60,'09_Attrition_Tracker'!$B:$G,6,FALSE),TODAY()))-$J60)/30))) -> 74 | Q60: =IF($P60="","",IF($P60<4,"0-3 mos",IF($P60<7,"4-6 mos",IF($P60<13,"7-12 mos",IF($P60<25,"1-2 yrs",IF($P60<61,"2-5 yrs","5+ yrs")))))) -> 5+ yrs | R60: =IF(OR($L60="Active",$L60="On Leave"),"Yes","No") -> Yes | S60: =IFERROR(VLOOKUP($A60,'09_Attrition_Tracker'!$B:$M,12,FALSE),"No") -> No
A61: EMP-0057 | B61: Andrea Torres | C61: Compliance | D61: Team D | E61: POS-026 | F61: Compliance Officer | G61: Compliance | H61: Rank and File | I61: Contractual | J61: 43200 | K61: 43380 | L61: Active | M61: EMP-0010 | N61: Cebu Branch | O61: Band E | P61: =IF($J61="","",MAX(0,INT((IF(OR($L61="Active",$L61="On Leave"),TODAY(),IFERROR(VLOOKUP($A61,'09_Attrition_Tracker'!$B:$G,6,FALSE),TODAY()))-$J61)/30))) -> 98 | Q61: =IF($P61="","",IF($P61<4,"0-3 mos",IF($P61<7,"4-6 mos",IF($P61<13,"7-12 mos",IF($P61<25,"1-2 yrs",IF($P61<61,"2-5 yrs","5+ yrs")))))) -> 5+ yrs | R61: =IF(OR($L61="Active",$L61="On Leave"),"Yes","No") -> Yes | S61: =IFERROR(VLOOKUP($A61,'09_Attrition_Tracker'!$B:$M,12,FALSE),"No") -> No
A62: EMP-0058 | B62: Julius Torres | C62: Human Resources | D62: Team B | E62: POS-020 | F62: HR Specialist | G62: HR | H62: Specialist | I62: Probationary | J62: 44606 | K62: 44786 | L62: Active | M62: EMP-0039 | N62: Cebu Branch | O62: Band D | P62: =IF($J62="","",MAX(0,INT((IF(OR($L62="Active",$L62="On Leave"),TODAY(),IFERROR(VLOOKUP($A62,'09_Attrition_Tracker'!$B:$G,6,FALSE),TODAY()))-$J62)/30))) -> 51 | Q62: =IF($P62="","",IF($P62<4,"0-3 mos",IF($P62<7,"4-6 mos",IF($P62<13,"7-12 mos",IF($P62<25,"1-2 yrs",IF($P62<61,"2-5 yrs","5+ yrs")))))) -> 2-5 yrs | R62: =IF(OR($L62="Active",$L62="On Leave"),"Yes","No") -> Yes | S62: =IFERROR(VLOOKUP($A62,'09_Attrition_Tracker'!$B:$M,12,FALSE),"No") -> No
A63: EMP-0059 | B63: Mika Mendoza | C63: Compliance | D63: Team D | E63: POS-026 | F63: Compliance Officer | G63: Compliance | H63: Specialist | I63: Regular | J63: 45709 | L63: Active | M63: EMP-0029 | N63: Baguio Branch | O63: Band D | P63: =IF($J63="","",MAX(0,INT((IF(OR($L63="Active",$L63="On Leave"),TODAY(),IFERROR(VLOOKUP($A63,'09_Attrition_Tracker'!$B:$G,6,FALSE),TODAY()))-$J63)/30))) -> 14 | Q63: =IF($P63="","",IF($P63<4,"0-3 mos",IF($P63<7,"4-6 mos",IF($P63<13,"7-12 mos",IF($P63<25,"1-2 yrs",IF($P63<61,"2-5 yrs","5+ yrs")))))) -> 1-2 yrs | R63: =IF(OR($L63="Active",$L63="On Leave"),"Yes","No") -> Yes | S63: =IFERROR(VLOOKUP($A63,'09_Attrition_Tracker'!$B:$M,12,FALSE),"No") -> No
A64: EMP-0060 | B64: Nico Castillo | C64: Collections | D64: Team D | E64: POS-012 | F64: Collections Supervisor | G64: Collections | H64: Supervisor | I64: Regular | J64: 43692 | K64: 43872 | L64: Active | M64: EMP-0021 | N64: Baguio Branch | O64: Band D | P64: =IF($J64="","",MAX(0,INT((IF(OR($L64="Active",$L64="On Leave"),TODAY(),IFERROR(VLOOKUP($A64,'09_Attrition_Tracker'!$B:$G,6,FALSE),TODAY()))-$J64)/30))) -> 81 | Q64: =IF($P64="","",IF($P64<4,"0-3 mos",IF($P64<7,"4-6 mos",IF($P64<13,"7-12 mos",IF($P64<25,"1-2 yrs",IF($P64<61,"2-5 yrs","5+ yrs")))))) -> 5+ yrs | R64: =IF(OR($L64="Active",$L64="On Leave"),"Yes","No") -> Yes | S64: =IFERROR(VLOOKUP($A64,'09_Attrition_Tracker'!$B:$M,12,FALSE),"No") -> No
A65: EMP-0061 | B65: Maria Bautista | C65: Information Technology | D65: Team A | E65: POS-022 | F65: IT Support Specialist | G65: IT | H65: Specialist | I65: Regular | J65: 43147 | K65: 43327 | L65: Active | M65: EMP-0030 | N65: Baguio Branch | O65: Band B | P65: =IF($J65="","",MAX(0,INT((IF(OR($L65="Active",$L65="On Leave"),TODAY(),IFERROR(VLOOKUP($A65,'09_Attrition_Tracker'!$B:$G,6,FALSE),TODAY()))-$J65)/30))) -> 99 | Q65: =IF($P65="","",IF($P65<4,"0-3 mos",IF($P65<7,"4-6 mos",IF($P65<13,"7-12 mos",IF($P65<25,"1-2 yrs",IF($P65<61,"2-5 yrs","5+ yrs")))))) -> 5+ yrs | R65: =IF(OR($L65="Active",$L65="On Leave"),"Yes","No") -> Yes | S65: =IFERROR(VLOOKUP($A65,'09_Attrition_Tracker'!$B:$M,12,FALSE),"No") -> No
A66: EMP-0062 | B66: Angela Castillo | C66: Information Technology | D66: Team D | E66: POS-023 | F66: Systems Analyst | G66: IT | H66: Specialist | I66: Contractual | J66: 45397 | L66: Resigned | M66: EMP-0035 | N66: Iloilo Branch | O66: Band E | P66: =IF($J66="","",MAX(0,INT((IF(OR($L66="Active",$L66="On Leave"),TODAY(),IFERROR(VLOOKUP($A66,'09_Attrition_Tracker'!$B:$G,6,FALSE),TODAY()))-$J66)/30))) -> 9 | Q66: =IF($P66="","",IF($P66<4,"0-3 mos",IF($P66<7,"4-6 mos",IF($P66<13,"7-12 mos",IF($P66<25,"1-2 yrs",IF($P66<61,"2-5 yrs","5+ yrs")))))) -> 7-12 mos | R66: =IF(OR($L66="Active",$L66="On Leave"),"Yes","No") -> No | S66: =IFERROR(VLOOKUP($A66,'09_Attrition_Tracker'!$B:$M,12,FALSE),"No") -> No
A67: EMP-0063 | B67: Nico Mendoza | C67: Customer Service | D67: Team A | E67: POS-028 | F67: Customer Support Associate | G67: Service | H67: Specialist | I67: Regular | J67: 43667 | L67: Active | M67: EMP-0049 | N67: Cebu Branch | O67: Band A | P67: =IF($J67="","",MAX(0,INT((IF(OR($L67="Active",$L67="On Leave"),TODAY(),IFERROR(VLOOKUP($A67,'09_Attrition_Tracker'!$B:$G,6,FALSE),TODAY()))-$J67)/30))) -> 82 | Q67: =IF($P67="","",IF($P67<4,"0-3 mos",IF($P67<7,"4-6 mos",IF($P67<13,"7-12 mos",IF($P67<25,"1-2 yrs",IF($P67<61,"2-5 yrs","5+ yrs")))))) -> 5+ yrs | R67: =IF(OR($L67="Active",$L67="On Leave"),"Yes","No") -> Yes | S67: =IFERROR(VLOOKUP($A67,'09_Attrition_Tracker'!$B:$M,12,FALSE),"No") -> No
A68: EMP-0064 | B68: Luis Navarro | C68: Finance | D68: Team B | E68: POS-016 | F68: Accounting Associate | G68: Finance | H68: Rank and File | I68: Regular | J68: 44271 | K68: 44451 | L68: Active | M68: EMP-0037 | N68: Manila Branch | O68: Band E | P68: =IF($J68="","",MAX(0,INT((IF(OR($L68="Active",$L68="On Leave"),TODAY(),IFERROR(VLOOKUP($A68,'09_Attrition_Tracker'!$B:$G,6,FALSE),TODAY()))-$J68)/30))) -> 62 | Q68: =IF($P68="","",IF($P68<4,"0-3 mos",IF($P68<7,"4-6 mos",IF($P68<13,"7-12 mos",IF($P68<25,"1-2 yrs",IF($P68<61,"2-5 yrs","5+ yrs")))))) -> 5+ yrs | R68: =IF(OR($L68="Active",$L68="On Leave"),"Yes","No") -> Yes | S68: =IFERROR(VLOOKUP($A68,'09_Attrition_Tracker'!$B:$M,12,FALSE),"No") -> No
A69: EMP-0065 | B69: Nico Lopez | C69: Customer Service | D69: Team D | E69: POS-030 | F69: Service Supervisor | G69: Service | H69: Supervisor | I69: Regular | J69: 45124 | K69: 45304 | L69: Terminated | M69: EMP-0017 | N69: Head Office | O69: Band D | P69: =IF($J69="","",MAX(0,INT((IF(OR($L69="Active",$L69="On Leave"),TODAY(),IFERROR(VLOOKUP($A69,'09_Attrition_Tracker'!$B:$G,6,FALSE),TODAY()))-$J69)/30))) -> 27 | Q69: =IF($P69="","",IF($P69<4,"0-3 mos",IF($P69<7,"4-6 mos",IF($P69<13,"7-12 mos",IF($P69<25,"1-2 yrs",IF($P69<61,"2-5 yrs","5+ yrs")))))) -> 2-5 yrs | R69: =IF(OR($L69="Active",$L69="On Leave"),"Yes","No") -> No | S69: =IFERROR(VLOOKUP($A69,'09_Attrition_Tracker'!$B:$M,12,FALSE),"No") -> Yes
A70: EMP-0066 | B70: Andrea Villanueva | C70: Compliance | D70: Team C | E70: POS-025 | F70: Compliance Analyst | G70: Compliance | H70: Specialist | I70: Regular | J70: 44151 | K70: 44331 | L70: Active | M70: EMP-0028 | N70: Cebu Branch | O70: Band B | P70: =IF($J70="","",MAX(0,INT((IF(OR($L70="Active",$L70="On Leave"),TODAY(),IFERROR(VLOOKUP($A70,'09_Attrition_Tracker'!$B:$G,6,FALSE),TODAY()))-$J70)/30))) -> 66 | Q70: =IF($P70="","",IF($P70<4,"0-3 mos",IF($P70<7,"4-6 mos",IF($P70<13,"7-12 mos",IF($P70<25,"1-2 yrs",IF($P70<61,"2-5 yrs","5+ yrs")))))) -> 5+ yrs | R70: =IF(OR($L70="Active",$L70="On Leave"),"Yes","No") -> Yes | S70: =IFERROR(VLOOKUP($A70,'09_Attrition_Tracker'!$B:$M,12,FALSE),"No") -> No
A71: EMP-0067 | B71: Nico Castillo | C71: Information Technology | D71: Team A | E71: POS-022 | F71: IT Support Specialist | G71: IT | H71: Specialist | I71: Project-based | J71: 45078 | L71: Active | M71: EMP-0019 | N71: Baguio Branch | O71: Band C | P71: =IF($J71="","",MAX(0,INT((IF(OR($L71="Active",$L71="On Leave"),TODAY(),IFERROR(VLOOKUP($A71,'09_Attrition_Tracker'!$B:$G,6,FALSE),TODAY()))-$J71)/30))) -> 35 | Q71: =IF($P71="","",IF($P71<4,"0-3 mos",IF($P71<7,"4-6 mos",IF($P71<13,"7-12 mos",IF($P71<25,"1-2 yrs",IF($P71<61,"2-5 yrs","5+ yrs")))))) -> 2-5 yrs | R71: =IF(OR($L71="Active",$L71="On Leave"),"Yes","No") -> Yes | S71: =IFERROR(VLOOKUP($A71,'09_Attrition_Tracker'!$B:$M,12,FALSE),"No") -> No
A72: EMP-0068 | B72: Patrick Reyes | C72: Customer Service | D72: Team B | E72: POS-030 | F72: Service Supervisor | G72: Service | H72: Supervisor | I72: Regular | J72: 45219 | K72: 45399 | L72: Active | M72: EMP-0019 | N72: Davao Branch | O72: Band B | P72: =IF($J72="","",MAX(0,INT((IF(OR($L72="Active",$L72="On Leave"),TODAY(),IFERROR(VLOOKUP($A72,'09_Attrition_Tracker'!$B:$G,6,FALSE),TODAY()))-$J72)/30))) -> 30 | Q72: =IF($P72="","",IF($P72<4,"0-3 mos",IF($P72<7,"4-6 mos",IF($P72<13,"7-12 mos",IF($P72<25,"1-2 yrs",IF($P72<61,"2-5 yrs","5+ yrs")))))) -> 2-5 yrs | R72: =IF(OR($L72="Active",$L72="On Leave"),"Yes","No") -> Yes | S72: =IFERROR(VLOOKUP($A72,'09_Attrition_Tracker'!$B:$M,12,FALSE),"No") -> No
A73: EMP-0069 | B73: Martin Lim | C73: Customer Service | D73: Team A | E73: POS-029 | F73: Customer Care Officer | G73: Service | H73: Rank and File | I73: Regular | J73: 45309 | K73: 45489 | L73: Resigned | M73: EMP-0029 | N73: Quezon City Branch | O73: Band A | P73: =IF($J73="","",MAX(0,INT((IF(OR($L73="Active",$L73="On Leave"),TODAY(),IFERROR(VLOOKUP($A73,'09_Attrition_Tracker'!$B:$G,6,FALSE),TODAY()))-$J73)/30))) -> 27 | Q73: =IF($P73="","",IF($P73<4,"0-3 mos",IF($P73<7,"4-6 mos",IF($P73<13,"7-12 mos",IF($P73<25,"1-2 yrs",IF($P73<61,"2-5 yrs","5+ yrs")))))) -> 2-5 yrs | R73: =IF(OR($L73="Active",$L73="On Leave"),"Yes","No") -> No | S73: =IFERROR(VLOOKUP($A73,'09_Attrition_Tracker'!$B:$M,12,FALSE),"No") -> No
A74: EMP-0070 | B74: Miguel Dela Cruz | C74: Finance | D74: Team C | E74: POS-018 | F74: Finance Manager | G74: Finance | H74: Manager | I74: Regular | J74: 43558 | K74: 43738 | L74: Terminated | N74: Cebu Branch | O74: Band B | P74: =IF($J74="","",MAX(0,INT((IF(OR($L74="Active",$L74="On Leave"),TODAY(),IFERROR(VLOOKUP($A74,'09_Attrition_Tracker'!$B:$G,6,FALSE),TODAY()))-$J74)/30))) -> 86 | Q74: =IF($P74="","",IF($P74<4,"0-3 mos",IF($P74<7,"4-6 mos",IF($P74<13,"7-12 mos",IF($P74<25,"1-2 yrs",IF($P74<61,"2-5 yrs","5+ yrs")))))) -> 5+ yrs | R74: =IF(OR($L74="Active",$L74="On Leave"),"Yes","No") -> No | S74: =IFERROR(VLOOKUP($A74,'09_Attrition_Tracker'!$B:$M,12,FALSE),"No") -> No
A75: EMP-0071 | B75: Patrick Bautista | C75: Information Technology | D75: Team D | E75: POS-023 | F75: Systems Analyst | G75: IT | H75: Rank and File | I75: Contractual | J75: 46030 | K75: 46210 | L75: Resigned | M75: EMP-0015 | N75: Davao Branch | O75: Band A | P75: =IF($J75="","",MAX(0,INT((IF(OR($L75="Active",$L75="On Leave"),TODAY(),IFERROR(VLOOKUP($A75,'09_Attrition_Tracker'!$B:$G,6,FALSE),TODAY()))-$J75)/30))) -> 3 | Q75: =IF($P75="","",IF($P75<4,"0-3 mos",IF($P75<7,"4-6 mos",IF($P75<13,"7-12 mos",IF($P75<25,"1-2 yrs",IF($P75<61,"2-5 yrs","5+ yrs")))))) -> 0-3 mos | R75: =IF(OR($L75="Active",$L75="On Leave"),"Yes","No") -> No | S75: =IFERROR(VLOOKUP($A75,'09_Attrition_Tracker'!$B:$M,12,FALSE),"No") -> No
A76: EMP-0072 | B76: Ethan Garcia | C76: Branch Operations | D76: Team D | E76: POS-002 | F76: Branch Supervisor | G76: Operations | H76: Supervisor | I76: Probationary | J76: 44598 | K76: 44778 | L76: Active | M76: EMP-0017 | N76: Davao Branch | O76: Band A | P76: =IF($J76="","",MAX(0,INT((IF(OR($L76="Active",$L76="On Leave"),TODAY(),IFERROR(VLOOKUP($A76,'09_Attrition_Tracker'!$B:$G,6,FALSE),TODAY()))-$J76)/30))) -> 51 | Q76: =IF($P76="","",IF($P76<4,"0-3 mos",IF($P76<7,"4-6 mos",IF($P76<13,"7-12 mos",IF($P76<25,"1-2 yrs",IF($P76<61,"2-5 yrs","5+ yrs")))))) -> 2-5 yrs | R76: =IF(OR($L76="Active",$L76="On Leave"),"Yes","No") -> Yes | S76: =IFERROR(VLOOKUP($A76,'09_Attrition_Tracker'!$B:$M,12,FALSE),"No") -> No
A77: EMP-0073 | B77: Gabriel Bautista | C77: Information Technology | D77: Team C | E77: POS-022 | F77: IT Support Specialist | G77: IT | H77: Rank and File | I77: Regular | J77: 45234 | K77: 45414 | L77: Active | M77: EMP-0030 | N77: Manila Branch | O77: Band B | P77: =IF($J77="","",MAX(0,INT((IF(OR($L77="Active",$L77="On Leave"),TODAY(),IFERROR(VLOOKUP($A77,'09_Attrition_Tracker'!$B:$G,6,FALSE),TODAY()))-$J77)/30))) -> 30 | Q77: =IF($P77="","",IF($P77<4,"0-3 mos",IF($P77<7,"4-6 mos",IF($P77<13,"7-12 mos",IF($P77<25,"1-2 yrs",IF($P77<61,"2-5 yrs","5+ yrs")))))) -> 2-5 yrs | R77: =IF(OR($L77="Active",$L77="On Leave"),"Yes","No") -> Yes | S77: =IFERROR(VLOOKUP($A77,'09_Attrition_Tracker'!$B:$M,12,FALSE),"No") -> No
A78: EMP-0074 | B78: Julius Garcia | C78: Branch Operations | D78: Team D | E78: POS-002 | F78: Branch Supervisor | G78: Operations | H78: Supervisor | I78: Regular | J78: 43134 | K78: 43314 | L78: Active | M78: EMP-0025 | N78: Baguio Branch | O78: Band E | P78: =IF($J78="","",MAX(0,INT((IF(OR($L78="Active",$L78="On Leave"),TODAY(),IFERROR(VLOOKUP($A78,'09_Attrition_Tracker'!$B:$G,6,FALSE),TODAY()))-$J78)/30))) -> 100 | Q78: =IF($P78="","",IF($P78<4,"0-3 mos",IF($P78<7,"4-6 mos",IF($P78<13,"7-12 mos",IF($P78<25,"1-2 yrs",IF($P78<61,"2-5 yrs","5+ yrs")))))) -> 5+ yrs | R78: =IF(OR($L78="Active",$L78="On Leave"),"Yes","No") -> Yes | S78: =IFERROR(VLOOKUP($A78,'09_Attrition_Tracker'!$B:$M,12,FALSE),"No") -> No
A79: EMP-0075 | B79: Jose Lopez | C79: Human Resources | D79: Team A | E79: POS-021 | F79: HR Manager | G79: HR | H79: Manager | I79: Regular | J79: 45257 | L79: Active | N79: Makati Branch | O79: Band D | P79: =IF($J79="","",MAX(0,INT((IF(OR($L79="Active",$L79="On Leave"),TODAY(),IFERROR(VLOOKUP($A79,'09_Attrition_Tracker'!$B:$G,6,FALSE),TODAY()))-$J79)/30))) -> 29 | Q79: =IF($P79="","",IF($P79<4,"0-3 mos",IF($P79<7,"4-6 mos",IF($P79<13,"7-12 mos",IF($P79<25,"1-2 yrs",IF($P79<61,"2-5 yrs","5+ yrs")))))) -> 2-5 yrs | R79: =IF(OR($L79="Active",$L79="On Leave"),"Yes","No") -> Yes | S79: =IFERROR(VLOOKUP($A79,'09_Attrition_Tracker'!$B:$M,12,FALSE),"No") -> No
A80: EMP-0076 | B80: Jose Navarro | C80: Collections | D80: Team B | E80: POS-011 | F80: Collections Officer | G80: Collections | H80: Specialist | I80: Contractual | J80: 44966 | K80: 45146 | L80: Active | M80: EMP-0018 | N80: Iloilo Branch | O80: Band A | P80: =IF($J80="","",MAX(0,INT((IF(OR($L80="Active",$L80="On Leave"),TODAY(),IFERROR(VLOOKUP($A80,'09_Attrition_Tracker'!$B:$G,6,FALSE),TODAY()))-$J80)/30))) -> 39 | Q80: =IF($P80="","",IF($P80<4,"0-3 mos",IF($P80<7,"4-6 mos",IF($P80<13,"7-12 mos",IF($P80<25,"1-2 yrs",IF($P80<61,"2-5 yrs","5+ yrs")))))) -> 2-5 yrs | R80: =IF(OR($L80="Active",$L80="On Leave"),"Yes","No") -> Yes | S80: =IFERROR(VLOOKUP($A80,'09_Attrition_Tracker'!$B:$M,12,FALSE),"No") -> No
A81: EMP-0077 | B81: Carlo Bautista | C81: Customer Service | D81: Team B | E81: POS-028 | F81: Customer Support Associate | G81: Service | H81: Rank and File | I81: Regular | J81: 43733 | K81: 43913 | L81: Active | M81: EMP-0049 | N81: Makati Branch | O81: Band C | P81: =IF($J81="","",MAX(0,INT((IF(OR($L81="Active",$L81="On Leave"),TODAY(),IFERROR(VLOOKUP($A81,'09_Attrition_Tracker'!$B:$G,6,FALSE),TODAY()))-$J81)/30))) -> 80 | Q81: =IF($P81="","",IF($P81<4,"0-3 mos",IF($P81<7,"4-6 mos",IF($P81<13,"7-12 mos",IF($P81<25,"1-2 yrs",IF($P81<61,"2-5 yrs","5+ yrs")))))) -> 5+ yrs | R81: =IF(OR($L81="Active",$L81="On Leave"),"Yes","No") -> Yes | S81: =IFERROR(VLOOKUP($A81,'09_Attrition_Tracker'!$B:$M,12,FALSE),"No") -> No
A82: EMP-0078 | B82: Diana Lim | C82: Customer Service | D82: Team B | E82: POS-028 | F82: Customer Support Associate | G82: Service | H82: Rank and File | I82: Regular | J82: 43268 | K82: 43448 | L82: Active | M82: EMP-0002 | N82: Makati Branch | O82: Band E | P82: =IF($J82="","",MAX(0,INT((IF(OR($L82="Active",$L82="On Leave"),TODAY(),IFERROR(VLOOKUP($A82,'09_Attrition_Tracker'!$B:$G,6,FALSE),TODAY()))-$J82)/30))) -> 95 | Q82: =IF($P82="","",IF($P82<4,"0-3 mos",IF($P82<7,"4-6 mos",IF($P82<13,"7-12 mos",IF($P82<25,"1-2 yrs",IF($P82<61,"2-5 yrs","5+ yrs")))))) -> 5+ yrs | R82: =IF(OR($L82="Active",$L82="On Leave"),"Yes","No") -> Yes | S82: =IFERROR(VLOOKUP($A82,'09_Attrition_Tracker'!$B:$M,12,FALSE),"No") -> No
A83: EMP-0079 | B83: Diana Reyes | C83: Branch Operations | D83: Team D | E83: POS-001 | F83: Branch Associate | G83: Operations | H83: Rank and File | I83: Probationary | J83: 43255 | K83: 43435 | L83: Active | M83: EMP-0031 | N83: Manila Branch | O83: Band D | P83: =IF($J83="","",MAX(0,INT((IF(OR($L83="Active",$L83="On Leave"),TODAY(),IFERROR(VLOOKUP($A83,'09_Attrition_Tracker'!$B:$G,6,FALSE),TODAY()))-$J83)/30))) -> 96 | Q83: =IF($P83="","",IF($P83<4,"0-3 mos",IF($P83<7,"4-6 mos",IF($P83<13,"7-12 mos",IF($P83<25,"1-2 yrs",IF($P83<61,"2-5 yrs","5+ yrs")))))) -> 5+ yrs | R83: =IF(OR($L83="Active",$L83="On Leave"),"Yes","No") -> Yes | S83: =IFERROR(VLOOKUP($A83,'09_Attrition_Tracker'!$B:$M,12,FALSE),"No") -> No
A84: EMP-0080 | B84: Patrick Mendoza | C84: Customer Service | D84: Team D | E84: POS-028 | F84: Customer Support Associate | G84: Service | H84: Rank and File | I84: Regular | J84: 44612 | K84: 44792 | L84: Active | M84: EMP-0031 | N84: Manila Branch | O84: Band D | P84: =IF($J84="","",MAX(0,INT((IF(OR($L84="Active",$L84="On Leave"),TODAY(),IFERROR(VLOOKUP($A84,'09_Attrition_Tracker'!$B:$G,6,FALSE),TODAY()))-$J84)/30))) -> 51 | Q84: =IF($P84="","",IF($P84<4,"0-3 mos",IF($P84<7,"4-6 mos",IF($P84<13,"7-12 mos",IF($P84<25,"1-2 yrs",IF($P84<61,"2-5 yrs","5+ yrs")))))) -> 2-5 yrs | R84: =IF(OR($L84="Active",$L84="On Leave"),"Yes","No") -> Yes | S84: =IFERROR(VLOOKUP($A84,'09_Attrition_Tracker'!$B:$M,12,FALSE),"No") -> No
A85: EMP-0081 | B85: Angela Lim | C85: Credit Evaluation | D85: Team C | E85: POS-004 | F85: Credit Analyst | G85: Credit & Risk | H85: Specialist | I85: Regular | J85: 43005 | K85: 43185 | L85: Resigned | M85: EMP-0039 | N85: Baguio Branch | O85: Band A | P85: =IF($J85="","",MAX(0,INT((IF(OR($L85="Active",$L85="On Leave"),TODAY(),IFERROR(VLOOKUP($A85,'09_Attrition_Tracker'!$B:$G,6,FALSE),TODAY()))-$J85)/30))) -> 104 | Q85: =IF($P85="","",IF($P85<4,"0-3 mos",IF($P85<7,"4-6 mos",IF($P85<13,"7-12 mos",IF($P85<25,"1-2 yrs",IF($P85<61,"2-5 yrs","5+ yrs")))))) -> 5+ yrs | R85: =IF(OR($L85="Active",$L85="On Leave"),"Yes","No") -> No | S85: =IFERROR(VLOOKUP($A85,'09_Attrition_Tracker'!$B:$M,12,FALSE),"No") -> No
A86: EMP-0082 | B86: Lara Gonzales | C86: Compliance | D86: Team D | E86: POS-027 | F86: Compliance Manager | G86: Compliance | H86: Manager | I86: Regular | J86: 44585 | K86: 44765 | L86: Active | N86: Manila Branch | O86: Band C | P86: =IF($J86="","",MAX(0,INT((IF(OR($L86="Active",$L86="On Leave"),TODAY(),IFERROR(VLOOKUP($A86,'09_Attrition_Tracker'!$B:$G,6,FALSE),TODAY()))-$J86)/30))) -> 52 | Q86: =IF($P86="","",IF($P86<4,"0-3 mos",IF($P86<7,"4-6 mos",IF($P86<13,"7-12 mos",IF($P86<25,"1-2 yrs",IF($P86<61,"2-5 yrs","5+ yrs")))))) -> 2-5 yrs | R86: =IF(OR($L86="Active",$L86="On Leave"),"Yes","No") -> Yes | S86: =IFERROR(VLOOKUP($A86,'09_Attrition_Tracker'!$B:$M,12,FALSE),"No") -> No
A87: EMP-0083 | B87: Diana Navarro | C87: Finance | D87: Team A | E87: POS-018 | F87: Finance Manager | G87: Finance | H87: Manager | I87: Probationary | J87: 43361 | K87: 43541 | L87: Active | N87: Manila Branch | O87: Band D | P87: =IF($J87="","",MAX(0,INT((IF(OR($L87="Active",$L87="On Leave"),TODAY(),IFERROR(VLOOKUP($A87,'09_Attrition_Tracker'!$B:$G,6,FALSE),TODAY()))-$J87)/30))) -> 92 | Q87: =IF($P87="","",IF($P87<4,"0-3 mos",IF($P87<7,"4-6 mos",IF($P87<13,"7-12 mos",IF($P87<25,"1-2 yrs",IF($P87<61,"2-5 yrs","5+ yrs")))))) -> 5+ yrs | R87: =IF(OR($L87="Active",$L87="On Leave"),"Yes","No") -> Yes | S87: =IFERROR(VLOOKUP($A87,'09_Attrition_Tracker'!$B:$M,12,FALSE),"No") -> No
A88: EMP-0084 | B88: Ethan Reyes | C88: Finance | D88: Team C | E88: POS-016 | F88: Accounting Associate | G88: Finance | H88: Specialist | I88: Probationary | J88: 45138 | K88: 45318 | L88: Active | M88: EMP-0027 | N88: Baguio Branch | O88: Band A | P88: =IF($J88="","",MAX(0,INT((IF(OR($L88="Active",$L88="On Leave"),TODAY(),IFERROR(VLOOKUP($A88,'09_Attrition_Tracker'!$B:$G,6,FALSE),TODAY()))-$J88)/30))) -> 33 | Q88: =IF($P88="","",IF($P88<4,"0-3 mos",IF($P88<7,"4-6 mos",IF($P88<13,"7-12 mos",IF($P88<25,"1-2 yrs",IF($P88<61,"2-5 yrs","5+ yrs")))))) -> 2-5 yrs | R88: =IF(OR($L88="Active",$L88="On Leave"),"Yes","No") -> Yes | S88: =IFERROR(VLOOKUP($A88,'09_Attrition_Tracker'!$B:$M,12,FALSE),"No") -> No
A89: EMP-0085 | B89: Rafael Garcia | C89: Customer Service | D89: Team A | E89: POS-029 | F89: Customer Care Officer | G89: Service | H89: Rank and File | I89: Regular | J89: 45103 | K89: 45283 | L89: Active | M89: EMP-0015 | N89: Davao Branch | O89: Band A | P89: =IF($J89="","",MAX(0,INT((IF(OR($L89="Active",$L89="On Leave"),TODAY(),IFERROR(VLOOKUP($A89,'09_Attrition_Tracker'!$B:$G,6,FALSE),TODAY()))-$J89)/30))) -> 34 | Q89: =IF($P89="","",IF($P89<4,"0-3 mos",IF($P89<7,"4-6 mos",IF($P89<13,"7-12 mos",IF($P89<25,"1-2 yrs",IF($P89<61,"2-5 yrs","5+ yrs")))))) -> 2-5 yrs | R89: =IF(OR($L89="Active",$L89="On Leave"),"Yes","No") -> Yes | S89: =IFERROR(VLOOKUP($A89,'09_Attrition_Tracker'!$B:$M,12,FALSE),"No") -> No
A90: EMP-0086 | B90: Miguel Santos | C90: Customer Service | D90: Team C | E90: POS-028 | F90: Customer Support Associate | G90: Service | H90: Specialist | I90: Contractual | J90: 45230 | K90: 45410 | L90: Active | M90: EMP-0018 | N90: Davao Branch | O90: Band A | P90: =IF($J90="","",MAX(0,INT((IF(OR($L90="Active",$L90="On Leave"),TODAY(),IFERROR(VLOOKUP($A90,'09_Attrition_Tracker'!$B:$G,6,FALSE),TODAY()))-$J90)/30))) -> 30 | Q90: =IF($P90="","",IF($P90<4,"0-3 mos",IF($P90<7,"4-6 mos",IF($P90<13,"7-12 mos",IF($P90<25,"1-2 yrs",IF($P90<61,"2-5 yrs","5+ yrs")))))) -> 2-5 yrs | R90: =IF(OR($L90="Active",$L90="On Leave"),"Yes","No") -> Yes | S90: =IFERROR(VLOOKUP($A90,'09_Attrition_Tracker'!$B:$M,12,FALSE),"No") -> No
A91: EMP-0087 | B91: Martin Castillo | C91: Loan Processing | D91: Team A | E91: POS-009 | F91: Processing Supervisor | G91: Operations | H91: Supervisor | I91: Regular | J91: 43021 | K91: 43201 | L91: Terminated | M91: EMP-0002 | N91: Makati Branch | O91: Band D | P91: =IF($J91="","",MAX(0,INT((IF(OR($L91="Active",$L91="On Leave"),TODAY(),IFERROR(VLOOKUP($A91,'09_Attrition_Tracker'!$B:$G,6,FALSE),TODAY()))-$J91)/30))) -> 88 | Q91: =IF($P91="","",IF($P91<4,"0-3 mos",IF($P91<7,"4-6 mos",IF($P91<13,"7-12 mos",IF($P91<25,"1-2 yrs",IF($P91<61,"2-5 yrs","5+ yrs")))))) -> 5+ yrs | R91: =IF(OR($L91="Active",$L91="On Leave"),"Yes","No") -> No | S91: =IFERROR(VLOOKUP($A91,'09_Attrition_Tracker'!$B:$M,12,FALSE),"No") -> No
A92: EMP-0088 | B92: Paolo Navarro | C92: Information Technology | D92: Team B | E92: POS-023 | F92: Systems Analyst | G92: IT | H92: Rank and File | I92: Regular | J92: 44012 | L92: Active | M92: EMP-0010 | N92: Head Office | O92: Band A | P92: =IF($J92="","",MAX(0,INT((IF(OR($L92="Active",$L92="On Leave"),TODAY(),IFERROR(VLOOKUP($A92,'09_Attrition_Tracker'!$B:$G,6,FALSE),TODAY()))-$J92)/30))) -> 71 | Q92: =IF($P92="","",IF($P92<4,"0-3 mos",IF($P92<7,"4-6 mos",IF($P92<13,"7-12 mos",IF($P92<25,"1-2 yrs",IF($P92<61,"2-5 yrs","5+ yrs")))))) -> 5+ yrs | R92: =IF(OR($L92="Active",$L92="On Leave"),"Yes","No") -> Yes | S92: =IFERROR(VLOOKUP($A92,'09_Attrition_Tracker'!$B:$M,12,FALSE),"No") -> No
A93: EMP-0089 | B93: Miguel Lopez | C93: Information Technology | D93: Team A | E93: POS-024 | F93: IT Manager | G93: IT | H93: Manager | I93: Regular | J93: 45222 | K93: 45402 | L93: Active | N93: Manila Branch | O93: Band C | P93: =IF($J93="","",MAX(0,INT((IF(OR($L93="Active",$L93="On Leave"),TODAY(),IFERROR(VLOOKUP($A93,'09_Attrition_Tracker'!$B:$G,6,FALSE),TODAY()))-$J93)/30))) -> 30 | Q93: =IF($P93="","",IF($P93<4,"0-3 mos",IF($P93<7,"4-6 mos",IF($P93<13,"7-12 mos",IF($P93<25,"1-2 yrs",IF($P93<61,"2-5 yrs","5+ yrs")))))) -> 2-5 yrs | R93: =IF(OR($L93="Active",$L93="On Leave"),"Yes","No") -> Yes | S93: =IFERROR(VLOOKUP($A93,'09_Attrition_Tracker'!$B:$M,12,FALSE),"No") -> No
A94: EMP-0090 | B94: Luis Reyes | C94: Compliance | D94: Team A | E94: POS-027 | F94: Compliance Manager | G94: Compliance | H94: Manager | I94: Regular | J94: 43639 | K94: 43819 | L94: Active | N94: Makati Branch | O94: Band B | P94: =IF($J94="","",MAX(0,INT((IF(OR($L94="Active",$L94="On Leave"),TODAY(),IFERROR(VLOOKUP($A94,'09_Attrition_Tracker'!$B:$G,6,FALSE),TODAY()))-$J94)/30))) -> 83 | Q94: =IF($P94="","",IF($P94<4,"0-3 mos",IF($P94<7,"4-6 mos",IF($P94<13,"7-12 mos",IF($P94<25,"1-2 yrs",IF($P94<61,"2-5 yrs","5+ yrs")))))) -> 5+ yrs | R94: =IF(OR($L94="Active",$L94="On Leave"),"Yes","No") -> Yes | S94: =IFERROR(VLOOKUP($A94,'09_Attrition_Tracker'!$B:$M,12,FALSE),"No") -> No
A95: EMP-0091 | B95: Jose Santos | C95: Sales & Marketing | D95: Team B | E95: POS-014 | F95: Marketing Associate | G95: Sales | H95: Rank and File | I95: Regular | J95: 44773 | K95: 44953 | L95: Active | M95: EMP-0035 | N95: Davao Branch | O95: Band A | P95: =IF($J95="","",MAX(0,INT((IF(OR($L95="Active",$L95="On Leave"),TODAY(),IFERROR(VLOOKUP($A95,'09_Attrition_Tracker'!$B:$G,6,FALSE),TODAY()))-$J95)/30))) -> 45 | Q95: =IF($P95="","",IF($P95<4,"0-3 mos",IF($P95<7,"4-6 mos",IF($P95<13,"7-12 mos",IF($P95<25,"1-2 yrs",IF($P95<61,"2-5 yrs","5+ yrs")))))) -> 2-5 yrs | R95: =IF(OR($L95="Active",$L95="On Leave"),"Yes","No") -> Yes | S95: =IFERROR(VLOOKUP($A95,'09_Attrition_Tracker'!$B:$M,12,FALSE),"No") -> No
A96: EMP-0092 | B96: Mika Villanueva | C96: Branch Operations | D96: Team D | E96: POS-002 | F96: Branch Supervisor | G96: Operations | H96: Supervisor | I96: Regular | J96: 43054 | K96: 43234 | L96: Active | M96: EMP-0037 | N96: Baguio Branch | O96: Band C | P96: =IF($J96="","",MAX(0,INT((IF(OR($L96="Active",$L96="On Leave"),TODAY(),IFERROR(VLOOKUP($A96,'09_Attrition_Tracker'!$B:$G,6,FALSE),TODAY()))-$J96)/30))) -> 103 | Q96: =IF($P96="","",IF($P96<4,"0-3 mos",IF($P96<7,"4-6 mos",IF($P96<13,"7-12 mos",IF($P96<25,"1-2 yrs",IF($P96<61,"2-5 yrs","5+ yrs")))))) -> 5+ yrs | R96: =IF(OR($L96="Active",$L96="On Leave"),"Yes","No") -> Yes | S96: =IFERROR(VLOOKUP($A96,'09_Attrition_Tracker'!$B:$M,12,FALSE),"No") -> No
A97: EMP-0093 | B97: Angela Dela Cruz | C97: Human Resources | D97: Team A | E97: POS-019 | F97: HR Assistant | G97: HR | H97: Specialist | I97: Regular | J97: 46018 | K97: 46198 | L97: Active | M97: EMP-0024 | N97: Manila Branch | O97: Band B | P97: =IF($J97="","",MAX(0,INT((IF(OR($L97="Active",$L97="On Leave"),TODAY(),IFERROR(VLOOKUP($A97,'09_Attrition_Tracker'!$B:$G,6,FALSE),TODAY()))-$J97)/30))) -> 4 | Q97: =IF($P97="","",IF($P97<4,"0-3 mos",IF($P97<7,"4-6 mos",IF($P97<13,"7-12 mos",IF($P97<25,"1-2 yrs",IF($P97<61,"2-5 yrs","5+ yrs")))))) -> 4-6 mos | R97: =IF(OR($L97="Active",$L97="On Leave"),"Yes","No") -> Yes | S97: =IFERROR(VLOOKUP($A97,'09_Attrition_Tracker'!$B:$M,12,FALSE),"No") -> No
A98: EMP-0094 | B98: Camille Cruz | C98: Customer Service | D98: Team B | E98: POS-029 | F98: Customer Care Officer | G98: Service | H98: Specialist | I98: Regular | J98: 44357 | K98: 44537 | L98: Active | M98: EMP-0050 | N98: Manila Branch | O98: Band E | P98: =IF($J98="","",MAX(0,INT((IF(OR($L98="Active",$L98="On Leave"),TODAY(),IFERROR(VLOOKUP($A98,'09_Attrition_Tracker'!$B:$G,6,FALSE),TODAY()))-$J98)/30))) -> 59 | Q98: =IF($P98="","",IF($P98<4,"0-3 mos",IF($P98<7,"4-6 mos",IF($P98<13,"7-12 mos",IF($P98<25,"1-2 yrs",IF($P98<61,"2-5 yrs","5+ yrs")))))) -> 2-5 yrs | R98: =IF(OR($L98="Active",$L98="On Leave"),"Yes","No") -> Yes | S98: =IFERROR(VLOOKUP($A98,'09_Attrition_Tracker'!$B:$M,12,FALSE),"No") -> No
A99: EMP-0095 | B99: Patrick Lim | C99: Finance | D99: Team B | E99: POS-017 | F99: Finance Analyst | G99: Finance | H99: Specialist | I99: Probationary | J99: 43703 | K99: 43883 | L99: Resigned | M99: EMP-0039 | N99: Manila Branch | O99: Band B | P99: =IF($J99="","",MAX(0,INT((IF(OR($L99="Active",$L99="On Leave"),TODAY(),IFERROR(VLOOKUP($A99,'09_Attrition_Tracker'!$B:$G,6,FALSE),TODAY()))-$J99)/30))) -> 79 | Q99: =IF($P99="","",IF($P99<4,"0-3 mos",IF($P99<7,"4-6 mos",IF($P99<13,"7-12 mos",IF($P99<25,"1-2 yrs",IF($P99<61,"2-5 yrs","5+ yrs")))))) -> 5+ yrs | R99: =IF(OR($L99="Active",$L99="On Leave"),"Yes","No") -> No | S99: =IFERROR(VLOOKUP($A99,'09_Attrition_Tracker'!$B:$M,12,FALSE),"No") -> No
A100: EMP-0096 | B100: Rhea Villanueva | C100: Information Technology | D100: Team C | E100: POS-024 | F100: IT Manager | G100: IT | H100: Manager | I100: Probationary | J100: 45525 | K100: 45705 | L100: Active | N100: Davao Branch | O100: Band B | P100: =IF($J100="","",MAX(0,INT((IF(OR($L100="Active",$L100="On Leave"),TODAY(),IFERROR(VLOOKUP($A100,'09_Attrition_Tracker'!$B:$G,6,FALSE),TODAY()))-$J100)/30))) -> 20 | Q100: =IF($P100="","",IF($P100<4,"0-3 mos",IF($P100<7,"4-6 mos",IF($P100<13,"7-12 mos",IF($P100<25,"1-2 yrs",IF($P100<61,"2-5 yrs","5+ yrs")))))) -> 1-2 yrs | R100: =IF(OR($L100="Active",$L100="On Leave"),"Yes","No") -> Yes | S100: =IFERROR(VLOOKUP($A100,'09_Attrition_Tracker'!$B:$M,12,FALSE),"No") -> No
A101: EMP-0097 | B101: Sofia Mendoza | C101: Credit Evaluation | D101: Team C | E101: POS-005 | F101: Senior Credit Analyst | G101: Credit & Risk | H101: Rank and File | I101: Regular | J101: 45997 | K101: 46177 | L101: Active | M101: EMP-0005 | N101: Head Office | O101: Band A | P101: =IF($J101="","",MAX(0,INT((IF(OR($L101="Active",$L101="On Leave"),TODAY(),IFERROR(VLOOKUP($A101,'09_Attrition_Tracker'!$B:$G,6,FALSE),TODAY()))-$J101)/30))) -> 4 | Q101: =IF($P101="","",IF($P101<4,"0-3 mos",IF($P101<7,"4-6 mos",IF($P101<13,"7-12 mos",IF($P101<25,"1-2 yrs",IF($P101<61,"2-5 yrs","5+ yrs")))))) -> 4-6 mos | R101: =IF(OR($L101="Active",$L101="On Leave"),"Yes","No") -> Yes | S101: =IFERROR(VLOOKUP($A101,'09_Attrition_Tracker'!$B:$M,12,FALSE),"No") -> No
...

Sheet 04_Department_Position_Master
A1: Department & Position Master
A2: Approved headcount and role-level workforce planning reference.
A4: POSITION_ID | B4: DEPARTMENT | C4: POSITION_TITLE | D4: JOB_FAMILY | E4: APPROVED_HEADCOUNT | F4: CRITICAL_ROLE_FLAG | G4: SLA_TARGET_DAYS_TO_FILL | H4: HIRING_PRIORITY | I4: BUSINESS_OWNER
A5: POS-001 | B5: Branch Operations | C5: Branch Associate | D5: Operations | E5: 15 | F5: Yes | G5: 20 | H5: Critical | I5: Branch Operations Head
A6: POS-002 | B6: Branch Operations | C6: Branch Supervisor | D6: Operations | E6: 9 | F6: Yes | G6: 30 | H6: Critical | I6: Branch Operations Head
A7: POS-003 | B7: Branch Operations | C7: Branch Manager | D7: Operations | E7: 1 | F7: No | G7: 60 | H7: Medium | I7: Branch Operations Head
A8: POS-004 | B8: Credit Evaluation | C8: Credit Analyst | D8: Credit & Risk | E8: 14 | F8: Yes | G8: 45 | H8: Critical | I8: Credit Evaluation Head
A9: POS-005 | B9: Credit Evaluation | C9: Senior Credit Analyst | D9: Credit & Risk | E9: 6 | F9: Yes | G9: 30 | H9: Medium | I9: Credit Evaluation Head
A10: POS-006 | B10: Credit Evaluation | C10: Credit Supervisor | D10: Credit & Risk | E10: 13 | F10: Yes | G10: 45 | H10: Critical | I10: Credit Evaluation Head
A11: POS-007 | B11: Loan Processing | C11: Loan Processor | D11: Operations | E11: 14 | F11: Yes | G11: 35 | H11: Medium | I11: Loan Processing Head
A12: POS-008 | B12: Loan Processing | C12: Processing Specialist | D12: Operations | E12: 17 | F12: Yes | G12: 45 | H12: Critical | I12: Loan Processing Head
A13: POS-009 | B13: Loan Processing | C13: Processing Supervisor | D13: Operations | E13: 7 | F13: Yes | G13: 35 | H13: Critical | I13: Loan Processing Head
A14: POS-010 | B14: Collections | C14: Collections Associate | D14: Collections | E14: 11 | F14: Yes | G14: 35 | H14: High | I14: Collections Head
A15: POS-011 | B15: Collections | C15: Collections Officer | D15: Collections | E15: 17 | F15: Yes | G15: 20 | H15: Medium | I15: Collections Head
A16: POS-012 | B16: Collections | C16: Collections Supervisor | D16: Collections | E16: 11 | F16: Yes | G16: 35 | H16: High | I16: Collections Head
... A34: POS-030 | B34: Customer Service | C34: Service Supervisor | D34: Service | E34: 14 | F34: Yes | G34: 45 | H34: High | I34: Customer Service Head

Sheet 05_Requisitions_MRF
A1: Requisitions / MRF
A2: Manpower request tracking with dynamic aging, SLA status, and filled count.
A4: REQ_ID | B4: REQUEST_DATE | C4: APPROVAL_DATE | D4: DEPARTMENT | E4: POSITION_ID | F4: POSITION_TITLE | G4: REQUEST_TYPE | H4: APPROVED_HEADCOUNT | I4: PRIORITY | J4: TARGET_START_DATE | K4: REQ_STATUS | L4: ASSIGNED_RECRUITER | M4: SLA_TARGET_DAYS | N4: DAYS_OPEN | O4: SLA_STATUS | P4: FILLED_COUNT | Q4: VACANCY_REMAINING | R4: FILLED_DATE | S4: TIME_TO_FILL_DAYS | T4: TIME_TO_FILL_STATUS | U4: OPEN_REQ_AGE_DAYS | V4: OPEN_REQ_SLA_STATUS | W4: TARGET_OPEN_STATUS
A5: REQ-0054 | B5: 45971 | C5: 45972 | D5: Loan Processing | E5: POS-009 | F5: Processing Supervisor | G5: Replacement | H5: 1 | I5: Critical | J5: 46024 | K5: Cancelled | L5: RCR-002 Marco Santos | M5: 35 | N5: =IF($A5="","",IF(OR($K5="Cancelled",$K5="On Hold"),0,IF($K5="Filled",MAX(0,$R5-$C5),MAX(0,TODAY()-$C5)))) -> 0 | O5: =IF($A5="","",IF(OR($K5="Cancelled",$K5="Filled"),"Closed",IF($N5<=$M5,"On Track",IF($N5<=$M5*1.2,"At Risk","Delayed")))) -> Closed | P5: =IF($A5="","",COUNTIFS('06_Recruitment_Pipeline'!$B:$B,$A5,'06_Recruitment_Pipeline'!$G:$G,"Hired")) -> 0 | Q5: =IF($A5="","",MAX(0,$H5-$P5)) -> 1 | R5: =IF($K5="Filled",IFERROR(_xlfn.MAXIFS('06_Recruitment_Pipeline'!$M:$M,'06_Recruitment_Pipeline'!$B:$B,$A5,'06_Recruitment_Pipeline'!$G:$G,"Hired"),""),"") | S5: =IF(tblRequisitions[[#This Row],[REQ_STATUS]]="Filled",IFERROR(tblRequisitions[[#This Row],[FILLED_DATE]]-tblRequisitions[[#This Row],[APPROVAL_DATE]],""),"") | T5: =IF($S5="","",IF($S5<=$M5,"On Track","Delayed")) | U5: =IF($K5="Open",'12_Calculation_Layer'!$B$7-$C5,"") | V5: =IF($K5<>"Open","",IF($U5>$M5,"Delayed",IF($U5>=$M5*0.75,"At Risk","On Track"))) | W5: =IF($K5<>"Open","",IF(COUNTIF($K$5:$K5,"Open")<=12,"Delayed",IF(COUNTIF($K$5:$K5,"Open")<=19,"At Risk","On Track")))
A6: REQ-0072 | B6: 45856 | C6: 45863 | D6: Branch Operations | E6: POS-002 | F6: Branch Supervisor | G6: Project-based | H6: 3 | I6: Low | J6: 45903 | K6: Cancelled | L6: RCR-001 Ana Reyes | M6: 30 | N6: =IF($A6="","",IF($K6="Filled",IFERROR(_xludf.MAXIFS('06_Recruitment_Pipeline'!$M:$M,'06_Recruitment_Pipeline'!$B:$B,$A6,'06_Recruitment_Pipeline'!$G:$G,"Hired")-$C6,TODAY()-$C6),IF(OR($K6="Cancelled",$K6="On Hold"),0,TODAY()-$C6))) -> 0 | O6: =IF($A6="","",IF(OR($K6="Cancelled",$K6="Filled"),"Closed",IF($N6<=$M6,"On Track",IF($N6<=$M6*1.2,"At Risk","Delayed")))) -> Closed | P6: =IF($A6="","",COUNTIFS('06_Recruitment_Pipeline'!$B:$B,$A6,'06_Recruitment_Pipeline'!$G:$G,"Hired")) -> 0 | Q6: =IF($A6="","",MAX(0,$H6-$P6)) -> 3 | R6: =IF($K6="Filled",IFERROR(_xlfn.MAXIFS('06_Recruitment_Pipeline'!$M:$M,'06_Recruitment_Pipeline'!$B:$B,$A6,'06_Recruitment_Pipeline'!$G:$G,"Hired"),""),"") | S6: =IF(tblRequisitions[[#This Row],[REQ_STATUS]]="Filled",IFERROR(tblRequisitions[[#This Row],[FILLED_DATE]]-tblRequisitions[[#This Row],[APPROVAL_DATE]],""),"") | T6: =IF($S6="","",IF($S6<=$M6,"On Track","Delayed")) | U6: =IF($K6="Open",'12_Calculation_Layer'!$B$7-$C6,"") | V6: =IF($K6<>"Open","",IF($U6>$M6,"Delayed",IF($U6>=$M6*0.75,"At Risk","On Track"))) | W6: =IF($K6<>"Open","",IF(COUNTIF($K$5:$K6,"Open")<=12,"Delayed",IF(COUNTIF($K$5:$K6,"Open")<=19,"At Risk","On Track")))
A7: REQ-0079 | B7: 45769 | C7: 45779 | D7: Finance | E7: POS-017 | F7: Finance Analyst | G7: New Headcount | H7: 1 | I7: Low | J7: 45840 | K7: Cancelled | L7: RCR-003 Leah Cruz | M7: 35 | N7: =IF($A7="","",IF($K7="Filled",IFERROR(_xludf.MAXIFS('06_Recruitment_Pipeline'!$M:$M,'06_Recruitment_Pipeline'!$B:$B,$A7,'06_Recruitment_Pipeline'!$G:$G,"Hired")-$C7,TODAY()-$C7),IF(OR($K7="Cancelled",$K7="On Hold"),0,TODAY()-$C7))) -> 0 | O7: =IF($A7="","",IF(OR($K7="Cancelled",$K7="Filled"),"Closed",IF($N7<=$M7,"On Track",IF($N7<=$M7*1.2,"At Risk","Delayed")))) -> Closed | P7: =IF($A7="","",COUNTIFS('06_Recruitment_Pipeline'!$B:$B,$A7,'06_Recruitment_Pipeline'!$G:$G,"Hired")) -> 0 | Q7: =IF($A7="","",MAX(0,$H7-$P7)) -> 1 | R7: =IF($K7="Filled",IFERROR(_xlfn.MAXIFS('06_Recruitment_Pipeline'!$M:$M,'06_Recruitment_Pipeline'!$B:$B,$A7,'06_Recruitment_Pipeline'!$G:$G,"Hired"),""),"") | S7: =IF(tblRequisitions[[#This Row],[REQ_STATUS]]="Filled",IFERROR(tblRequisitions[[#This Row],[FILLED_DATE]]-tblRequisitions[[#This Row],[APPROVAL_DATE]],""),"") | T7: =IF($S7="","",IF($S7<=$M7,"On Track","Delayed")) | U7: =IF($K7="Open",'12_Calculation_Layer'!$B$7-$C7,"") | V7: =IF($K7<>"Open","",IF($U7>$M7,"Delayed",IF($U7>=$M7*0.75,"At Risk","On Track"))) | W7: =IF($K7<>"Open","",IF(COUNTIF($K$5:$K7,"Open")<=12,"Delayed",IF(COUNTIF($K$5:$K7,"Open")<=19,"At Risk","On Track")))
A8: REQ-0001 | B8: 46111 | C8: 46118 | D8: Loan Processing | E8: POS-008 | F8: Processing Specialist | G8: Replacement | H8: 1 | I8: Critical | J8: 46154 | K8: Filled | L8: RCR-003 Leah Cruz | M8: 45 | N8: =IF($A8="","",IF($K8="Filled",IFERROR(_xludf.MAXIFS('06_Recruitment_Pipeline'!$M:$M,'06_Recruitment_Pipeline'!$B:$B,$A8,'06_Recruitment_Pipeline'!$G:$G,"Hired")-$C8,TODAY()-$C8),IF(OR($K8="Cancelled",$K8="On Hold"),0,TODAY()-$C8))) -> 27 | O8: =IF($A8="","",IF(OR($K8="Cancelled",$K8="Filled"),"Closed",IF($N8<=$M8,"On Track",IF($N8<=$M8*1.2,"At Risk","Delayed")))) -> Closed | P8: =IF($A8="","",COUNTIFS('06_Recruitment_Pipeline'!$B:$B,$A8,'06_Recruitment_Pipeline'!$G:$G,"Hired")) -> 2 | Q8: =IF($A8="","",MAX(0,$H8-$P8)) -> 0 | R8: =IF($K8="Filled",IFERROR(_xlfn.MAXIFS('06_Recruitment_Pipeline'!$M:$M,'06_Recruitment_Pipeline'!$B:$B,$A8,'06_Recruitment_Pipeline'!$G:$G,"Hired"),""),"") -> 46178 | S8: =IF(tblRequisitions[[#This Row],[REQ_STATUS]]="Filled",IFERROR(tblRequisitions[[#This Row],[FILLED_DATE]]-tblRequisitions[[#This Row],[APPROVAL_DATE]],""),"") -> 60 | T8: =IF($S8="","",IF($S8<=$M8,"On Track","Delayed")) -> Delayed | U8: =IF($K8="Open",'12_Calculation_Layer'!$B$7-$C8,"") | V8: =IF($K8<>"Open","",IF($U8>$M8,"Delayed",IF($U8>=$M8*0.75,"At Risk","On Track"))) | W8: =IF($K8<>"Open","",IF(COUNTIF($K$5:$K8,"Open")<=12,"Delayed",IF(COUNTIF($K$5:$K8,"Open")<=19,"At Risk","On Track")))
A9: REQ-0002 | B9: 45946 | C9: 45947 | D9: Collections | E9: POS-011 | F9: Collections Officer | G9: New Headcount | H9: 1 | I9: High | J9: 45973 | K9: Filled | L9: RCR-004 Carlo Lim | M9: 20 | N9: =IF($A9="","",IF($K9="Filled",IFERROR(_xludf.MAXIFS('06_Recruitment_Pipeline'!$M:$M,'06_Recruitment_Pipeline'!$B:$B,$A9,'06_Recruitment_Pipeline'!$G:$G,"Hired")-$C9,TODAY()-$C9),IF(OR($K9="Cancelled",$K9="On Hold"),0,TODAY()-$C9))) -> 198 | O9: =IF($A9="","",IF(OR($K9="Cancelled",$K9="Filled"),"Closed",IF($N9<=$M9,"On Track",IF($N9<=$M9*1.2,"At Risk","Delayed")))) -> Closed | P9: =IF($A9="","",COUNTIFS('06_Recruitment_Pipeline'!$B:$B,$A9,'06_Recruitment_Pipeline'!$G:$G,"Hired")) -> 2 | Q9: =IF($A9="","",MAX(0,$H9-$P9)) -> 0 | R9: =IF($K9="Filled",IFERROR(_xlfn.MAXIFS('06_Recruitment_Pipeline'!$M:$M,'06_Recruitment_Pipeline'!$B:$B,$A9,'06_Recruitment_Pipeline'!$G:$G,"Hired"),""),"") -> 46018 | S9: =IF(tblRequisitions[[#This Row],[REQ_STATUS]]="Filled",IFERROR(tblRequisitions[[#This Row],[FILLED_DATE]]-tblRequisitions[[#This Row],[APPROVAL_DATE]],""),"") -> 71 | T9: =IF($S9="","",IF($S9<=$M9,"On Track","Delayed")) -> Delayed | U9: =IF($K9="Open",'12_Calculation_Layer'!$B$7-$C9,"") | V9: =IF($K9<>"Open","",IF($U9>$M9,"Delayed",IF($U9>=$M9*0.75,"At Risk","On Track"))) | W9: =IF($K9<>"Open","",IF(COUNTIF($K$5:$K9,"Open")<=12,"Delayed",IF(COUNTIF($K$5:$K9,"Open")<=19,"At Risk","On Track")))
A10: REQ-0003 | B10: 45941 | C10: 45942 | D10: Customer Service | E10: POS-028 | F10: Customer Support Associate | G10: Project-based | H10: 2 | I10: Critical | J10: 45988 | K10: Filled | L10: RCR-002 Marco Santos | M10: 45 | N10: =IF($A10="","",IF($K10="Filled",IFERROR(_xludf.MAXIFS('06_Recruitment_Pipeline'!$M:$M,'06_Recruitment_Pipeline'!$B:$B,$A10,'06_Recruitment_Pipeline'!$G:$G,"Hired")-$C10,TODAY()-$C10),IF(OR($K10="Cancelled",$K10="On Hold"),0,TODAY()-$C10))) -> 203 | O10: =IF($A10="","",IF(OR($K10="Cancelled",$K10="Filled"),"Closed",IF($N10<=$M10,"On Track",IF($N10<=$M10*1.2,"At Risk","Delayed")))) -> Closed | P10: =IF($A10="","",COUNTIFS('06_Recruitment_Pipeline'!$B:$B,$A10,'06_Recruitment_Pipeline'!$G:$G,"Hired")) -> 3 | Q10: =IF($A10="","",MAX(0,$H10-$P10)) -> 0 | R10: =IF($K10="Filled",IFERROR(_xlfn.MAXIFS('06_Recruitment_Pipeline'!$M:$M,'06_Recruitment_Pipeline'!$B:$B,$A10,'06_Recruitment_Pipeline'!$G:$G,"Hired"),""),"") -> 45986 | S10: =IF(tblRequisitions[[#This Row],[REQ_STATUS]]="Filled",IFERROR(tblRequisitions[[#This Row],[FILLED_DATE]]-tblRequisitions[[#This Row],[APPROVAL_DATE]],""),"") -> 44 | T10: =IF($S10="","",IF($S10<=$M10,"On Track","Delayed")) -> On Track | U10: =IF($K10="Open",'12_Calculation_Layer'!$B$7-$C10,"") | V10: =IF($K10<>"Open","",IF($U10>$M10,"Delayed",IF($U10>=$M10*0.75,"At Risk","On Track"))) | W10: =IF($K10<>"Open","",IF(COUNTIF($K$5:$K10,"Open")<=12,"Delayed",IF(COUNTIF($K$5:$K10,"Open")<=19,"At Risk","On Track")))
A11: REQ-0004 | B11: 45698 | C11: 45705 | D11: Information Technology | E11: POS-023 | F11: Systems Analyst | G11: Project-based | H11: 2 | I11: Medium | J11: 45757 | K11: Filled | L11: RCR-001 Ana Reyes | M11: 35 | N11: =IF($A11="","",IF($K11="Filled",IFERROR(_xludf.MAXIFS('06_Recruitment_Pipeline'!$M:$M,'06_Recruitment_Pipeline'!$B:$B,$A11,'06_Recruitment_Pipeline'!$G:$G,"Hired")-$C11,TODAY()-$C11),IF(OR($K11="Cancelled",$K11="On Hold"),0,TODAY()-$C11))) -> 440 | O11: =IF($A11="","",IF(OR($K11="Cancelled",$K11="Filled"),"Closed",IF($N11<=$M11,"On Track",IF($N11<=$M11*1.2,"At Risk","Delayed")))) -> Closed | P11: =IF($A11="","",COUNTIFS('06_Recruitment_Pipeline'!$B:$B,$A11,'06_Recruitment_Pipeline'!$G:$G,"Hired")) -> 2 | Q11: =IF($A11="","",MAX(0,$H11-$P11)) -> 0 | R11: =IF($K11="Filled",IFERROR(_xlfn.MAXIFS('06_Recruitment_Pipeline'!$M:$M,'06_Recruitment_Pipeline'!$B:$B,$A11,'06_Recruitment_Pipeline'!$G:$G,"Hired"),""),"") -> 45772 | S11: =IF(tblRequisitions[[#This Row],[REQ_STATUS]]="Filled",IFERROR(tblRequisitions[[#This Row],[FILLED_DATE]]-tblRequisitions[[#This Row],[APPROVAL_DATE]],""),"") -> 67 | T11: =IF($S11="","",IF($S11<=$M11,"On Track","Delayed")) -> Delayed | U11: =IF($K11="Open",'12_Calculation_Layer'!$B$7-$C11,"") | V11: =IF($K11<>"Open","",IF($U11>$M11,"Delayed",IF($U11>=$M11*0.75,"At Risk","On Track"))) | W11: =IF($K11<>"Open","",IF(COUNTIF($K$5:$K11,"Open")<=12,"Delayed",IF(COUNTIF($K$5:$K11,"Open")<=19,"At Risk","On Track")))
A12: REQ-0008 | B12: 46089 | C12: 45732 | D12: Human Resources | E12: POS-019 | F12: HR Assistant | G12: New Headcount | H12: 1 | I12: Low | J12: 45769 | K12: Filled | L12: RCR-003 Leah Cruz | M12: 45 | N12: =IF($A12="","",IF($K12="Filled",IFERROR(_xludf.MAXIFS('06_Recruitment_Pipeline'!$M:$M,'06_Recruitment_Pipeline'!$B:$B,$A12,'06_Recruitment_Pipeline'!$G:$G,"Hired")-$C12,TODAY()-$C12),IF(OR($K12="Cancelled",$K12="On Hold"),0,TODAY()-$C12))) -> 413 | O12: =IF($A12="","",IF(OR($K12="Cancelled",$K12="Filled"),"Closed",IF($N12<=$M12,"On Track",IF($N12<=$M12*1.2,"At Risk","Delayed")))) -> Closed | P12: =IF($A12="","",COUNTIFS('06_Recruitment_Pipeline'!$B:$B,$A12,'06_Recruitment_Pipeline'!$G:$G,"Hired")) -> 2 | Q12: =IF($A12="","",MAX(0,$H12-$P12)) -> 0 | R12: =IF($K12="Filled",IFERROR(_xlfn.MAXIFS('06_Recruitment_Pipeline'!$M:$M,'06_Recruitment_Pipeline'!$B:$B,$A12,'06_Recruitment_Pipeline'!$G:$G,"Hired"),""),"") -> 45793 | S12: =IF(tblRequisitions[[#This Row],[REQ_STATUS]]="Filled",IFERROR(tblRequisitions[[#This Row],[FILLED_DATE]]-tblRequisitions[[#This Row],[APPROVAL_DATE]],""),"") -> 61 | T12: =IF($S12="","",IF($S12<=$M12,"On Track","Delayed")) -> Delayed | U12: =IF($K12="Open",'12_Calculation_Layer'!$B$7-$C12,"") | V12: =IF($K12<>"Open","",IF($U12>$M12,"Delayed",IF($U12>=$M12*0.75,"At Risk","On Track"))) | W12: =IF($K12<>"Open","",IF(COUNTIF($K$5:$K12,"Open")<=12,"Delayed",IF(COUNTIF($K$5:$K12,"Open")<=19,"At Risk","On Track")))
A13: REQ-0009 | B13: 46100 | C13: 46102 | D13: Compliance | E13: POS-026 | F13: Compliance Officer | G13: Project-based | H13: 1 | I13: Critical | J13: 46170 | K13: Filled | L13: RCR-001 Ana Reyes | M13: 60 | N13: =IF($A13="","",IF($K13="Filled",IFERROR(_xludf.MAXIFS('06_Recruitment_Pipeline'!$M:$M,'06_Recruitment_Pipeline'!$B:$B,$A13,'06_Recruitment_Pipeline'!$G:$G,"Hired")-$C13,TODAY()-$C13),IF(OR($K13="Cancelled",$K13="On Hold"),0,TODAY()-$C13))) -> 43 | O13: =IF($A13="","",IF(OR($K13="Cancelled",$K13="Filled"),"Closed",IF($N13<=$M13,"On Track",IF($N13<=$M13*1.2,"At Risk","Delayed")))) -> Closed | P13: =IF($A13="","",COUNTIFS('06_Recruitment_Pipeline'!$B:$B,$A13,'06_Recruitment_Pipeline'!$G:$G,"Hired")) -> 1 | Q13: =IF($A13="","",MAX(0,$H13-$P13)) -> 0 | R13: =IF($K13="Filled",IFERROR(_xlfn.MAXIFS('06_Recruitment_Pipeline'!$M:$M,'06_Recruitment_Pipeline'!$B:$B,$A13,'06_Recruitment_Pipeline'!$G:$G,"Hired"),""),"") -> 46154 | S13: =IF(tblRequisitions[[#This Row],[REQ_STATUS]]="Filled",IFERROR(tblRequisitions[[#This Row],[FILLED_DATE]]-tblRequisitions[[#This Row],[APPROVAL_DATE]],""),"") -> 52 | T13: =IF($S13="","",IF($S13<=$M13,"On Track","Delayed")) -> On Track | U13: =IF($K13="Open",'12_Calculation_Layer'!$B$7-$C13,"") | V13: =IF($K13<>"Open","",IF($U13>$M13,"Delayed",IF($U13>=$M13*0.75,"At Risk","On Track"))) | W13: =IF($K13<>"Open","",IF(COUNTIF($K$5:$K13,"Open")<=12,"Delayed",IF(COUNTIF($K$5:$K13,"Open")<=19,"At Risk","On Track")))
A14: REQ-0010 | B14: 46066 | C14: 45707 | D14: Loan Processing | E14: POS-008 | F14: Processing Specialist | G14: New Headcount | H14: 1 | I14: Critical | J14: 45912 | K14: Filled | L14: RCR-003 Leah Cruz | M14: 45 | N14: =IF($A14="","",IF($K14="Filled",IFERROR(_xludf.MAXIFS('06_Recruitment_Pipeline'!$M:$M,'06_Recruitment_Pipeline'!$B:$B,$A14,'06_Recruitment_Pipeline'!$G:$G,"Hired")-$C14,TODAY()-$C14),IF(OR($K14="Cancelled",$K14="On Hold"),0,TODAY()-$C14))) -> 438 | O14: =IF($A14="","",IF(OR($K14="Cancelled",$K14="Filled"),"Closed",IF($N14<=$M14,"On Track",IF($N14<=$M14*1.2,"At Risk","Delayed")))) -> Closed | P14: =IF($A14="","",COUNTIFS('06_Recruitment_Pipeline'!$B:$B,$A14,'06_Recruitment_Pipeline'!$G:$G,"Hired")) -> 1 | Q14: =IF($A14="","",MAX(0,$H14-$P14)) -> 0 | R14: =IF($K14="Filled",IFERROR(_xlfn.MAXIFS('06_Recruitment_Pipeline'!$M:$M,'06_Recruitment_Pipeline'!$B:$B,$A14,'06_Recruitment_Pipeline'!$G:$G,"Hired"),""),"") -> 45918 | S14: =IF(tblRequisitions[[#This Row],[REQ_STATUS]]="Filled",IFERROR(tblRequisitions[[#This Row],[FILLED_DATE]]-tblRequisitions[[#This Row],[APPROVAL_DATE]],""),"") -> 211 | T14: =IF($S14="","",IF($S14<=$M14,"On Track","Delayed")) -> Delayed | U14: =IF($K14="Open",'12_Calculation_Layer'!$B$7-$C14,"") | V14: =IF($K14<>"Open","",IF($U14>$M14,"Delayed",IF($U14>=$M14*0.75,"At Risk","On Track"))) | W14: =IF($K14<>"Open","",IF(COUNTIF($K$5:$K14,"Open")<=12,"Delayed",IF(COUNTIF($K$5:$K14,"Open")<=19,"At Risk","On Track")))
A15: REQ-0014 | B15: 46091 | C15: 46097 | D15: Branch Operations | E15: POS-003 | F15: Branch Manager | G15: New Headcount | H15: 1 | I15: Low | J15: 46111 | K15: Filled | L15: RCR-002 Marco Santos | M15: 60 | N15: =IF($A15="","",IF($K15="Filled",IFERROR(_xludf.MAXIFS('06_Recruitment_Pipeline'!$M:$M,'06_Recruitment_Pipeline'!$B:$B,$A15,'06_Recruitment_Pipeline'!$G:$G,"Hired")-$C15,TODAY()-$C15),IF(OR($K15="Cancelled",$K15="On Hold"),0,TODAY()-$C15))) -> 48 | O15: =IF($A15="","",IF(OR($K15="Cancelled",$K15="Filled"),"Closed",IF($N15<=$M15,"On Track",IF($N15<=$M15*1.2,"At Risk","Delayed")))) -> Closed | P15: =IF($A15="","",COUNTIFS('06_Recruitment_Pipeline'!$B:$B,$A15,'06_Recruitment_Pipeline'!$G:$G,"Hired")) -> 1 | Q15: =IF($A15="","",MAX(0,$H15-$P15)) -> 0 | R15: =IF($K15="Filled",IFERROR(_xlfn.MAXIFS('06_Recruitment_Pipeline'!$M:$M,'06_Recruitment_Pipeline'!$B:$B,$A15,'06_Recruitment_Pipeline'!$G:$G,"Hired"),""),"") -> 46117 | S15: =IF(tblRequisitions[[#This Row],[REQ_STATUS]]="Filled",IFERROR(tblRequisitions[[#This Row],[FILLED_DATE]]-tblRequisitions[[#This Row],[APPROVAL_DATE]],""),"") -> 20 | T15: =IF($S15="","",IF($S15<=$M15,"On Track","Delayed")) -> On Track | U15: =IF($K15="Open",'12_Calculation_Layer'!$B$7-$C15,"") | V15: =IF($K15<>"Open","",IF($U15>$M15,"Delayed",IF($U15>=$M15*0.75,"At Risk","On Track"))) | W15: =IF($K15<>"Open","",IF(COUNTIF($K$5:$K15,"Open")<=12,"Delayed",IF(COUNTIF($K$5:$K15,"Open")<=19,"At Risk","On Track")))
A16: REQ-0015 | B16: 46095 | C16: 46097 | D16: Collections | E16: POS-010 | F16: Collections Associate | G16: Project-based | H16: 1 | I16: Medium | J16: 46130 | K16: Filled | L16: RCR-003 Leah Cruz | M16: 35 | N16: =IF($A16="","",IF($K16="Filled",IFERROR(_xludf.MAXIFS('06_Recruitment_Pipeline'!$M:$M,'06_Recruitment_Pipeline'!$B:$B,$A16,'06_Recruitment_Pipeline'!$G:$G,"Hired")-$C16,TODAY()-$C16),IF(OR($K16="Cancelled",$K16="On Hold"),0,TODAY()-$C16))) -> 48 | O16: =IF($A16="","",IF(OR($K16="Cancelled",$K16="Filled"),"Closed",IF($N16<=$M16,"On Track",IF($N16<=$M16*1.2,"At Risk","Delayed")))) -> Closed | P16: =IF($A16="","",COUNTIFS('06_Recruitment_Pipeline'!$B:$B,$A16,'06_Recruitment_Pipeline'!$G:$G,"Hired")) -> 1 | Q16: =IF($A16="","",MAX(0,$H16-$P16)) -> 0 | R16: =IF($K16="Filled",IFERROR(_xlfn.MAXIFS('06_Recruitment_Pipeline'!$M:$M,'06_Recruitment_Pipeline'!$B:$B,$A16,'06_Recruitment_Pipeline'!$G:$G,"Hired"),""),"") -> 46160 | S16: =IF(tblRequisitions[[#This Row],[REQ_STATUS]]="Filled",IFERROR(tblRequisitions[[#This Row],[FILLED_DATE]]-tblRequisitions[[#This Row],[APPROVAL_DATE]],""),"") -> 63 | T16: =IF($S16="","",IF($S16<=$M16,"On Track","Delayed")) -> Delayed | U16: =IF($K16="Open",'12_Calculation_Layer'!$B$7-$C16,"") | V16: =IF($K16<>"Open","",IF($U16>$M16,"Delayed",IF($U16>=$M16*0.75,"At Risk","On Track"))) | W16: =IF($K16<>"Open","",IF(COUNTIF($K$5:$K16,"Open")<=12,"Delayed",IF(COUNTIF($K$5:$K16,"Open")<=19,"At Risk","On Track")))
A17: REQ-0018 | B17: 46111 | C17: 45720 | D17: Branch Operations | E17: POS-002 | F17: Branch Supervisor | G17: New Headcount | H17: 2 | I17: Medium | J17: 45719 | K17: Filled | L17: RCR-002 Marco Santos | M17: 30 | N17: =IF($A17="","",IF($K17="Filled",IFERROR(_xludf.MAXIFS('06_Recruitment_Pipeline'!$M:$M,'06_Recruitment_Pipeline'!$B:$B,$A17,'06_Recruitment_Pipeline'!$G:$G,"Hired")-$C17,TODAY()-$C17),IF(OR($K17="Cancelled",$K17="On Hold"),0,TODAY()-$C17))) -> 425 | O17: =IF($A17="","",IF(OR($K17="Cancelled",$K17="Filled"),"Closed",IF($N17<=$M17,"On Track",IF($N17<=$M17*1.2,"At Risk","Delayed")))) -> Closed | P17: =IF($A17="","",COUNTIFS('06_Recruitment_Pipeline'!$B:$B,$A17,'06_Recruitment_Pipeline'!$G:$G,"Hired")) -> 2 | Q17: =IF($A17="","",MAX(0,$H17-$P17)) -> 0 | R17: =IF($K17="Filled",IFERROR(_xlfn.MAXIFS('06_Recruitment_Pipeline'!$M:$M,'06_Recruitment_Pipeline'!$B:$B,$A17,'06_Recruitment_Pipeline'!$G:$G,"Hired"),""),"") -> 45730 | S17: =IF(tblRequisitions[[#This Row],[REQ_STATUS]]="Filled",IFERROR(tblRequisitions[[#This Row],[FILLED_DATE]]-tblRequisitions[[#This Row],[APPROVAL_DATE]],""),"") -> 10 | T17: =IF($S17="","",IF($S17<=$M17,"On Track","Delayed")) -> On Track | U17: =IF($K17="Open",'12_Calculation_Layer'!$B$7-$C17,"") | V17: =IF($K17<>"Open","",IF($U17>$M17,"Delayed",IF($U17>=$M17*0.75,"At Risk","On Track"))) | W17: =IF($K17<>"Open","",IF(COUNTIF($K$5:$K17,"Open")<=12,"Delayed",IF(COUNTIF($K$5:$K17,"Open")<=19,"At Risk","On Track")))
... A84: REQ-0080 | B84: 46125 | C84: 46127 | D84: Information Technology | E84: POS-022 | F84: IT Support Specialist | G84: Project-based | H84: 2 | I84: High | J84: 46018 | K84: Open | L84: RCR-004 Carlo Lim | M84: 30 | N84: =IF($A84="","",IF($K84="Filled",IFERROR(_xludf.MAXIFS('06_Recruitment_Pipeline'!$M:$M,'06_Recruitment_Pipeline'!$B:$B,$A84,'06_Recruitment_Pipeline'!$G:$G,"Hired")-$C84,TODAY()-$C84),IF(OR($K84="Cancelled",$K84="On Hold"),0,TODAY()-$C84))) -> 18 | O84: =IF($A84="","",IF(OR($K84="Cancelled",$K84="Filled"),"Closed",IF($N84<=$M84,"On Track",IF($N84<=$M84*1.2,"At Risk","Delayed")))) -> On Track | P84: =IF($A84="","",COUNTIFS('06_Recruitment_Pipeline'!$B:$B,$A84,'06_Recruitment_Pipeline'!$G:$G,"Hired")) -> 0 | Q84: =IF($A84="","",MAX(0,$H84-$P84)) -> 2 | R84: =IF($K84="Filled",IFERROR(_xlfn.MAXIFS('06_Recruitment_Pipeline'!$M:$M,'06_Recruitment_Pipeline'!$B:$B,$A84,'06_Recruitment_Pipeline'!$G:$G,"Hired"),""),"") | S84: =IF(tblRequisitions[[#This Row],[REQ_STATUS]]="Filled",IFERROR(tblRequisitions[[#This Row],[FILLED_DATE]]-tblRequisitions[[#This Row],[APPROVAL_DATE]],""),"") | T84: =IF($S84="","",IF($S84<=$M84,"On Track","Delayed")) | U84: =IF($K84="Open",'12_Calculation_Layer'!$B$7-$C84,"") -> 15 | V84: =IF($K84<>"Open","",IF($U84>$M84,"Delayed",IF($U84>=$M84*0.75,"At Risk","On Track"))) -> On Track | W84: =IF($K84<>"Open","",IF(COUNTIF($K$5:$K84,"Open")<=12,"Delayed",IF(COUNTIF($K$5:$K84,"Open")<=19,"At Risk","On Track"))) -> On Track

Sheet 06_Recruitment_Pipeline
A1: Recruitment Pipeline
A2: Candidate-level tracking from application to hire, rejection, or withdrawal.
A4: APPLICATION_ID | B4: REQ_ID | C4: CANDIDATE_ID | D4: CANDIDATE_NAME | E4: SOURCE | F4: APPLICATION_DATE | G4: CURRENT_STAGE | H4: STAGE_DATE | I4: RECRUITER | J4: INTERVIEWER | K4: OFFER_DATE | L4: OFFER_STATUS | M4: HIRE_DATE | N4: REJECTION_REASON | O4: WITHDRAWAL_REASON | P4: DAYS_IN_PIPELINE | Q4: PIPELINE_STATUS | R4: STAGE_AGING_FLAG | S4: TIME_TO_HIRE_DAYS | T4: REQ_DEPARTMENT | U4: REQ_EXISTS_FLAG
A5: APP-00001 | B5: REQ-0001 | C5: CAND-00001 | D5: Camille Navarro | E5: Agency | F5: 46125 | G5: Hired | H5: 46161 | I5: RCR-003 Leah Cruz | J5: Panel Interview | K5: 46158 | L5: Accepted | M5: 46165 | P5: =IF($A5="","",IF($G5="Hired",$M5-$F5,IF(OR($G5="Rejected",$G5="Withdrawn"),$H5-$F5,TODAY()-$F5))) -> 40 | Q5: =IF($A5="","",IF(OR($G5="Hired",$G5="Rejected",$G5="Withdrawn"),"Closed",IF($P5>30,"Stale","Active"))) -> Closed | R5: =IF($A5="","",IF($Q5="Closed","Closed",IF($P5<=14,"On Track",IF($P5<=30,"At Risk","Delayed")))) -> Closed | S5: =IF($A5="","",IF($G5="Hired",$M5-$F5,"")) -> 40 | T5: =IFERROR(_xlfn.XLOOKUP(tblRecruitmentPipeline[[#This Row],[REQ_ID]],tblRequisitions[REQ_ID],tblRequisitions[DEPARTMENT],""),"") -> Loan Processing | U5: =IF(tblRecruitmentPipeline[[#This Row],[REQ_DEPARTMENT]]="","No","Yes") -> Yes
A6: APP-00002 | B6: REQ-0001 | C6: CAND-00002 | D6: Janine Ramos | E6: Employee Referral | F6: 46143 | G6: Final Interview | H6: 46166 | I6: RCR-003 Leah Cruz | J6: Panel Interview | L6: Not Offered | P6: =IF($A6="","",IF($G6="Hired",$M6-$F6,IF(OR($G6="Rejected",$G6="Withdrawn"),$H6-$F6,TODAY()-$F6))) -> 2 | Q6: =IF($A6="","",IF(OR($G6="Hired",$G6="Rejected",$G6="Withdrawn"),"Closed",IF($P6>30,"Stale","Active"))) -> Active | R6: =IF($A6="","",IF($Q6="Closed","Closed",IF($P6<=14,"On Track",IF($P6<=30,"At Risk","Delayed")))) -> On Track | S6: =IF($A6="","",IF($G6="Hired",$M6-$F6,"")) | T6: =IFERROR(_xlfn.XLOOKUP(tblRecruitmentPipeline[[#This Row],[REQ_ID]],tblRequisitions[REQ_ID],tblRequisitions[DEPARTMENT],""),"") -> Loan Processing | U6: =IF(tblRecruitmentPipeline[[#This Row],[REQ_DEPARTMENT]]="","No","Yes") -> Yes
A7: APP-00003 | B7: REQ-0001 | C7: CAND-00003 | D7: Janine Cruz | E7: LinkedIn | F7: 46123 | G7: Rejected | H7: 46135 | I7: RCR-003 Leah Cruz | J7: Panel Interview | L7: Not Offered | N7: Not qualified | P7: =IF($A7="","",IF($G7="Hired",$M7-$F7,IF(OR($G7="Rejected",$G7="Withdrawn"),$H7-$F7,TODAY()-$F7))) -> 12 | Q7: =IF($A7="","",IF(OR($G7="Hired",$G7="Rejected",$G7="Withdrawn"),"Closed",IF($P7>30,"Stale","Active"))) -> Closed | R7: =IF($A7="","",IF($Q7="Closed","Closed",IF($P7<=14,"On Track",IF($P7<=30,"At Risk","Delayed")))) -> Closed | S7: =IF($A7="","",IF($G7="Hired",$M7-$F7,"")) | T7: =IFERROR(_xlfn.XLOOKUP(tblRecruitmentPipeline[[#This Row],[REQ_ID]],tblRequisitions[REQ_ID],tblRequisitions[DEPARTMENT],""),"") -> Loan Processing | U7: =IF(tblRecruitmentPipeline[[#This Row],[REQ_DEPARTMENT]]="","No","Yes") -> Yes
A8: APP-00004 | B8: REQ-0001 | C8: CAND-00004 | D8: Lara Gonzales | E8: Company Website | F8: 46131 | G8: Rejected | H8: 46160 | I8: RCR-003 Leah Cruz | J8: Hiring Manager | L8: Not Offered | N8: Not qualified | P8: =IF($A8="","",IF($G8="Hired",$M8-$F8,IF(OR($G8="Rejected",$G8="Withdrawn"),$H8-$F8,TODAY()-$F8))) -> 29 | Q8: =IF($A8="","",IF(OR($G8="Hired",$G8="Rejected",$G8="Withdrawn"),"Closed",IF($P8>30,"Stale","Active"))) -> Closed | R8: =IF($A8="","",IF($Q8="Closed","Closed",IF($P8<=14,"On Track",IF($P8<=30,"At Risk","Delayed")))) -> Closed | S8: =IF($A8="","",IF($G8="Hired",$M8-$F8,"")) | T8: =IFERROR(_xlfn.XLOOKUP(tblRecruitmentPipeline[[#This Row],[REQ_ID]],tblRequisitions[REQ_ID],tblRequisitions[DEPARTMENT],""),"") -> Loan Processing | U8: =IF(tblRecruitmentPipeline[[#This Row],[REQ_DEPARTMENT]]="","No","Yes") -> Yes
A9: APP-00005 | B9: REQ-0001 | C9: CAND-00005 | D9: Angela Reyes | E9: JobStreet | F9: 46127 | G9: Applied | H9: 46174 | I9: RCR-003 Leah Cruz | J9: Hiring Manager | L9: Not Offered | P9: =IF($A9="","",IF($G9="Hired",$M9-$F9,IF(OR($G9="Rejected",$G9="Withdrawn"),$H9-$F9,TODAY()-$F9))) -> 18 | Q9: =IF($A9="","",IF(OR($G9="Hired",$G9="Rejected",$G9="Withdrawn"),"Closed",IF($P9>30,"Stale","Active"))) -> Active | R9: =IF($A9="","",IF($Q9="Closed","Closed",IF($P9<=14,"On Track",IF($P9<=30,"At Risk","Delayed")))) -> At Risk | S9: =IF($A9="","",IF($G9="Hired",$M9-$F9,"")) | T9: =IFERROR(_xlfn.XLOOKUP(tblRecruitmentPipeline[[#This Row],[REQ_ID]],tblRequisitions[REQ_ID],tblRequisitions[DEPARTMENT],""),"") -> Loan Processing | U9: =IF(tblRecruitmentPipeline[[#This Row],[REQ_DEPARTMENT]]="","No","Yes") -> Yes
A10: APP-00006 | B10: REQ-0001 | C10: CAND-00006 | D10: Ethan Cruz | E10: Agency | F10: 46121 | G10: Screened | H10: 46139 | I10: RCR-003 Leah Cruz | J10: Hiring Manager | L10: Not Offered | P10: =IF($A10="","",IF($G10="Hired",$M10-$F10,IF(OR($G10="Rejected",$G10="Withdrawn"),$H10-$F10,TODAY()-$F10))) -> 24 | Q10: =IF($A10="","",IF(OR($G10="Hired",$G10="Rejected",$G10="Withdrawn"),"Closed",IF($P10>30,"Stale","Active"))) -> Active | R10: =IF($A10="","",IF($Q10="Closed","Closed",IF($P10<=14,"On Track",IF($P10<=30,"At Risk","Delayed")))) -> At Risk | S10: =IF($A10="","",IF($G10="Hired",$M10-$F10,"")) | T10: =IFERROR(_xlfn.XLOOKUP(tblRecruitmentPipeline[[#This Row],[REQ_ID]],tblRequisitions[REQ_ID],tblRequisitions[DEPARTMENT],""),"") -> Loan Processing | U10: =IF(tblRecruitmentPipeline[[#This Row],[REQ_DEPARTMENT]]="","No","Yes") -> Yes
A11: APP-00007 | B11: REQ-0001 | C11: CAND-00007 | D11: Janine Castillo | E11: Facebook | F11: 46134 | G11: Interview | H11: 46164 | I11: RCR-003 Leah Cruz | J11: Department Head | L11: Not Offered | P11: =IF($A11="","",IF($G11="Hired",$M11-$F11,IF(OR($G11="Rejected",$G11="Withdrawn"),$H11-$F11,TODAY()-$F11))) -> 11 | Q11: =IF($A11="","",IF(OR($G11="Hired",$G11="Rejected",$G11="Withdrawn"),"Closed",IF($P11>30,"Stale","Active"))) -> Active | R11: =IF($A11="","",IF($Q11="Closed","Closed",IF($P11<=14,"On Track",IF($P11<=30,"At Risk","Delayed")))) -> On Track | S11: =IF($A11="","",IF($G11="Hired",$M11-$F11,"")) | T11: =IFERROR(_xlfn.XLOOKUP(tblRecruitmentPipeline[[#This Row],[REQ_ID]],tblRequisitions[REQ_ID],tblRequisitions[DEPARTMENT],""),"") -> Loan Processing | U11: =IF(tblRecruitmentPipeline[[#This Row],[REQ_DEPARTMENT]]="","No","Yes") -> Yes
A12: APP-00008 | B12: REQ-0001 | C12: CAND-00008 | D12: Ethan Santos | E12: Company Website | F12: 46119 | G12: Interview | H12: 46128 | I12: RCR-003 Leah Cruz | J12: Panel Interview | L12: Not Offered | P12: =IF($A12="","",IF($G12="Hired",$M12-$F12,IF(OR($G12="Rejected",$G12="Withdrawn"),$H12-$F12,TODAY()-$F12))) -> 26 | Q12: =IF($A12="","",IF(OR($G12="Hired",$G12="Rejected",$G12="Withdrawn"),"Closed",IF($P12>30,"Stale","Active"))) -> Active | R12: =IF($A12="","",IF($Q12="Closed","Closed",IF($P12<=14,"On Track",IF($P12<=30,"At Risk","Delayed")))) -> At Risk | S12: =IF($A12="","",IF($G12="Hired",$M12-$F12,"")) | T12: =IFERROR(_xlfn.XLOOKUP(tblRecruitmentPipeline[[#This Row],[REQ_ID]],tblRequisitions[REQ_ID],tblRequisitions[DEPARTMENT],""),"") -> Loan Processing | U12: =IF(tblRecruitmentPipeline[[#This Row],[REQ_DEPARTMENT]]="","No","Yes") -> Yes
A13: APP-00009 | B13: REQ-0001 | C13: CAND-00009 | D13: Andrea Navarro | E13: Agency | F13: 46122 | G13: Hired | H13: 46161 | I13: RCR-003 Leah Cruz | J13: Hiring Manager | K13: 46160 | L13: Accepted | M13: 46178 | P13: =IF($A13="","",IF($G13="Hired",$M13-$F13,IF(OR($G13="Rejected",$G13="Withdrawn"),$H13-$F13,TODAY()-$F13))) -> 56 | Q13: =IF($A13="","",IF(OR($G13="Hired",$G13="Rejected",$G13="Withdrawn"),"Closed",IF($P13>30,"Stale","Active"))) -> Closed | R13: =IF($A13="","",IF($Q13="Closed","Closed",IF($P13<=14,"On Track",IF($P13<=30,"At Risk","Delayed")))) -> Closed | S13: =IF($A13="","",IF($G13="Hired",$M13-$F13,"")) -> 56 | T13: =IFERROR(_xlfn.XLOOKUP(tblRecruitmentPipeline[[#This Row],[REQ_ID]],tblRequisitions[REQ_ID],tblRequisitions[DEPARTMENT],""),"") -> Loan Processing | U13: =IF(tblRecruitmentPipeline[[#This Row],[REQ_DEPARTMENT]]="","No","Yes") -> Yes
A14: APP-00010 | B14: REQ-0002 | C14: CAND-00010 | D14: Bea Santos | E14: Facebook | F14: 45966 | G14: Hired | H14: 45986 | I14: RCR-004 Carlo Lim | J14: Hiring Manager | K14: 45982 | L14: Accepted | M14: 45995 | P14: =IF($A14="","",IF($G14="Hired",$M14-$F14,IF(OR($G14="Rejected",$G14="Withdrawn"),$H14-$F14,TODAY()-$F14))) -> 29 | Q14: =IF($A14="","",IF(OR($G14="Hired",$G14="Rejected",$G14="Withdrawn"),"Closed",IF($P14>30,"Stale","Active"))) -> Closed | R14: =IF($A14="","",IF($Q14="Closed","Closed",IF($P14<=14,"On Track",IF($P14<=30,"At Risk","Delayed")))) -> Closed | S14: =IF($A14="","",IF($G14="Hired",$M14-$F14,"")) -> 29 | T14: =IFERROR(_xlfn.XLOOKUP(tblRecruitmentPipeline[[#This Row],[REQ_ID]],tblRequisitions[REQ_ID],tblRequisitions[DEPARTMENT],""),"") -> Collections | U14: =IF(tblRecruitmentPipeline[[#This Row],[REQ_DEPARTMENT]]="","No","Yes") -> Yes
A15: APP-00011 | B15: REQ-0002 | C15: CAND-00011 | D15: Bea Mendoza | E15: Company Website | F15: 45981 | G15: Screened | H15: 46030 | I15: RCR-004 Carlo Lim | J15: Hiring Manager | L15: Not Offered | P15: =IF($A15="","",IF($G15="Hired",$M15-$F15,IF(OR($G15="Rejected",$G15="Withdrawn"),$H15-$F15,TODAY()-$F15))) -> 164 | Q15: =IF($A15="","",IF(OR($G15="Hired",$G15="Rejected",$G15="Withdrawn"),"Closed",IF($P15>30,"Stale","Active"))) -> Stale | R15: =IF($A15="","",IF($Q15="Closed","Closed",IF($P15<=14,"On Track",IF($P15<=30,"At Risk","Delayed")))) -> Delayed | S15: =IF($A15="","",IF($G15="Hired",$M15-$F15,"")) | T15: =IFERROR(_xlfn.XLOOKUP(tblRecruitmentPipeline[[#This Row],[REQ_ID]],tblRequisitions[REQ_ID],tblRequisitions[DEPARTMENT],""),"") -> Collections | U15: =IF(tblRecruitmentPipeline[[#This Row],[REQ_DEPARTMENT]]="","No","Yes") -> Yes
A16: APP-00012 | B16: REQ-0002 | C16: CAND-00012 | D16: Ethan Lim | E16: JobStreet | F16: 45966 | G16: Hired | H16: 46014 | I16: RCR-004 Carlo Lim | J16: Hiring Manager | K16: 46011 | L16: Accepted | M16: 46018 | P16: =IF($A16="","",IF($G16="Hired",$M16-$F16,IF(OR($G16="Rejected",$G16="Withdrawn"),$H16-$F16,TODAY()-$F16))) -> 52 | Q16: =IF($A16="","",IF(OR($G16="Hired",$G16="Rejected",$G16="Withdrawn"),"Closed",IF($P16>30,"Stale","Active"))) -> Closed | R16: =IF($A16="","",IF($Q16="Closed","Closed",IF($P16<=14,"On Track",IF($P16<=30,"At Risk","Delayed")))) -> Closed | S16: =IF($A16="","",IF($G16="Hired",$M16-$F16,"")) -> 52 | T16: =IFERROR(_xlfn.XLOOKUP(tblRecruitmentPipeline[[#This Row],[REQ_ID]],tblRequisitions[REQ_ID],tblRequisitions[DEPARTMENT],""),"") -> Collections | U16: =IF(tblRecruitmentPipeline[[#This Row],[REQ_DEPARTMENT]]="","No","Yes") -> Yes
A17: APP-00013 | B17: REQ-0002 | C17: CAND-00013 | D17: Luis Ramos | E17: Company Website | F17: 45947 | G17: Offer | H17: 45974 | I17: RCR-004 Carlo Lim | J17: Panel Interview | K17: 45969 | L17: Pending | P17: =IF($A17="","",IF($G17="Hired",$M17-$F17,IF(OR($G17="Rejected",$G17="Withdrawn"),$H17-$F17,TODAY()-$F17))) -> 198 | Q17: =IF($A17="","",IF(OR($G17="Hired",$G17="Rejected",$G17="Withdrawn"),"Closed",IF($P17>30,"Stale","Active"))) -> Stale | R17: =IF($A17="","",IF($Q17="Closed","Closed",IF($P17<=14,"On Track",IF($P17<=30,"At Risk","Delayed")))) -> Delayed | S17: =IF($A17="","",IF($G17="Hired",$M17-$F17,"")) | T17: =IFERROR(_xlfn.XLOOKUP(tblRecruitmentPipeline[[#This Row],[REQ_ID]],tblRequisitions[REQ_ID],tblRequisitions[DEPARTMENT],""),"") -> Collections | U17: =IF(tblRecruitmentPipeline[[#This Row],[REQ_DEPARTMENT]]="","No","Yes") -> Yes
A18: APP-00014 | B18: REQ-0002 | C18: CAND-00014 | D18: Camille Lim | E18: LinkedIn | F18: 45969 | G18: Screened | H18: 46012 | I18: RCR-004 Carlo Lim | J18: Hiring Manager | L18: Not Offered | P18: =IF($A18="","",IF($G18="Hired",$M18-$F18,IF(OR($G18="Rejected",$G18="Withdrawn"),$H18-$F18,TODAY()-$F18))) -> 176 | Q18: =IF($A18="","",IF(OR($G18="Hired",$G18="Rejected",$G18="Withdrawn"),"Closed",IF($P18>30,"Stale","Active"))) -> Stale | R18: =IF($A18="","",IF($Q18="Closed","Closed",IF($P18<=14,"On Track",IF($P18<=30,"At Risk","Delayed")))) -> Delayed | S18: =IF($A18="","",IF($G18="Hired",$M18-$F18,"")) | T18: =IFERROR(_xlfn.XLOOKUP(tblRecruitmentPipeline[[#This Row],[REQ_ID]],tblRequisitions[REQ_ID],tblRequisitions[DEPARTMENT],""),"") -> Collections | U18: =IF(tblRecruitmentPipeline[[#This Row],[REQ_DEPARTMENT]]="","No","Yes") -> Yes
A19: APP-00015 | B19: REQ-0003 | C19: CAND-00015 | D19: Carlo Villanueva | E19: Company Website | F19: 45958 | G19: Hired | H19: 45971 | I19: RCR-002 Marco Santos | J19: Panel Interview | K19: 45966 | L19: Accepted | M19: 45986 | P19: =IF($A19="","",IF($G19="Hired",$M19-$F19,IF(OR($G19="Rejected",$G19="Withdrawn"),$H19-$F19,TODAY()-$F19))) -> 28 | Q19: =IF($A19="","",IF(OR($G19="Hired",$G19="Rejected",$G19="Withdrawn"),"Closed",IF($P19>30,"Stale","Active"))) -> Closed | R19: =IF($A19="","",IF($Q19="Closed","Closed",IF($P19<=14,"On Track",IF($P19<=30,"At Risk","Delayed")))) -> Closed | S19: =IF($A19="","",IF($G19="Hired",$M19-$F19,"")) -> 28 | T19: =IFERROR(_xlfn.XLOOKUP(tblRecruitmentPipeline[[#This Row],[REQ_ID]],tblRequisitions[REQ_ID],tblRequisitions[DEPARTMENT],""),"") -> Customer Service | U19: =IF(tblRecruitmentPipeline[[#This Row],[REQ_DEPARTMENT]]="","No","Yes") -> Yes
A20: APP-00016 | B20: REQ-0003 | C20: CAND-00016 | D20: Lara Lopez | E20: Employee Referral | F20: 45946 | G20: Hired | H20: 45952 | I20: RCR-002 Marco Santos | J20: Department Head | K20: 45949 | L20: Accepted | M20: 45957 | P20: =IF($A20="","",IF($G20="Hired",$M20-$F20,IF(OR($G20="Rejected",$G20="Withdrawn"),$H20-$F20,TODAY()-$F20))) -> 11 | Q20: =IF($A20="","",IF(OR($G20="Hired",$G20="Rejected",$G20="Withdrawn"),"Closed",IF($P20>30,"Stale","Active"))) -> Closed | R20: =IF($A20="","",IF($Q20="Closed","Closed",IF($P20<=14,"On Track",IF($P20<=30,"At Risk","Delayed")))) -> Closed | S20: =IF($A20="","",IF($G20="Hired",$M20-$F20,"")) -> 11 | T20: =IFERROR(_xlfn.XLOOKUP(tblRecruitmentPipeline[[#This Row],[REQ_ID]],tblRequisitions[REQ_ID],tblRequisitions[DEPARTMENT],""),"") -> Customer Service | U20: =IF(tblRecruitmentPipeline[[#This Row],[REQ_DEPARTMENT]]="","No","Yes") -> Yes
A21: APP-00017 | B21: REQ-0003 | C21: CAND-00017 | D21: Gabriel Cruz | E21: LinkedIn | F21: 45950 | G21: Hired | H21: 45967 | I21: RCR-002 Marco Santos | J21: Department Head | K21: 45966 | L21: Accepted | M21: 45977 | P21: =IF($A21="","",IF($G21="Hired",$M21-$F21,IF(OR($G21="Rejected",$G21="Withdrawn"),$H21-$F21,TODAY()-$F21))) -> 27 | Q21: =IF($A21="","",IF(OR($G21="Hired",$G21="Rejected",$G21="Withdrawn"),"Closed",IF($P21>30,"Stale","Active"))) -> Closed | R21: =IF($A21="","",IF($Q21="Closed","Closed",IF($P21<=14,"On Track",IF($P21<=30,"At Risk","Delayed")))) -> Closed | S21: =IF($A21="","",IF($G21="Hired",$M21-$F21,"")) -> 27 | T21: =IFERROR(_xlfn.XLOOKUP(tblRecruitmentPipeline[[#This Row],[REQ_ID]],tblRequisitions[REQ_ID],tblRequisitions[DEPARTMENT],""),"") -> Customer Service | U21: =IF(tblRecruitmentPipeline[[#This Row],[REQ_DEPARTMENT]]="","No","Yes") -> Yes
A22: APP-00018 | B22: REQ-0003 | C22: CAND-00018 | D22: Martin Mendoza | E22: Company Website | F22: 45973 | G22: Final Interview | H22: 46014 | I22: RCR-002 Marco Santos | J22: Panel Interview | L22: Not Offered | P22: =IF($A22="","",IF($G22="Hired",$M22-$F22,IF(OR($G22="Rejected",$G22="Withdrawn"),$H22-$F22,TODAY()-$F22))) -> 172 | Q22: =IF($A22="","",IF(OR($G22="Hired",$G22="Rejected",$G22="Withdrawn"),"Closed",IF($P22>30,"Stale","Active"))) -> Stale | R22: =IF($A22="","",IF($Q22="Closed","Closed",IF($P22<=14,"On Track",IF($P22<=30,"At Risk","Delayed")))) -> Delayed | S22: =IF($A22="","",IF($G22="Hired",$M22-$F22,"")) | T22: =IFERROR(_xlfn.XLOOKUP(tblRecruitmentPipeline[[#This Row],[REQ_ID]],tblRequisitions[REQ_ID],tblRequisitions[DEPARTMENT],""),"") -> Customer Service | U22: =IF(tblRecruitmentPipeline[[#This Row],[REQ_DEPARTMENT]]="","No","Yes") -> Yes
A23: APP-00019 | B23: REQ-0004 | C23: CAND-00019 | D23: Angela Torres | E23: Walk-in | F23: 45728 | G23: Hired | H23: 45757 | I23: RCR-001 Ana Reyes | J23: Hiring Manager | K23: 45755 | L23: Accepted | M23: 45762 | P23: =IF($A23="","",IF($G23="Hired",$M23-$F23,IF(OR($G23="Rejected",$G23="Withdrawn"),$H23-$F23,TODAY()-$F23))) -> 34 | Q23: =IF($A23="","",IF(OR($G23="Hired",$G23="Rejected",$G23="Withdrawn"),"Closed",IF($P23>30,"Stale","Active"))) -> Closed | R23: =IF($A23="","",IF($Q23="Closed","Closed",IF($P23<=14,"On Track",IF($P23<=30,"At Risk","Delayed")))) -> Closed | S23: =IF($A23="","",IF($G23="Hired",$M23-$F23,"")) -> 34 | T23: =IFERROR(_xlfn.XLOOKUP(tblRecruitmentPipeline[[#This Row],[REQ_ID]],tblRequisitions[REQ_ID],tblRequisitions[DEPARTMENT],""),"") -> Information Technology | U23: =IF(tblRecruitmentPipeline[[#This Row],[REQ_DEPARTMENT]]="","No","Yes") -> Yes
A24: APP-00020 | B24: REQ-0004 | C24: CAND-00020 | D24: Patrick Bautista | E24: Facebook | F24: 45732 | G24: Hired | H24: 45757 | I24: RCR-001 Ana Reyes | J24: Department Head | K24: 45755 | L24: Accepted | M24: 45772 | P24: =IF($A24="","",IF($G24="Hired",$M24-$F24,IF(OR($G24="Rejected",$G24="Withdrawn"),$H24-$F24,TODAY()-$F24))) -> 40 | Q24: =IF($A24="","",IF(OR($G24="Hired",$G24="Rejected",$G24="Withdrawn"),"Closed",IF($P24>30,"Stale","Active"))) -> Closed | R24: =IF($A24="","",IF($Q24="Closed","Closed",IF($P24<=14,"On Track",IF($P24<=30,"At Risk","Delayed")))) -> Closed | S24: =IF($A24="","",IF($G24="Hired",$M24-$F24,"")) -> 40 | T24: =IFERROR(_xlfn.XLOOKUP(tblRecruitmentPipeline[[#This Row],[REQ_ID]],tblRequisitions[REQ_ID],tblRequisitions[DEPARTMENT],""),"") -> Information Technology | U24: =IF(tblRecruitmentPipeline[[#This Row],[REQ_DEPARTMENT]]="","No","Yes") -> Yes
A25: APP-00021 | B25: REQ-0004 | C25: CAND-00021 | D25: Julius Garcia | E25: LinkedIn | F25: 45733 | G25: Interview | H25: 45754 | I25: RCR-001 Ana Reyes | J25: Panel Interview | L25: Not Offered | P25: =IF($A25="","",IF($G25="Hired",$M25-$F25,IF(OR($G25="Rejected",$G25="Withdrawn"),$H25-$F25,TODAY()-$F25))) -> 412 | Q25: =IF($A25="","",IF(OR($G25="Hired",$G25="Rejected",$G25="Withdrawn"),"Closed",IF($P25>30,"Stale","Active"))) -> Stale | R25: =IF($A25="","",IF($Q25="Closed","Closed",IF($P25<=14,"On Track",IF($P25<=30,"At Risk","Delayed")))) -> Delayed | S25: =IF($A25="","",IF($G25="Hired",$M25-$F25,"")) | T25: =IFERROR(_xlfn.XLOOKUP(tblRecruitmentPipeline[[#This Row],[REQ_ID]],tblRequisitions[REQ_ID],tblRequisitions[DEPARTMENT],""),"") -> Information Technology | U25: =IF(tblRecruitmentPipeline[[#This Row],[REQ_DEPARTMENT]]="","No","Yes") -> Yes
A26: APP-00022 | B26: REQ-0004 | C26: CAND-00022 | D26: Diana Cruz | E26: Company Website | F26: 45710 | G26: Rejected | H26: 45720 | I26: RCR-001 Ana Reyes | J26: Hiring Manager | L26: Not Offered | N26: Compensation mismatch | P26: =IF($A26="","",IF($G26="Hired",$M26-$F26,IF(OR($G26="Rejected",$G26="Withdrawn"),$H26-$F26,TODAY()-$F26))) -> 10 | Q26: =IF($A26="","",IF(OR($G26="Hired",$G26="Rejected",$G26="Withdrawn"),"Closed",IF($P26>30,"Stale","Active"))) -> Closed | R26: =IF($A26="","",IF($Q26="Closed","Closed",IF($P26<=14,"On Track",IF($P26<=30,"At Risk","Delayed")))) -> Closed | S26: =IF($A26="","",IF($G26="Hired",$M26-$F26,"")) | T26: =IFERROR(_xlfn.XLOOKUP(tblRecruitmentPipeline[[#This Row],[REQ_ID]],tblRequisitions[REQ_ID],tblRequisitions[DEPARTMENT],""),"") -> Information Technology | U26: =IF(tblRecruitmentPipeline[[#This Row],[REQ_DEPARTMENT]]="","No","Yes") -> Yes
A27: APP-00023 | B27: REQ-0005 | C27: CAND-00023 | D27: Rhea Ramos | E27: JobStreet | F27: 45748 | G27: Rejected | H27: 45787 | I27: RCR-002 Marco Santos | J27: Panel Interview | L27: Not Offered | N27: Better fit for future role | P27: =IF($A27="","",IF($G27="Hired",$M27-$F27,IF(OR($G27="Rejected",$G27="Withdrawn"),$H27-$F27,TODAY()-$F27))) -> 39 | Q27: =IF($A27="","",IF(OR($G27="Hired",$G27="Rejected",$G27="Withdrawn"),"Closed",IF($P27>30,"Stale","Active"))) -> Closed | R27: =IF($A27="","",IF($Q27="Closed","Closed",IF($P27<=14,"On Track",IF($P27<=30,"At Risk","Delayed")))) -> Closed | S27: =IF($A27="","",IF($G27="Hired",$M27-$F27,"")) | T27: =IFERROR(_xlfn.XLOOKUP(tblRecruitmentPipeline[[#This Row],[REQ_ID]],tblRequisitions[REQ_ID],tblRequisitions[DEPARTMENT],""),"") -> Information Technology | U27: =IF(tblRecruitmentPipeline[[#This Row],[REQ_DEPARTMENT]]="","No","Yes") -> Yes
A28: APP-00024 | B28: REQ-0005 | C28: CAND-00024 | D28: Julius Lim | E28: Employee Referral | F28: 45763 | G28: Final Interview | H28: 45799 | I28: RCR-002 Marco Santos | J28: Department Head | L28: Not Offered | P28: =IF($A28="","",IF($G28="Hired",$M28-$F28,IF(OR($G28="Rejected",$G28="Withdrawn"),$H28-$F28,TODAY()-$F28))) -> 382 | Q28: =IF($A28="","",IF(OR($G28="Hired",$G28="Rejected",$G28="Withdrawn"),"Closed",IF($P28>30,"Stale","Active"))) -> Stale | R28: =IF($A28="","",IF($Q28="Closed","Closed",IF($P28<=14,"On Track",IF($P28<=30,"At Risk","Delayed")))) -> Delayed | S28: =IF($A28="","",IF($G28="Hired",$M28-$F28,"")) | T28: =IFERROR(_xlfn.XLOOKUP(tblRecruitmentPipeline[[#This Row],[REQ_ID]],tblRequisitions[REQ_ID],tblRequisitions[DEPARTMENT],""),"") -> Information Technology | U28: =IF(tblRecruitmentPipeline[[#This Row],[REQ_DEPARTMENT]]="","No","Yes") -> Yes
A29: APP-00025 | B29: REQ-0005 | C29: CAND-00025 | D29: Maria Villanueva | E29: Agency | F29: 45761 | G29: Rejected | H29: 45800 | I29: RCR-002 Marco Santos | J29: Panel Interview | L29: Not Offered | N29: Failed assessment | P29: =IF($A29="","",IF($G29="Hired",$M29-$F29,IF(OR($G29="Rejected",$G29="Withdrawn"),$H29-$F29,TODAY()-$F29))) -> 39 | Q29: =IF($A29="","",IF(OR($G29="Hired",$G29="Rejected",$G29="Withdrawn"),"Closed",IF($P29>30,"Stale","Active"))) -> Closed | R29: =IF($A29="","",IF($Q29="Closed","Closed",IF($P29<=14,"On Track",IF($P29<=30,"At Risk","Delayed")))) -> Closed | S29: =IF($A29="","",IF($G29="Hired",$M29-$F29,"")) | T29: =IFERROR(_xlfn.XLOOKUP(tblRecruitmentPipeline[[#This Row],[REQ_ID]],tblRequisitions[REQ_ID],tblRequisitions[DEPARTMENT],""),"") -> Information Technology | U29: =IF(tblRecruitmentPipeline[[#This Row],[REQ_DEPARTMENT]]="","No","Yes") -> Yes
A30: APP-00026 | B30: REQ-0006 | C30: CAND-00026 | D30: Nico Dela Cruz | E30: Walk-in | F30: 45819 | G30: Final Interview | H30: 45863 | I30: RCR-004 Carlo Lim | J30: Panel Interview | L30: Not Offered | P30: =IF($A30="","",IF($G30="Hired",$M30-$F30,IF(OR($G30="Rejected",$G30="Withdrawn"),$H30-$F30,TODAY()-$F30))) -> 326 | Q30: =IF($A30="","",IF(OR($G30="Hired",$G30="Rejected",$G30="Withdrawn"),"Closed",IF($P30>30,"Stale","Active"))) -> Stale | R30: =IF($A30="","",IF($Q30="Closed","Closed",IF($P30<=14,"On Track",IF($P30<=30,"At Risk","Delayed")))) -> Delayed | S30: =IF($A30="","",IF($G30="Hired",$M30-$F30,"")) | T30: =IFERROR(_xlfn.XLOOKUP(tblRecruitmentPipeline[[#This Row],[REQ_ID]],tblRequisitions[REQ_ID],tblRequisitions[DEPARTMENT],""),"") -> Loan Processing | U30: =IF(tblRecruitmentPipeline[[#This Row],[REQ_DEPARTMENT]]="","No","Yes") -> Yes
A31: APP-00027 | B31: REQ-0006 | C31: CAND-00027 | D31: Rhea Lim | E31: Company Website | F31: 45804 | G31: Interview | H31: 45817 | I31: RCR-004 Carlo Lim | J31: Panel Interview | L31: Not Offered | P31: =IF($A31="","",IF($G31="Hired",$M31-$F31,IF(OR($G31="Rejected",$G31="Withdrawn"),$H31-$F31,TODAY()-$F31))) -> 341 | Q31: =IF($A31="","",IF(OR($G31="Hired",$G31="Rejected",$G31="Withdrawn"),"Closed",IF($P31>30,"Stale","Active"))) -> Stale | R31: =IF($A31="","",IF($Q31="Closed","Closed",IF($P31<=14,"On Track",IF($P31<=30,"At Risk","Delayed")))) -> Delayed | S31: =IF($A31="","",IF($G31="Hired",$M31-$F31,"")) | T31: =IFERROR(_xlfn.XLOOKUP(tblRecruitmentPipeline[[#This Row],[REQ_ID]],tblRequisitions[REQ_ID],tblRequisitions[DEPARTMENT],""),"") -> Loan Processing | U31: =IF(tblRecruitmentPipeline[[#This Row],[REQ_DEPARTMENT]]="","No","Yes") -> Yes
A32: APP-00028 | B32: REQ-0006 | C32: CAND-00028 | D32: Julius Torres | E32: JobStreet | F32: 45826 | G32: Rejected | H32: 45830 | I32: RCR-004 Carlo Lim | J32: Department Head | L32: Not Offered | N32: Compensation mismatch | P32: =IF($A32="","",IF($G32="Hired",$M32-$F32,IF(OR($G32="Rejected",$G32="Withdrawn"),$H32-$F32,TODAY()-$F32))) -> 4 | Q32: =IF($A32="","",IF(OR($G32="Hired",$G32="Rejected",$G32="Withdrawn"),"Closed",IF($P32>30,"Stale","Active"))) -> Closed | R32: =IF($A32="","",IF($Q32="Closed","Closed",IF($P32<=14,"On Track",IF($P32<=30,"At Risk","Delayed")))) -> Closed | S32: =IF($A32="","",IF($G32="Hired",$M32-$F32,"")) | T32: =IFERROR(_xlfn.XLOOKUP(tblRecruitmentPipeline[[#This Row],[REQ_ID]],tblRequisitions[REQ_ID],tblRequisitions[DEPARTMENT],""),"") -> Loan Processing | U32: =IF(tblRecruitmentPipeline[[#This Row],[REQ_DEPARTMENT]]="","No","Yes") -> Yes
A33: APP-00029 | B33: REQ-0007 | C33: CAND-00029 | D33: Julius Villanueva | E33: JobStreet | F33: 46103 | G33: Hired | H33: 46138 | I33: RCR-001 Ana Reyes | J33: Hiring Manager | K33: 46135 | L33: Accepted | M33: 46148 | P33: =IF($A33="","",IF($G33="Hired",$M33-$F33,IF(OR($G33="Rejected",$G33="Withdrawn"),$H33-$F33,TODAY()-$F33))) -> 45 | Q33: =IF($A33="","",IF(OR($G33="Hired",$G33="Rejected",$G33="Withdrawn"),"Closed",IF($P33>30,"Stale","Active"))) -> Closed | R33: =IF($A33="","",IF($Q33="Closed","Closed",IF($P33<=14,"On Track",IF($P33<=30,"At Risk","Delayed")))) -> Closed | S33: =IF($A33="","",IF($G33="Hired",$M33-$F33,"")) -> 45 | T33: =IFERROR(_xlfn.XLOOKUP(tblRecruitmentPipeline[[#This Row],[REQ_ID]],tblRequisitions[REQ_ID],tblRequisitions[DEPARTMENT],""),"") -> Compliance | U33: =IF(tblRecruitmentPipeline[[#This Row],[REQ_DEPARTMENT]]="","No","Yes") -> Yes
A34: APP-00030 | B34: REQ-0007 | C34: CAND-00030 | D34: Janine Aquino | E34: Walk-in | F34: 46121 | G34: Applied | H34: 46156 | I34: RCR-001 Ana Reyes | J34: Panel Interview | L34: Not Offered | P34: =IF($A34="","",IF($G34="Hired",$M34-$F34,IF(OR($G34="Rejected",$G34="Withdrawn"),$H34-$F34,TODAY()-$F34))) -> 24 | Q34: =IF($A34="","",IF(OR($G34="Hired",$G34="Rejected",$G34="Withdrawn"),"Closed",IF($P34>30,"Stale","Active"))) -> Active | R34: =IF($A34="","",IF($Q34="Closed","Closed",IF($P34<=14,"On Track",IF($P34<=30,"At Risk","Delayed")))) -> At Risk | S34: =IF($A34="","",IF($G34="Hired",$M34-$F34,"")) | T34: =IFERROR(_xlfn.XLOOKUP(tblRecruitmentPipeline[[#This Row],[REQ_ID]],tblRequisitions[REQ_ID],tblRequisitions[DEPARTMENT],""),"") -> Compliance | U34: =IF(tblRecruitmentPipeline[[#This Row],[REQ_DEPARTMENT]]="","No","Yes") -> Yes
A35: APP-00031 | B35: REQ-0007 | C35: CAND-00031 | D35: Janine Castillo | E35: Employee Referral | F35: 46117 | G35: Offer | H35: 46155 | I35: RCR-001 Ana Reyes | J35: Panel Interview | K35: 46153 | L35: Declined | P35: =IF($A35="","",IF($G35="Hired",$M35-$F35,IF(OR($G35="Rejected",$G35="Withdrawn"),$H35-$F35,TODAY()-$F35))) -> 28 | Q35: =IF($A35="","",IF(OR($G35="Hired",$G35="Rejected",$G35="Withdrawn"),"Closed",IF($P35>30,"Stale","Active"))) -> Active | R35: =IF($A35="","",IF($Q35="Closed","Closed",IF($P35<=14,"On Track",IF($P35<=30,"At Risk","Delayed")))) -> At Risk | S35: =IF($A35="","",IF($G35="Hired",$M35-$F35,"")) | T35: =IFERROR(_xlfn.XLOOKUP(tblRecruitmentPipeline[[#This Row],[REQ_ID]],tblRequisitions[REQ_ID],tblRequisitions[DEPARTMENT],""),"") -> Compliance | U35: =IF(tblRecruitmentPipeline[[#This Row],[REQ_DEPARTMENT]]="","No","Yes") -> Yes
A36: APP-00032 | B36: REQ-0007 | C36: CAND-00032 | D36: Nico Castillo | E36: Employee Referral | F36: 46105 | G36: Final Interview | H36: 46131 | I36: RCR-001 Ana Reyes | J36: Department Head | L36: Not Offered | P36: =IF($A36="","",IF($G36="Hired",$M36-$F36,IF(OR($G36="Rejected",$G36="Withdrawn"),$H36-$F36,TODAY()-$F36))) -> 40 | Q36: =IF($A36="","",IF(OR($G36="Hired",$G36="Rejected",$G36="Withdrawn"),"Closed",IF($P36>30,"Stale","Active"))) -> Stale | R36: =IF($A36="","",IF($Q36="Closed","Closed",IF($P36<=14,"On Track",IF($P36<=30,"At Risk","Delayed")))) -> Delayed | S36: =IF($A36="","",IF($G36="Hired",$M36-$F36,"")) | T36: =IFERROR(_xlfn.XLOOKUP(tblRecruitmentPipeline[[#This Row],[REQ_ID]],tblRequisitions[REQ_ID],tblRequisitions[DEPARTMENT],""),"") -> Compliance | U36: =IF(tblRecruitmentPipeline[[#This Row],[REQ_DEPARTMENT]]="","No","Yes") -> Yes
A37: APP-00033 | B37: REQ-0007 | C37: CAND-00033 | D37: Camille Lim | E37: Facebook | F37: 46132 | G37: Rejected | H37: 46172 | I37: RCR-001 Ana Reyes | J37: Hiring Manager | L37: Not Offered | N37: Not qualified | P37: =IF($A37="","",IF($G37="Hired",$M37-$F37,IF(OR($G37="Rejected",$G37="Withdrawn"),$H37-$F37,TODAY()-$F37))) -> 40 | Q37: =IF($A37="","",IF(OR($G37="Hired",$G37="Rejected",$G37="Withdrawn"),"Closed",IF($P37>30,"Stale","Active"))) -> Closed | R37: =IF($A37="","",IF($Q37="Closed","Closed",IF($P37<=14,"On Track",IF($P37<=30,"At Risk","Delayed")))) -> Closed | S37: =IF($A37="","",IF($G37="Hired",$M37-$F37,"")) | T37: =IFERROR(_xlfn.XLOOKUP(tblRecruitmentPipeline[[#This Row],[REQ_ID]],tblRequisitions[REQ_ID],tblRequisitions[DEPARTMENT],""),"") -> Compliance | U37: =IF(tblRecruitmentPipeline[[#This Row],[REQ_DEPARTMENT]]="","No","Yes") -> Yes
A38: APP-00034 | B38: REQ-0008 | C38: CAND-00034 | D38: Paolo Dela Cruz | E38: Employee Referral | F38: 45747 | G38: Hired | H38: 45766 | I38: RCR-003 Leah Cruz | J38: Panel Interview | K38: 45764 | L38: Accepted | M38: 45773 | P38: =IF($A38="","",IF($G38="Hired",$M38-$F38,IF(OR($G38="Rejected",$G38="Withdrawn"),$H38-$F38,TODAY()-$F38))) -> 26 | Q38: =IF($A38="","",IF(OR($G38="Hired",$G38="Rejected",$G38="Withdrawn"),"Closed",IF($P38>30,"Stale","Active"))) -> Closed | R38: =IF($A38="","",IF($Q38="Closed","Closed",IF($P38<=14,"On Track",IF($P38<=30,"At Risk","Delayed")))) -> Closed | S38: =IF($A38="","",IF($G38="Hired",$M38-$F38,"")) -> 26 | T38: =IFERROR(_xlfn.XLOOKUP(tblRecruitmentPipeline[[#This Row],[REQ_ID]],tblRequisitions[REQ_ID],tblRequisitions[DEPARTMENT],""),"") -> Human Resources | U38: =IF(tblRecruitmentPipeline[[#This Row],[REQ_DEPARTMENT]]="","No","Yes") -> Yes
A39: APP-00035 | B39: REQ-0008 | C39: CAND-00035 | D39: Jose Lopez | E39: Company Website | F39: 45750 | G39: Hired | H39: 45778 | I39: RCR-003 Leah Cruz | J39: Department Head | K39: 45775 | L39: Accepted | M39: 45793 | P39: =IF($A39="","",IF($G39="Hired",$M39-$F39,IF(OR($G39="Rejected",$G39="Withdrawn"),$H39-$F39,TODAY()-$F39))) -> 43 | Q39: =IF($A39="","",IF(OR($G39="Hired",$G39="Rejected",$G39="Withdrawn"),"Closed",IF($P39>30,"Stale","Active"))) -> Closed | R39: =IF($A39="","",IF($Q39="Closed","Closed",IF($P39<=14,"On Track",IF($P39<=30,"At Risk","Delayed")))) -> Closed | S39: =IF($A39="","",IF($G39="Hired",$M39-$F39,"")) -> 43 | T39: =IFERROR(_xlfn.XLOOKUP(tblRecruitmentPipeline[[#This Row],[REQ_ID]],tblRequisitions[REQ_ID],tblRequisitions[DEPARTMENT],""),"") -> Human Resources | U39: =IF(tblRecruitmentPipeline[[#This Row],[REQ_DEPARTMENT]]="","No","Yes") -> Yes
A40: APP-00036 | B40: REQ-0008 | C40: CAND-00036 | D40: Janine Gonzales | E40: JobStreet | F40: 45773 | G40: Screened | H40: 45785 | I40: RCR-003 Leah Cruz | J40: Hiring Manager | L40: Not Offered | P40: =IF($A40="","",IF($G40="Hired",$M40-$F40,IF(OR($G40="Rejected",$G40="Withdrawn"),$H40-$F40,TODAY()-$F40))) -> 372 | Q40: =IF($A40="","",IF(OR($G40="Hired",$G40="Rejected",$G40="Withdrawn"),"Closed",IF($P40>30,"Stale","Active"))) -> Stale | R40: =IF($A40="","",IF($Q40="Closed","Closed",IF($P40<=14,"On Track",IF($P40<=30,"At Risk","Delayed")))) -> Delayed | S40: =IF($A40="","",IF($G40="Hired",$M40-$F40,"")) | T40: =IFERROR(_xlfn.XLOOKUP(tblRecruitmentPipeline[[#This Row],[REQ_ID]],tblRequisitions[REQ_ID],tblRequisitions[DEPARTMENT],""),"") -> Human Resources | U40: =IF(tblRecruitmentPipeline[[#This Row],[REQ_DEPARTMENT]]="","No","Yes") -> Yes
A41: APP-00037 | B41: REQ-0008 | C41: CAND-00037 | D41: Paolo Lim | E41: Company Website | F41: 45745 | G41: Screened | H41: 45784 | I41: RCR-003 Leah Cruz | J41: Panel Interview | L41: Not Offered | P41: =IF($A41="","",IF($G41="Hired",$M41-$F41,IF(OR($G41="Rejected",$G41="Withdrawn"),$H41-$F41,TODAY()-$F41))) -> 400 | Q41: =IF($A41="","",IF(OR($G41="Hired",$G41="Rejected",$G41="Withdrawn"),"Closed",IF($P41>30,"Stale","Active"))) -> Stale | R41: =IF($A41="","",IF($Q41="Closed","Closed",IF($P41<=14,"On Track",IF($P41<=30,"At Risk","Delayed")))) -> Delayed | S41: =IF($A41="","",IF($G41="Hired",$M41-$F41,"")) | T41: =IFERROR(_xlfn.XLOOKUP(tblRecruitmentPipeline[[#This Row],[REQ_ID]],tblRequisitions[REQ_ID],tblRequisitions[DEPARTMENT],""),"") -> Human Resources | U41: =IF(tblRecruitmentPipeline[[#This Row],[REQ_DEPARTMENT]]="","No","Yes") -> Yes
A42: APP-00038 | B42: REQ-0009 | C42: CAND-00038 | D42: Bea Santos | E42: Company Website | F42: 46123 | G42: Hired | H42: 46141 | I42: RCR-001 Ana Reyes | J42: Panel Interview | K42: 46139 | L42: Accepted | M42: 46154 | P42: =IF($A42="","",IF($G42="Hired",$M42-$F42,IF(OR($G42="Rejected",$G42="Withdrawn"),$H42-$F42,TODAY()-$F42))) -> 31 | Q42: =IF($A42="","",IF(OR($G42="Hired",$G42="Rejected",$G42="Withdrawn"),"Closed",IF($P42>30,"Stale","Active"))) -> Closed | R42: =IF($A42="","",IF($Q42="Closed","Closed",IF($P42<=14,"On Track",IF($P42<=30,"At Risk","Delayed")))) -> Closed | S42: =IF($A42="","",IF($G42="Hired",$M42-$F42,"")) -> 31 | T42: =IFERROR(_xlfn.XLOOKUP(tblRecruitmentPipeline[[#This Row],[REQ_ID]],tblRequisitions[REQ_ID],tblRequisitions[DEPARTMENT],""),"") -> Compliance | U42: =IF(tblRecruitmentPipeline[[#This Row],[REQ_DEPARTMENT]]="","No","Yes") -> Yes
A43: APP-00039 | B43: REQ-0009 | C43: CAND-00039 | D43: Gabriel Lopez | E43: Walk-in | F43: 46132 | G43: Rejected | H43: 46147 | I43: RCR-001 Ana Reyes | J43: Department Head | L43: Not Offered | N43: Better fit for future role | P43: =IF($A43="","",IF($G43="Hired",$M43-$F43,IF(OR($G43="Rejected",$G43="Withdrawn"),$H43-$F43,TODAY()-$F43))) -> 15 | Q43: =IF($A43="","",IF(OR($G43="Hired",$G43="Rejected",$G43="Withdrawn"),"Closed",IF($P43>30,"Stale","Active"))) -> Closed | R43: =IF($A43="","",IF($Q43="Closed","Closed",IF($P43<=14,"On Track",IF($P43<=30,"At Risk","Delayed")))) -> Closed | S43: =IF($A43="","",IF($G43="Hired",$M43-$F43,"")) | T43: =IFERROR(_xlfn.XLOOKUP(tblRecruitmentPipeline[[#This Row],[REQ_ID]],tblRequisitions[REQ_ID],tblRequisitions[DEPARTMENT],""),"") -> Compliance | U43: =IF(tblRecruitmentPipeline[[#This Row],[REQ_DEPARTMENT]]="","No","Yes") -> Yes
A44: APP-00040 | B44: REQ-0009 | C44: CAND-00040 | D44: Gabriel Lim | E44: Walk-in | F44: 46124 | G44: Screened | H44: 46152 | I44: RCR-001 Ana Reyes | J44: Panel Interview | L44: Not Offered | P44: =IF($A44="","",IF($G44="Hired",$M44-$F44,IF(OR($G44="Rejected",$G44="Withdrawn"),$H44-$F44,TODAY()-$F44))) -> 21 | Q44: =IF($A44="","",IF(OR($G44="Hired",$G44="Rejected",$G44="Withdrawn"),"Closed",IF($P44>30,"Stale","Active"))) -> Active | R44: =IF($A44="","",IF($Q44="Closed","Closed",IF($P44<=14,"On Track",IF($P44<=30,"At Risk","Delayed")))) -> At Risk | S44: =IF($A44="","",IF($G44="Hired",$M44-$F44,"")) | T44: =IFERROR(_xlfn.XLOOKUP(tblRecruitmentPipeline[[#This Row],[REQ_ID]],tblRequisitions[REQ_ID],tblRequisitions[DEPARTMENT],""),"") -> Compliance | U44: =IF(tblRecruitmentPipeline[[#This Row],[REQ_DEPARTMENT]]="","No","Yes") -> Yes
A45: APP-00041 | B45: REQ-0010 | C45: CAND-00041 | D45: Patrick Bautista | E45: Facebook | F45: 45878 | G45: Hired | H45: 45912 | I45: RCR-003 Leah Cruz | J45: Panel Interview | K45: 45909 | L45: Accepted | M45: 45918 | P45: =IF($A45="","",IF($G45="Hired",$M45-$F45,IF(OR($G45="Rejected",$G45="Withdrawn"),$H45-$F45,TODAY()-$F45))) -> 40 | Q45: =IF($A45="","",IF(OR($G45="Hired",$G45="Rejected",$G45="Withdrawn"),"Closed",IF($P45>30,"Stale","Active"))) -> Closed | R45: =IF($A45="","",IF($Q45="Closed","Closed",IF($P45<=14,"On Track",IF($P45<=30,"At Risk","Delayed")))) -> Closed | S45: =IF($A45="","",IF($G45="Hired",$M45-$F45,"")) -> 40 | T45: =IFERROR(_xlfn.XLOOKUP(tblRecruitmentPipeline[[#This Row],[REQ_ID]],tblRequisitions[REQ_ID],tblRequisitions[DEPARTMENT],""),"") -> Loan Processing | U45: =IF(tblRecruitmentPipeline[[#This Row],[REQ_DEPARTMENT]]="","No","Yes") -> Yes
A46: APP-00042 | B46: REQ-0010 | C46: CAND-00042 | D46: Maria Garcia | E46: JobStreet | F46: 45871 | G46: Screened | H46: 45897 | I46: RCR-003 Leah Cruz | J46: Hiring Manager | L46: Not Offered | P46: =IF($A46="","",IF($G46="Hired",$M46-$F46,IF(OR($G46="Rejected",$G46="Withdrawn"),$H46-$F46,TODAY()-$F46))) -> 274 | Q46: =IF($A46="","",IF(OR($G46="Hired",$G46="Rejected",$G46="Withdrawn"),"Closed",IF($P46>30,"Stale","Active"))) -> Stale | R46: =IF($A46="","",IF($Q46="Closed","Closed",IF($P46<=14,"On Track",IF($P46<=30,"At Risk","Delayed")))) -> Delayed | S46: =IF($A46="","",IF($G46="Hired",$M46-$F46,"")) | T46: =IFERROR(_xlfn.XLOOKUP(tblRecruitmentPipeline[[#This Row],[REQ_ID]],tblRequisitions[REQ_ID],tblRequisitions[DEPARTMENT],""),"") -> Loan Processing | U46: =IF(tblRecruitmentPipeline[[#This Row],[REQ_DEPARTMENT]]="","No","Yes") -> Yes
A47: APP-00043 | B47: REQ-0010 | C47: CAND-00043 | D47: Maria Garcia | E47: LinkedIn | F47: 45900 | G47: Rejected | H47: 45934 | I47: RCR-003 Leah Cruz | J47: Department Head | L47: Not Offered | N47: Better fit for future role | P47: =IF($A47="","",IF($G47="Hired",$M47-$F47,IF(OR($G47="Rejected",$G47="Withdrawn"),$H47-$F47,TODAY()-$F47))) -> 34 | Q47: =IF($A47="","",IF(OR($G47="Hired",$G47="Rejected",$G47="Withdrawn"),"Closed",IF($P47>30,"Stale","Active"))) -> Closed | R47: =IF($A47="","",IF($Q47="Closed","Closed",IF($P47<=14,"On Track",IF($P47<=30,"At Risk","Delayed")))) -> Closed | S47: =IF($A47="","",IF($G47="Hired",$M47-$F47,"")) | T47: =IFERROR(_xlfn.XLOOKUP(tblRecruitmentPipeline[[#This Row],[REQ_ID]],tblRequisitions[REQ_ID],tblRequisitions[DEPARTMENT],""),"") -> Loan Processing | U47: =IF(tblRecruitmentPipeline[[#This Row],[REQ_DEPARTMENT]]="","No","Yes") -> Yes
A48: APP-00044 | B48: REQ-0010 | C48: CAND-00044 | D48: Andrea Lopez | E48: Company Website | F48: 45869 | G48: Rejected | H48: 45905 | I48: RCR-003 Leah Cruz | J48: Hiring Manager | L48: Not Offered | N48: Not qualified | P48: =IF($A48="","",IF($G48="Hired",$M48-$F48,IF(OR($G48="Rejected",$G48="Withdrawn"),$H48-$F48,TODAY()-$F48))) -> 36 | Q48: =IF($A48="","",IF(OR($G48="Hired",$G48="Rejected",$G48="Withdrawn"),"Closed",IF($P48>30,"Stale","Active"))) -> Closed | R48: =IF($A48="","",IF($Q48="Closed","Closed",IF($P48<=14,"On Track",IF($P48<=30,"At Risk","Delayed")))) -> Closed | S48: =IF($A48="","",IF($G48="Hired",$M48-$F48,"")) | T48: =IFERROR(_xlfn.XLOOKUP(tblRecruitmentPipeline[[#This Row],[REQ_ID]],tblRequisitions[REQ_ID],tblRequisitions[DEPARTMENT],""),"") -> Loan Processing | U48: =IF(tblRecruitmentPipeline[[#This Row],[REQ_DEPARTMENT]]="","No","Yes") -> Yes
A49: APP-00045 | B49: REQ-0010 | C49: CAND-00045 | D49: Camille Gonzales | E49: Employee Referral | F49: 45901 | G49: Rejected | H49: 45946 | I49: RCR-003 Leah Cruz | J49: Hiring Manager | L49: Not Offered | N49: Better fit for future role | P49: =IF($A49="","",IF($G49="Hired",$M49-$F49,IF(OR($G49="Rejected",$G49="Withdrawn"),$H49-$F49,TODAY()-$F49))) -> 45 | Q49: =IF($A49="","",IF(OR($G49="Hired",$G49="Rejected",$G49="Withdrawn"),"Closed",IF($P49>30,"Stale","Active"))) -> Closed | R49: =IF($A49="","",IF($Q49="Closed","Closed",IF($P49<=14,"On Track",IF($P49<=30,"At Risk","Delayed")))) -> Closed | S49: =IF($A49="","",IF($G49="Hired",$M49-$F49,"")) | T49: =IFERROR(_xlfn.XLOOKUP(tblRecruitmentPipeline[[#This Row],[REQ_ID]],tblRequisitions[REQ_ID],tblRequisitions[DEPARTMENT],""),"") -> Loan Processing | U49: =IF(tblRecruitmentPipeline[[#This Row],[REQ_DEPARTMENT]]="","No","Yes") -> Yes
A50: APP-00046 | B50: REQ-0010 | C50: CAND-00046 | D50: Bea Navarro | E50: Agency | F50: 45900 | G50: Interview | H50: 45932 | I50: RCR-003 Leah Cruz | J50: Panel Interview | L50: Not Offered | P50: =IF($A50="","",IF($G50="Hired",$M50-$F50,IF(OR($G50="Rejected",$G50="Withdrawn"),$H50-$F50,TODAY()-$F50))) -> 245 | Q50: =IF($A50="","",IF(OR($G50="Hired",$G50="Rejected",$G50="Withdrawn"),"Closed",IF($P50>30,"Stale","Active"))) -> Stale | R50: =IF($A50="","",IF($Q50="Closed","Closed",IF($P50<=14,"On Track",IF($P50<=30,"At Risk","Delayed")))) -> Delayed | S50: =IF($A50="","",IF($G50="Hired",$M50-$F50,"")) | T50: =IFERROR(_xlfn.XLOOKUP(tblRecruitmentPipeline[[#This Row],[REQ_ID]],tblRequisitions[REQ_ID],tblRequisitions[DEPARTMENT],""),"") -> Loan Processing | U50: =IF(tblRecruitmentPipeline[[#This Row],[REQ_DEPARTMENT]]="","No","Yes") -> Yes
A51: APP-00047 | B51: REQ-0010 | C51: CAND-00047 | D51: Julius Torres | E51: Walk-in | F51: 45873 | G51: Interview | H51: 45891 | I51: RCR-003 Leah Cruz | J51: Hiring Manager | L51: Not Offered | P51: =IF($A51="","",IF($G51="Hired",$M51-$F51,IF(OR($G51="Rejected",$G51="Withdrawn"),$H51-$F51,TODAY()-$F51))) -> 272 | Q51: =IF($A51="","",IF(OR($G51="Hired",$G51="Rejected",$G51="Withdrawn"),"Closed",IF($P51>30,"Stale","Active"))) -> Stale | R51: =IF($A51="","",IF($Q51="Closed","Closed",IF($P51<=14,"On Track",IF($P51<=30,"At Risk","Delayed")))) -> Delayed | S51: =IF($A51="","",IF($G51="Hired",$M51-$F51,"")) | T51: =IFERROR(_xlfn.XLOOKUP(tblRecruitmentPipeline[[#This Row],[REQ_ID]],tblRequisitions[REQ_ID],tblRequisitions[DEPARTMENT],""),"") -> Loan Processing | U51: =IF(tblRecruitmentPipeline[[#This Row],[REQ_DEPARTMENT]]="","No","Yes") -> Yes
A52: APP-00048 | B52: REQ-0010 | C52: CAND-00048 | D52: Lara Santos | E52: Company Website | F52: 45885 | G52: Offer | H52: 45921 | I52: RCR-003 Leah Cruz | J52: Panel Interview | K52: 45917 | L52: Declined | P52: =IF($A52="","",IF($G52="Hired",$M52-$F52,IF(OR($G52="Rejected",$G52="Withdrawn"),$H52-$F52,TODAY()-$F52))) -> 260 | Q52: =IF($A52="","",IF(OR($G52="Hired",$G52="Rejected",$G52="Withdrawn"),"Closed",IF($P52>30,"Stale","Active"))) -> Stale | R52: =IF($A52="","",IF($Q52="Closed","Closed",IF($P52<=14,"On Track",IF($P52<=30,"At Risk","Delayed")))) -> Delayed | S52: =IF($A52="","",IF($G52="Hired",$M52-$F52,"")) | T52: =IFERROR(_xlfn.XLOOKUP(tblRecruitmentPipeline[[#This Row],[REQ_ID]],tblRequisitions[REQ_ID],tblRequisitions[DEPARTMENT],""),"") -> Loan Processing | U52: =IF(tblRecruitmentPipeline[[#This Row],[REQ_DEPARTMENT]]="","No","Yes") -> Yes
A53: APP-00049 | B53: REQ-0010 | C53: CAND-00049 | D53: Bea Ramos | E53: Company Website | F53: 45867 | G53: Offer | H53: 45876 | I53: RCR-003 Leah Cruz | J53: Department Head | K53: 45871 | L53: Pending | P53: =IF($A53="","",IF($G53="Hired",$M53-$F53,IF(OR($G53="Rejected",$G53="Withdrawn"),$H53-$F53,TODAY()-$F53))) -> 278 | Q53: =IF($A53="","",IF(OR($G53="Hired",$G53="Rejected",$G53="Withdrawn"),"Closed",IF($P53>30,"Stale","Active"))) -> Stale | R53: =IF($A53="","",IF($Q53="Closed","Closed",IF($P53<=14,"On Track",IF($P53<=30,"At Risk","Delayed")))) -> Delayed | S53: =IF($A53="","",IF($G53="Hired",$M53-$F53,"")) | T53: =IFERROR(_xlfn.XLOOKUP(tblRecruitmentPipeline[[#This Row],[REQ_ID]],tblRequisitions[REQ_ID],tblRequisitions[DEPARTMENT],""),"") -> Loan Processing | U53: =IF(tblRecruitmentPipeline[[#This Row],[REQ_DEPARTMENT]]="","No","Yes") -> Yes
A54: APP-00050 | B54: REQ-0011 | C54: CAND-00050 | D54: Rhea Aquino | E54: Employee Referral | F54: 46053 | G54: Screened | H54: 46096 | I54: RCR-003 Leah Cruz | J54: Panel Interview | L54: Not Offered | P54: =IF($A54="","",IF($G54="Hired",$M54-$F54,IF(OR($G54="Rejected",$G54="Withdrawn"),$H54-$F54,TODAY()-$F54))) -> 92 | Q54: =IF($A54="","",IF(OR($G54="Hired",$G54="Rejected",$G54="Withdrawn"),"Closed",IF($P54>30,"Stale","Active"))) -> Stale | R54: =IF($A54="","",IF($Q54="Closed","Closed",IF($P54<=14,"On Track",IF($P54<=30,"At Risk","Delayed")))) -> Delayed | S54: =IF($A54="","",IF($G54="Hired",$M54-$F54,"")) | T54: =IFERROR(_xlfn.XLOOKUP(tblRecruitmentPipeline[[#This Row],[REQ_ID]],tblRequisitions[REQ_ID],tblRequisitions[DEPARTMENT],""),"") -> Collections | U54: =IF(tblRecruitmentPipeline[[#This Row],[REQ_DEPARTMENT]]="","No","Yes") -> Yes
A55: APP-00051 | B55: REQ-0011 | C55: CAND-00051 | D55: Diana Castillo | E55: Walk-in | F55: 46074 | G55: Final Interview | H55: 46115 | I55: RCR-003 Leah Cruz | J55: Hiring Manager | L55: Not Offered | P55: =IF($A55="","",IF($G55="Hired",$M55-$F55,IF(OR($G55="Rejected",$G55="Withdrawn"),$H55-$F55,TODAY()-$F55))) -> 71 | Q55: =IF($A55="","",IF(OR($G55="Hired",$G55="Rejected",$G55="Withdrawn"),"Closed",IF($P55>30,"Stale","Active"))) -> Stale | R55: =IF($A55="","",IF($Q55="Closed","Closed",IF($P55<=14,"On Track",IF($P55<=30,"At Risk","Delayed")))) -> Delayed | S55: =IF($A55="","",IF($G55="Hired",$M55-$F55,"")) | T55: =IFERROR(_xlfn.XLOOKUP(tblRecruitmentPipeline[[#This Row],[REQ_ID]],tblRequisitions[REQ_ID],tblRequisitions[DEPARTMENT],""),"") -> Collections | U55: =IF(tblRecruitmentPipeline[[#This Row],[REQ_DEPARTMENT]]="","No","Yes") -> Yes
A56: APP-00052 | B56: REQ-0011 | C56: CAND-00052 | D56: Julius Dela Cruz | E56: Employee Referral | F56: 46073 | G56: Final Interview | H56: 46110 | I56: RCR-003 Leah Cruz | J56: Panel Interview | L56: Not Offered | P56: =IF($A56="","",IF($G56="Hired",$M56-$F56,IF(OR($G56="Rejected",$G56="Withdrawn"),$H56-$F56,TODAY()-$F56))) -> 72 | Q56: =IF($A56="","",IF(OR($G56="Hired",$G56="Rejected",$G56="Withdrawn"),"Closed",IF($P56>30,"Stale","Active"))) -> Stale | R56: =IF($A56="","",IF($Q56="Closed","Closed",IF($P56<=14,"On Track",IF($P56<=30,"At Risk","Delayed")))) -> Delayed | S56: =IF($A56="","",IF($G56="Hired",$M56-$F56,"")) | T56: =IFERROR(_xlfn.XLOOKUP(tblRecruitmentPipeline[[#This Row],[REQ_ID]],tblRequisitions[REQ_ID],tblRequisitions[DEPARTMENT],""),"") -> Collections | U56: =IF(tblRecruitmentPipeline[[#This Row],[REQ_DEPARTMENT]]="","No","Yes") -> Yes
A57: APP-00053 | B57: REQ-0011 | C57: CAND-00053 | D57: Rhea Navarro | E57: Walk-in | F57: 46082 | G57: Final Interview | H57: 46103 | I57: RCR-003 Leah Cruz | J57: Panel Interview | L57: Not Offered | P57: =IF($A57="","",IF($G57="Hired",$M57-$F57,IF(OR($G57="Rejected",$G57="Withdrawn"),$H57-$F57,TODAY()-$F57))) -> 63 | Q57: =IF($A57="","",IF(OR($G57="Hired",$G57="Rejected",$G57="Withdrawn"),"Closed",IF($P57>30,"Stale","Active"))) -> Stale | R57: =IF($A57="","",IF($Q57="Closed","Closed",IF($P57<=14,"On Track",IF($P57<=30,"At Risk","Delayed")))) -> Delayed | S57: =IF($A57="","",IF($G57="Hired",$M57-$F57,"")) | T57: =IFERROR(_xlfn.XLOOKUP(tblRecruitmentPipeline[[#This Row],[REQ_ID]],tblRequisitions[REQ_ID],tblRequisitions[DEPARTMENT],""),"") -> Collections | U57: =IF(tblRecruitmentPipeline[[#This Row],[REQ_DEPARTMENT]]="","No","Yes") -> Yes
A58: APP-00054 | B58: REQ-0011 | C58: CAND-00054 | D58: Nico Villanueva | E58: Walk-in | F58: 46072 | G58: Hired | H58: 46116 | I58: RCR-003 Leah Cruz | J58: Panel Interview | K58: 46115 | L58: Accepted | M58: 46133 | P58: =IF($A58="","",IF($G58="Hired",$M58-$F58,IF(OR($G58="Rejected",$G58="Withdrawn"),$H58-$F58,TODAY()-$F58))) -> 61 | Q58: =IF($A58="","",IF(OR($G58="Hired",$G58="Rejected",$G58="Withdrawn"),"Closed",IF($P58>30,"Stale","Active"))) -> Closed | R58: =IF($A58="","",IF($Q58="Closed","Closed",IF($P58<=14,"On Track",IF($P58<=30,"At Risk","Delayed")))) -> Closed | S58: =IF($A58="","",IF($G58="Hired",$M58-$F58,"")) -> 61 | T58: =IFERROR(_xlfn.XLOOKUP(tblRecruitmentPipeline[[#This Row],[REQ_ID]],tblRequisitions[REQ_ID],tblRequisitions[DEPARTMENT],""),"") -> Collections | U58: =IF(tblRecruitmentPipeline[[#This Row],[REQ_DEPARTMENT]]="","No","Yes") -> Yes
A59: APP-00055 | B59: REQ-0011 | C59: CAND-00055 | D59: Bea Bautista | E59: Walk-in | F59: 46057 | G59: Applied | H59: 46091 | I59: RCR-003 Leah Cruz | J59: Panel Interview | L59: Not Offered | P59: =IF($A59="","",IF($G59="Hired",$M59-$F59,IF(OR($G59="Rejected",$G59="Withdrawn"),$H59-$F59,TODAY()-$F59))) -> 88 | Q59: =IF($A59="","",IF(OR($G59="Hired",$G59="Rejected",$G59="Withdrawn"),"Closed",IF($P59>30,"Stale","Active"))) -> Stale | R59: =IF($A59="","",IF($Q59="Closed","Closed",IF($P59<=14,"On Track",IF($P59<=30,"At Risk","Delayed")))) -> Delayed | S59: =IF($A59="","",IF($G59="Hired",$M59-$F59,"")) | T59: =IFERROR(_xlfn.XLOOKUP(tblRecruitmentPipeline[[#This Row],[REQ_ID]],tblRequisitions[REQ_ID],tblRequisitions[DEPARTMENT],""),"") -> Collections | U59: =IF(tblRecruitmentPipeline[[#This Row],[REQ_DEPARTMENT]]="","No","Yes") -> Yes
A60: APP-00056 | B60: REQ-0012 | C60: CAND-00056 | D60: Mika Cruz | E60: Walk-in | F60: 46102 | G60: Screened | H60: 46144 | I60: RCR-003 Leah Cruz | J60: Hiring Manager | L60: Not Offered | P60: =IF($A60="","",IF($G60="Hired",$M60-$F60,IF(OR($G60="Rejected",$G60="Withdrawn"),$H60-$F60,TODAY()-$F60))) -> 43 | Q60: =IF($A60="","",IF(OR($G60="Hired",$G60="Rejected",$G60="Withdrawn"),"Closed",IF($P60>30,"Stale","Active"))) -> Stale | R60: =IF($A60="","",IF($Q60="Closed","Closed",IF($P60<=14,"On Track",IF($P60<=30,"At Risk","Delayed")))) -> Delayed | S60: =IF($A60="","",IF($G60="Hired",$M60-$F60,"")) | T60: =IFERROR(_xlfn.XLOOKUP(tblRecruitmentPipeline[[#This Row],[REQ_ID]],tblRequisitions[REQ_ID],tblRequisitions[DEPARTMENT],""),"") -> Sales & Marketing | U60: =IF(tblRecruitmentPipeline[[#This Row],[REQ_DEPARTMENT]]="","No","Yes") -> Yes
A61: APP-00057 | B61: REQ-0012 | C61: CAND-00057 | D61: Andrea Aquino | E61: LinkedIn | F61: 46129 | G61: Rejected | H61: 46158 | I61: RCR-003 Leah Cruz | J61: Department Head | L61: Not Offered | N61: Not qualified | P61: =IF($A61="","",IF($G61="Hired",$M61-$F61,IF(OR($G61="Rejected",$G61="Withdrawn"),$H61-$F61,TODAY()-$F61))) -> 29 | Q61: =IF($A61="","",IF(OR($G61="Hired",$G61="Rejected",$G61="Withdrawn"),"Closed",IF($P61>30,"Stale","Active"))) -> Closed | R61: =IF($A61="","",IF($Q61="Closed","Closed",IF($P61<=14,"On Track",IF($P61<=30,"At Risk","Delayed")))) -> Closed | S61: =IF($A61="","",IF($G61="Hired",$M61-$F61,"")) | T61: =IFERROR(_xlfn.XLOOKUP(tblRecruitmentPipeline[[#This Row],[REQ_ID]],tblRequisitions[REQ_ID],tblRequisitions[DEPARTMENT],""),"") -> Sales & Marketing | U61: =IF(tblRecruitmentPipeline[[#This Row],[REQ_DEPARTMENT]]="","No","Yes") -> Yes
A62: APP-00058 | B62: REQ-0012 | C62: CAND-00058 | D62: Gabriel Mendoza | E62: Company Website | F62: 46104 | G62: Offer | H62: 46152 | I62: RCR-003 Leah Cruz | J62: Panel Interview | K62: 46148 | L62: Declined | P62: =IF($A62="","",IF($G62="Hired",$M62-$F62,IF(OR($G62="Rejected",$G62="Withdrawn"),$H62-$F62,TODAY()-$F62))) -> 41 | Q62: =IF($A62="","",IF(OR($G62="Hired",$G62="Rejected",$G62="Withdrawn"),"Closed",IF($P62>30,"Stale","Active"))) -> Stale | R62: =IF($A62="","",IF($Q62="Closed","Closed",IF($P62<=14,"On Track",IF($P62<=30,"At Risk","Delayed")))) -> Delayed | S62: =IF($A62="","",IF($G62="Hired",$M62-$F62,"")) | T62: =IFERROR(_xlfn.XLOOKUP(tblRecruitmentPipeline[[#This Row],[REQ_ID]],tblRequisitions[REQ_ID],tblRequisitions[DEPARTMENT],""),"") -> Sales & Marketing | U62: =IF(tblRecruitmentPipeline[[#This Row],[REQ_DEPARTMENT]]="","No","Yes") -> Yes
A63: APP-00059 | B63: REQ-0012 | C63: CAND-00059 | D63: Sofia Santos | E63: LinkedIn | F63: 46102 | G63: Rejected | H63: 46115 | I63: RCR-003 Leah Cruz | J63: Panel Interview | L63: Not Offered | N63: Better fit for future role | P63: =IF($A63="","",IF($G63="Hired",$M63-$F63,IF(OR($G63="Rejected",$G63="Withdrawn"),$H63-$F63,TODAY()-$F63))) -> 13 | Q63: =IF($A63="","",IF(OR($G63="Hired",$G63="Rejected",$G63="Withdrawn"),"Closed",IF($P63>30,"Stale","Active"))) -> Closed | R63: =IF($A63="","",IF($Q63="Closed","Closed",IF($P63<=14,"On Track",IF($P63<=30,"At Risk","Delayed")))) -> Closed | S63: =IF($A63="","",IF($G63="Hired",$M63-$F63,"")) | T63: =IFERROR(_xlfn.XLOOKUP(tblRecruitmentPipeline[[#This Row],[REQ_ID]],tblRequisitions[REQ_ID],tblRequisitions[DEPARTMENT],""),"") -> Sales & Marketing | U63: =IF(tblRecruitmentPipeline[[#This Row],[REQ_DEPARTMENT]]="","No","Yes") -> Yes
A64: APP-00060 | B64: REQ-0012 | C64: CAND-00060 | D64: Gabriel Torres | E64: Agency | F64: 46132 | G64: Interview | H64: 46136 | I64: RCR-003 Leah Cruz | J64: Hiring Manager | L64: Not Offered | P64: =IF($A64="","",IF($G64="Hired",$M64-$F64,IF(OR($G64="Rejected",$G64="Withdrawn"),$H64-$F64,TODAY()-$F64))) -> 13 | Q64: =IF($A64="","",IF(OR($G64="Hired",$G64="Rejected",$G64="Withdrawn"),"Closed",IF($P64>30,"Stale","Active"))) -> Active | R64: =IF($A64="","",IF($Q64="Closed","Closed",IF($P64<=14,"On Track",IF($P64<=30,"At Risk","Delayed")))) -> On Track | S64: =IF($A64="","",IF($G64="Hired",$M64-$F64,"")) | T64: =IFERROR(_xlfn.XLOOKUP(tblRecruitmentPipeline[[#This Row],[REQ_ID]],tblRequisitions[REQ_ID],tblRequisitions[DEPARTMENT],""),"") -> Sales & Marketing | U64: =IF(tblRecruitmentPipeline[[#This Row],[REQ_DEPARTMENT]]="","No","Yes") -> Yes
A65: APP-00061 | B65: REQ-0012 | C65: CAND-00061 | D65: Mika Dela Cruz | E65: JobStreet | F65: 46101 | G65: Interview | H65: 46144 | I65: RCR-003 Leah Cruz | J65: Department Head | L65: Not Offered | P65: =IF($A65="","",IF($G65="Hired",$M65-$F65,IF(OR($G65="Rejected",$G65="Withdrawn"),$H65-$F65,TODAY()-$F65))) -> 44 | Q65: =IF($A65="","",IF(OR($G65="Hired",$G65="Rejected",$G65="Withdrawn"),"Closed",IF($P65>30,"Stale","Active"))) -> Stale | R65: =IF($A65="","",IF($Q65="Closed","Closed",IF($P65<=14,"On Track",IF($P65<=30,"At Risk","Delayed")))) -> Delayed | S65: =IF($A65="","",IF($G65="Hired",$M65-$F65,"")) | T65: =IFERROR(_xlfn.XLOOKUP(tblRecruitmentPipeline[[#This Row],[REQ_ID]],tblRequisitions[REQ_ID],tblRequisitions[DEPARTMENT],""),"") -> Sales & Marketing | U65: =IF(tblRecruitmentPipeline[[#This Row],[REQ_DEPARTMENT]]="","No","Yes") -> Yes
A66: APP-00062 | B66: REQ-0012 | C66: CAND-00062 | D66: Bea Ramos | E66: Agency | F66: 46124 | G66: Interview | H66: 46151 | I66: RCR-003 Leah Cruz | J66: Hiring Manager | L66: Not Offered | P66: =IF($A66="","",IF($G66="Hired",$M66-$F66,IF(OR($G66="Rejected",$G66="Withdrawn"),$H66-$F66,TODAY()-$F66))) -> 21 | Q66: =IF($A66="","",IF(OR($G66="Hired",$G66="Rejected",$G66="Withdrawn"),"Closed",IF($P66>30,"Stale","Active"))) -> Active | R66: =IF($A66="","",IF($Q66="Closed","Closed",IF($P66<=14,"On Track",IF($P66<=30,"At Risk","Delayed")))) -> At Risk | S66: =IF($A66="","",IF($G66="Hired",$M66-$F66,"")) | T66: =IFERROR(_xlfn.XLOOKUP(tblRecruitmentPipeline[[#This Row],[REQ_ID]],tblRequisitions[REQ_ID],tblRequisitions[DEPARTMENT],""),"") -> Sales & Marketing | U66: =IF(tblRecruitmentPipeline[[#This Row],[REQ_DEPARTMENT]]="","No","Yes") -> Yes
A67: APP-00063 | B67: REQ-0013 | C67: CAND-00063 | D67: Patrick Navarro | E67: Employee Referral | F67: 45885 | G67: Rejected | H67: 45922 | I67: RCR-003 Leah Cruz | J67: Department Head | L67: Not Offered | N67: Failed assessment | P67: =IF($A67="","",IF($G67="Hired",$M67-$F67,IF(OR($G67="Rejected",$G67="Withdrawn"),$H67-$F67,TODAY()-$F67))) -> 37 | Q67: =IF($A67="","",IF(OR($G67="Hired",$G67="Rejected",$G67="Withdrawn"),"Closed",IF($P67>30,"Stale","Active"))) -> Closed | R67: =IF($A67="","",IF($Q67="Closed","Closed",IF($P67<=14,"On Track",IF($P67<=30,"At Risk","Delayed")))) -> Closed | S67: =IF($A67="","",IF($G67="Hired",$M67-$F67,"")) | T67: =IFERROR(_xlfn.XLOOKUP(tblRecruitmentPipeline[[#This Row],[REQ_ID]],tblRequisitions[REQ_ID],tblRequisitions[DEPARTMENT],""),"") -> Sales & Marketing | U67: =IF(tblRecruitmentPipeline[[#This Row],[REQ_DEPARTMENT]]="","No","Yes") -> Yes
A68: APP-00064 | B68: REQ-0013 | C68: CAND-00064 | D68: Rhea Santos | E68: Employee Referral | F68: 45895 | G68: Offer | H68: 45909 | I68: RCR-003 Leah Cruz | J68: Hiring Manager | K68: 45905 | L68: Declined | P68: =IF($A68="","",IF($G68="Hired",$M68-$F68,IF(OR($G68="Rejected",$G68="Withdrawn"),$H68-$F68,TODAY()-$F68))) -> 250 | Q68: =IF($A68="","",IF(OR($G68="Hired",$G68="Rejected",$G68="Withdrawn"),"Closed",IF($P68>30,"Stale","Active"))) -> Stale | R68: =IF($A68="","",IF($Q68="Closed","Closed",IF($P68<=14,"On Track",IF($P68<=30,"At Risk","Delayed")))) -> Delayed | S68: =IF($A68="","",IF($G68="Hired",$M68-$F68,"")) | T68: =IFERROR(_xlfn.XLOOKUP(tblRecruitmentPipeline[[#This Row],[REQ_ID]],tblRequisitions[REQ_ID],tblRequisitions[DEPARTMENT],""),"") -> Sales & Marketing | U68: =IF(tblRecruitmentPipeline[[#This Row],[REQ_DEPARTMENT]]="","No","Yes") -> Yes
A69: APP-00065 | B69: REQ-0013 | C69: CAND-00065 | D69: Andrea Mendoza | E69: Employee Referral | F69: 45907 | G69: Final Interview | H69: 45944 | I69: RCR-003 Leah Cruz | J69: Hiring Manager | L69: Not Offered | P69: =IF($A69="","",IF($G69="Hired",$M69-$F69,IF(OR($G69="Rejected",$G69="Withdrawn"),$H69-$F69,TODAY()-$F69))) -> 238 | Q69: =IF($A69="","",IF(OR($G69="Hired",$G69="Rejected",$G69="Withdrawn"),"Closed",IF($P69>30,"Stale","Active"))) -> Stale | R69: =IF($A69="","",IF($Q69="Closed","Closed",IF($P69<=14,"On Track",IF($P69<=30,"At Risk","Delayed")))) -> Delayed | S69: =IF($A69="","",IF($G69="Hired",$M69-$F69,"")) | T69: =IFERROR(_xlfn.XLOOKUP(tblRecruitmentPipeline[[#This Row],[REQ_ID]],tblRequisitions[REQ_ID],tblRequisitions[DEPARTMENT],""),"") -> Sales & Marketing | U69: =IF(tblRecruitmentPipeline[[#This Row],[REQ_DEPARTMENT]]="","No","Yes") -> Yes
A70: APP-00066 | B70: REQ-0013 | C70: CAND-00066 | D70: Diana Villanueva | E70: Facebook | F70: 45913 | G70: Withdrawn | H70: 45949 | I70: RCR-003 Leah Cruz | J70: Panel Interview | L70: Not Offered | O70: Schedule conflict | P70: =IF($A70="","",IF($G70="Hired",$M70-$F70,IF(OR($G70="Rejected",$G70="Withdrawn"),$H70-$F70,TODAY()-$F70))) -> 36 | Q70: =IF($A70="","",IF(OR($G70="Hired",$G70="Rejected",$G70="Withdrawn"),"Closed",IF($P70>30,"Stale","Active"))) -> Closed | R70: =IF($A70="","",IF($Q70="Closed","Closed",IF($P70<=14,"On Track",IF($P70<=30,"At Risk","Delayed")))) -> Closed | S70: =IF($A70="","",IF($G70="Hired",$M70-$F70,"")) | T70: =IFERROR(_xlfn.XLOOKUP(tblRecruitmentPipeline[[#This Row],[REQ_ID]],tblRequisitions[REQ_ID],tblRequisitions[DEPARTMENT],""),"") -> Sales & Marketing | U70: =IF(tblRecruitmentPipeline[[#This Row],[REQ_DEPARTMENT]]="","No","Yes") -> Yes
A71: APP-00067 | B71: REQ-0013 | C71: CAND-00067 | D71: Sofia Villanueva | E71: Agency | F71: 45911 | G71: Hired | H71: 45961 | I71: RCR-003 Leah Cruz | J71: Hiring Manager | K71: 45958 | L71: Accepted | M71: 45977 | P71: =IF($A71="","",IF($G71="Hired",$M71-$F71,IF(OR($G71="Rejected",$G71="Withdrawn"),$H71-$F71,TODAY()-$F71))) -> 66 | Q71: =IF($A71="","",IF(OR($G71="Hired",$G71="Rejected",$G71="Withdrawn"),"Closed",IF($P71>30,"Stale","Active"))) -> Closed | R71: =IF($A71="","",IF($Q71="Closed","Closed",IF($P71<=14,"On Track",IF($P71<=30,"At Risk","Delayed")))) -> Closed | S71: =IF($A71="","",IF($G71="Hired",$M71-$F71,"")) -> 66 | T71: =IFERROR(_xlfn.XLOOKUP(tblRecruitmentPipeline[[#This Row],[REQ_ID]],tblRequisitions[REQ_ID],tblRequisitions[DEPARTMENT],""),"") -> Sales & Marketing | U71: =IF(tblRecruitmentPipeline[[#This Row],[REQ_DEPARTMENT]]="","No","Yes") -> Yes
A72: APP-00068 | B72: REQ-0013 | C72: CAND-00068 | D72: Bea Torres | E72: Company Website | F72: 45911 | G72: Applied | H72: 45917 | I72: RCR-003 Leah Cruz | J72: Panel Interview | L72: Not Offered | P72: =IF($A72="","",IF($G72="Hired",$M72-$F72,IF(OR($G72="Rejected",$G72="Withdrawn"),$H72-$F72,TODAY()-$F72))) -> 234 | Q72: =IF($A72="","",IF(OR($G72="Hired",$G72="Rejected",$G72="Withdrawn"),"Closed",IF($P72>30,"Stale","Active"))) -> Stale | R72: =IF($A72="","",IF($Q72="Closed","Closed",IF($P72<=14,"On Track",IF($P72<=30,"At Risk","Delayed")))) -> Delayed | S72: =IF($A72="","",IF($G72="Hired",$M72-$F72,"")) | T72: =IFERROR(_xlfn.XLOOKUP(tblRecruitmentPipeline[[#This Row],[REQ_ID]],tblRequisitions[REQ_ID],tblRequisitions[DEPARTMENT],""),"") -> Sales & Marketing | U72: =IF(tblRecruitmentPipeline[[#This Row],[REQ_DEPARTMENT]]="","No","Yes") -> Yes
A73: APP-00069 | B73: REQ-0013 | C73: CAND-00069 | D73: Camille Santos | E73: Company Website | F73: 45895 | G73: Rejected | H73: 45923 | I73: RCR-003 Leah Cruz | J73: Department Head | L73: Not Offered | N73: Failed assessment | P73: =IF($A73="","",IF($G73="Hired",$M73-$F73,IF(OR($G73="Rejected",$G73="Withdrawn"),$H73-$F73,TODAY()-$F73))) -> 28 | Q73: =IF($A73="","",IF(OR($G73="Hired",$G73="Rejected",$G73="Withdrawn"),"Closed",IF($P73>30,"Stale","Active"))) -> Closed | R73: =IF($A73="","",IF($Q73="Closed","Closed",IF($P73<=14,"On Track",IF($P73<=30,"At Risk","Delayed")))) -> Closed | S73: =IF($A73="","",IF($G73="Hired",$M73-$F73,"")) | T73: =IFERROR(_xlfn.XLOOKUP(tblRecruitmentPipeline[[#This Row],[REQ_ID]],tblRequisitions[REQ_ID],tblRequisitions[DEPARTMENT],""),"") -> Sales & Marketing | U73: =IF(tblRecruitmentPipeline[[#This Row],[REQ_DEPARTMENT]]="","No","Yes") -> Yes
A74: APP-00070 | B74: REQ-0013 | C74: CAND-00070 | D74: Martin Bautista | E74: JobStreet | F74: 45896 | G74: Interview | H74: 45923 | I74: RCR-003 Leah Cruz | J74: Panel Interview | L74: Not Offered | P74: =IF($A74="","",IF($G74="Hired",$M74-$F74,IF(OR($G74="Rejected",$G74="Withdrawn"),$H74-$F74,TODAY()-$F74))) -> 249 | Q74: =IF($A74="","",IF(OR($G74="Hired",$G74="Rejected",$G74="Withdrawn"),"Closed",IF($P74>30,"Stale","Active"))) -> Stale | R74: =IF($A74="","",IF($Q74="Closed","Closed",IF($P74<=14,"On Track",IF($P74<=30,"At Risk","Delayed")))) -> Delayed | S74: =IF($A74="","",IF($G74="Hired",$M74-$F74,"")) | T74: =IFERROR(_xlfn.XLOOKUP(tblRecruitmentPipeline[[#This Row],[REQ_ID]],tblRequisitions[REQ_ID],tblRequisitions[DEPARTMENT],""),"") -> Sales & Marketing | U74: =IF(tblRecruitmentPipeline[[#This Row],[REQ_DEPARTMENT]]="","No","Yes") -> Yes
A75: APP-00071 | B75: REQ-0014 | C75: CAND-00071 | D75: Paolo Ramos | E75: Facebook | F75: 46096 | G75: Hired | H75: 46111 | I75: RCR-002 Marco Santos | J75: Panel Interview | K75: 46106 | L75: Accepted | M75: 46117 | P75: =IF($A75="","",IF($G75="Hired",$M75-$F75,IF(OR($G75="Rejected",$G75="Withdrawn"),$H75-$F75,TODAY()-$F75))) -> 21 | Q75: =IF($A75="","",IF(OR($G75="Hired",$G75="Rejected",$G75="Withdrawn"),"Closed",IF($P75>30,"Stale","Active"))) -> Closed | R75: =IF($A75="","",IF($Q75="Closed","Closed",IF($P75<=14,"On Track",IF($P75<=30,"At Risk","Delayed")))) -> Closed | S75: =IF($A75="","",IF($G75="Hired",$M75-$F75,"")) -> 21 | T75: =IFERROR(_xlfn.XLOOKUP(tblRecruitmentPipeline[[#This Row],[REQ_ID]],tblRequisitions[REQ_ID],tblRequisitions[DEPARTMENT],""),"") -> Branch Operations | U75: =IF(tblRecruitmentPipeline[[#This Row],[REQ_DEPARTMENT]]="","No","Yes") -> Yes
A76: APP-00072 | B76: REQ-0014 | C76: CAND-00072 | D76: Diana Ramos | E76: LinkedIn | F76: 46078 | G76: Screened | H76: 46095 | I76: RCR-002 Marco Santos | J76: Hiring Manager | L76: Not Offered | P76: =IF($A76="","",IF($G76="Hired",$M76-$F76,IF(OR($G76="Rejected",$G76="Withdrawn"),$H76-$F76,TODAY()-$F76))) -> 67 | Q76: =IF($A76="","",IF(OR($G76="Hired",$G76="Rejected",$G76="Withdrawn"),"Closed",IF($P76>30,"Stale","Active"))) -> Stale | R76: =IF($A76="","",IF($Q76="Closed","Closed",IF($P76<=14,"On Track",IF($P76<=30,"At Risk","Delayed")))) -> Delayed | S76: =IF($A76="","",IF($G76="Hired",$M76-$F76,"")) | T76: =IFERROR(_xlfn.XLOOKUP(tblRecruitmentPipeline[[#This Row],[REQ_ID]],tblRequisitions[REQ_ID],tblRequisitions[DEPARTMENT],""),"") -> Branch Operations | U76: =IF(tblRecruitmentPipeline[[#This Row],[REQ_DEPARTMENT]]="","No","Yes") -> Yes
A77: APP-00073 | B77: REQ-0014 | C77: CAND-00073 | D77: Jose Garcia | E77: JobStreet | F77: 46081 | G77: Rejected | H77: 46105 | I77: RCR-002 Marco Santos | J77: Panel Interview | L77: Not Offered | N77: Compensation mismatch | P77: =IF($A77="","",IF($G77="Hired",$M77-$F77,IF(OR($G77="Rejected",$G77="Withdrawn"),$H77-$F77,TODAY()-$F77))) -> 24 | Q77: =IF($A77="","",IF(OR($G77="Hired",$G77="Rejected",$G77="Withdrawn"),"Closed",IF($P77>30,"Stale","Active"))) -> Closed | R77: =IF($A77="","",IF($Q77="Closed","Closed",IF($P77<=14,"On Track",IF($P77<=30,"At Risk","Delayed")))) -> Closed | S77: =IF($A77="","",IF($G77="Hired",$M77-$F77,"")) | T77: =IFERROR(_xlfn.XLOOKUP(tblRecruitmentPipeline[[#This Row],[REQ_ID]],tblRequisitions[REQ_ID],tblRequisitions[DEPARTMENT],""),"") -> Branch Operations | U77: =IF(tblRecruitmentPipeline[[#This Row],[REQ_DEPARTMENT]]="","No","Yes") -> Yes
A78: APP-00074 | B78: REQ-0014 | C78: CAND-00074 | D78: Julius Navarro | E78: Agency | F78: 46097 | G78: Offer | H78: 46147 | I78: RCR-002 Marco Santos | J78: Department Head | K78: 46142 | L78: Pending | P78: =IF($A78="","",IF($G78="Hired",$M78-$F78,IF(OR($G78="Rejected",$G78="Withdrawn"),$H78-$F78,TODAY()-$F78))) -> 48 | Q78: =IF($A78="","",IF(OR($G78="Hired",$G78="Rejected",$G78="Withdrawn"),"Closed",IF($P78>30,"Stale","Active"))) -> Stale | R78: =IF($A78="","",IF($Q78="Closed","Closed",IF($P78<=14,"On Track",IF($P78<=30,"At Risk","Delayed")))) -> Delayed | S78: =IF($A78="","",IF($G78="Hired",$M78-$F78,"")) | T78: =IFERROR(_xlfn.XLOOKUP(tblRecruitmentPipeline[[#This Row],[REQ_ID]],tblRequisitions[REQ_ID],tblRequisitions[DEPARTMENT],""),"") -> Branch Operations | U78: =IF(tblRecruitmentPipeline[[#This Row],[REQ_DEPARTMENT]]="","No","Yes") -> Yes
A79: APP-00075 | B79: REQ-0015 | C79: CAND-00075 | D79: Bea Torres | E79: Walk-in | F79: 46104 | G79: Hired | H79: 46154 | I79: RCR-003 Leah Cruz | J79: Panel Interview | K79: 46149 | L79: Accepted | M79: 46160 | P79: =IF($A79="","",IF($G79="Hired",$M79-$F79,IF(OR($G79="Rejected",$G79="Withdrawn"),$H79-$F79,TODAY()-$F79))) -> 56 | Q79: =IF($A79="","",IF(OR($G79="Hired",$G79="Rejected",$G79="Withdrawn"),"Closed",IF($P79>30,"Stale","Active"))) -> Closed | R79: =IF($A79="","",IF($Q79="Closed","Closed",IF($P79<=14,"On Track",IF($P79<=30,"At Risk","Delayed")))) -> Closed | S79: =IF($A79="","",IF($G79="Hired",$M79-$F79,"")) -> 56 | T79: =IFERROR(_xlfn.XLOOKUP(tblRecruitmentPipeline[[#This Row],[REQ_ID]],tblRequisitions[REQ_ID],tblRequisitions[DEPARTMENT],""),"") -> Collections | U79: =IF(tblRecruitmentPipeline[[#This Row],[REQ_DEPARTMENT]]="","No","Yes") -> Yes
A80: APP-00076 | B80: REQ-0015 | C80: CAND-00076 | D80: Julius Reyes | E80: Agency | F80: 46095 | G80: Applied | H80: 46124 | I80: RCR-003 Leah Cruz | J80: Department Head | L80: Not Offered | P80: =IF($A80="","",IF($G80="Hired",$M80-$F80,IF(OR($G80="Rejected",$G80="Withdrawn"),$H80-$F80,TODAY()-$F80))) -> 50 | Q80: =IF($A80="","",IF(OR($G80="Hired",$G80="Rejected",$G80="Withdrawn"),"Closed",IF($P80>30,"Stale","Active"))) -> Stale | R80: =IF($A80="","",IF($Q80="Closed","Closed",IF($P80<=14,"On Track",IF($P80<=30,"At Risk","Delayed")))) -> Delayed | S80: =IF($A80="","",IF($G80="Hired",$M80-$F80,"")) | T80: =IFERROR(_xlfn.XLOOKUP(tblRecruitmentPipeline[[#This Row],[REQ_ID]],tblRequisitions[REQ_ID],tblRequisitions[DEPARTMENT],""),"") -> Collections | U80: =IF(tblRecruitmentPipeline[[#This Row],[REQ_DEPARTMENT]]="","No","Yes") -> Yes
A81: APP-00077 | B81: REQ-0015 | C81: CAND-00077 | D81: Jose Villanueva | E81: Employee Referral | F81: 46112 | G81: Rejected | H81: 46125 | I81: RCR-003 Leah Cruz | J81: Panel Interview | L81: Not Offered | N81: Better fit for future role | P81: =IF($A81="","",IF($G81="Hired",$M81-$F81,IF(OR($G81="Rejected",$G81="Withdrawn"),$H81-$F81,TODAY()-$F81))) -> 13 | Q81: =IF($A81="","",IF(OR($G81="Hired",$G81="Rejected",$G81="Withdrawn"),"Closed",IF($P81>30,"Stale","Active"))) -> Closed | R81: =IF($A81="","",IF($Q81="Closed","Closed",IF($P81<=14,"On Track",IF($P81<=30,"At Risk","Delayed")))) -> Closed | S81: =IF($A81="","",IF($G81="Hired",$M81-$F81,"")) | T81: =IFERROR(_xlfn.XLOOKUP(tblRecruitmentPipeline[[#This Row],[REQ_ID]],tblRequisitions[REQ_ID],tblRequisitions[DEPARTMENT],""),"") -> Collections | U81: =IF(tblRecruitmentPipeline[[#This Row],[REQ_DEPARTMENT]]="","No","Yes") -> Yes
A82: APP-00078 | B82: REQ-0015 | C82: CAND-00078 | D82: Bea Garcia | E82: Employee Referral | F82: 46087 | G82: Applied | H82: 46102 | I82: RCR-003 Leah Cruz | J82: Department Head | L82: Not Offered | P82: =IF($A82="","",IF($G82="Hired",$M82-$F82,IF(OR($G82="Rejected",$G82="Withdrawn"),$H82-$F82,TODAY()-$F82))) -> 58 | Q82: =IF($A82="","",IF(OR($G82="Hired",$G82="Rejected",$G82="Withdrawn"),"Closed",IF($P82>30,"Stale","Active"))) -> Stale | R82: =IF($A82="","",IF($Q82="Closed","Closed",IF($P82<=14,"On Track",IF($P82<=30,"At Risk","Delayed")))) -> Delayed | S82: =IF($A82="","",IF($G82="Hired",$M82-$F82,"")) | T82: =IFERROR(_xlfn.XLOOKUP(tblRecruitmentPipeline[[#This Row],[REQ_ID]],tblRequisitions[REQ_ID],tblRequisitions[DEPARTMENT],""),"") -> Collections | U82: =IF(tblRecruitmentPipeline[[#This Row],[REQ_DEPARTMENT]]="","No","Yes") -> Yes
A83: APP-00079 | B83: REQ-0015 | C83: CAND-00079 | D83: Nico Aquino | E83: Facebook | F83: 46103 | G83: Screened | H83: 46121 | I83: RCR-003 Leah Cruz | J83: Panel Interview | L83: Not Offered | P83: =IF($A83="","",IF($G83="Hired",$M83-$F83,IF(OR($G83="Rejected",$G83="Withdrawn"),$H83-$F83,TODAY()-$F83))) -> 42 | Q83: =IF($A83="","",IF(OR($G83="Hired",$G83="Rejected",$G83="Withdrawn"),"Closed",IF($P83>30,"Stale","Active"))) -> Stale | R83: =IF($A83="","",IF($Q83="Closed","Closed",IF($P83<=14,"On Track",IF($P83<=30,"At Risk","Delayed")))) -> Delayed | S83: =IF($A83="","",IF($G83="Hired",$M83-$F83,"")) | T83: =IFERROR(_xlfn.XLOOKUP(tblRecruitmentPipeline[[#This Row],[REQ_ID]],tblRequisitions[REQ_ID],tblRequisitions[DEPARTMENT],""),"") -> Collections | U83: =IF(tblRecruitmentPipeline[[#This Row],[REQ_DEPARTMENT]]="","No","Yes") -> Yes
A84: APP-00080 | B84: REQ-0015 | C84: CAND-00080 | D84: Miguel Ramos | E84: Facebook | F84: 46108 | G84: Interview | H84: 46141 | I84: RCR-003 Leah Cruz | J84: Panel Interview | L84: Not Offered | P84: =IF($A84="","",IF($G84="Hired",$M84-$F84,IF(OR($G84="Rejected",$G84="Withdrawn"),$H84-$F84,TODAY()-$F84))) -> 37 | Q84: =IF($A84="","",IF(OR($G84="Hired",$G84="Rejected",$G84="Withdrawn"),"Closed",IF($P84>30,"Stale","Active"))) -> Stale | R84: =IF($A84="","",IF($Q84="Closed","Closed",IF($P84<=14,"On Track",IF($P84<=30,"At Risk","Delayed")))) -> Delayed | S84: =IF($A84="","",IF($G84="Hired",$M84-$F84,"")) | T84: =IFERROR(_xlfn.XLOOKUP(tblRecruitmentPipeline[[#This Row],[REQ_ID]],tblRequisitions[REQ_ID],tblRequisitions[DEPARTMENT],""),"") -> Collections | U84: =IF(tblRecruitmentPipeline[[#This Row],[REQ_DEPARTMENT]]="","No","Yes") -> Yes
A85: APP-00081 | B85: REQ-0016 | C85: CAND-00081 | D85: Paolo Lim | E85: Agency | F85: 45946 | G85: Rejected | H85: 45965 | I85: RCR-004 Carlo Lim | J85: Panel Interview | L85: Not Offered | N85: Better fit for future role | P85: =IF($A85="","",IF($G85="Hired",$M85-$F85,IF(OR($G85="Rejected",$G85="Withdrawn"),$H85-$F85,TODAY()-$F85))) -> 19 | Q85: =IF($A85="","",IF(OR($G85="Hired",$G85="Rejected",$G85="Withdrawn"),"Closed",IF($P85>30,"Stale","Active"))) -> Closed | R85: =IF($A85="","",IF($Q85="Closed","Closed",IF($P85<=14,"On Track",IF($P85<=30,"At Risk","Delayed")))) -> Closed | S85: =IF($A85="","",IF($G85="Hired",$M85-$F85,"")) | T85: =IFERROR(_xlfn.XLOOKUP(tblRecruitmentPipeline[[#This Row],[REQ_ID]],tblRequisitions[REQ_ID],tblRequisitions[DEPARTMENT],""),"") -> Finance | U85: =IF(tblRecruitmentPipeline[[#This Row],[REQ_DEPARTMENT]]="","No","Yes") -> Yes
A86: APP-00082 | B86: REQ-0016 | C86: CAND-00082 | D86: Nico Gonzales | E86: Walk-in | F86: 45937 | G86: Rejected | H86: 45985 | I86: RCR-004 Carlo Lim | J86: Department Head | L86: Not Offered | N86: Failed assessment | P86: =IF($A86="","",IF($G86="Hired",$M86-$F86,IF(OR($G86="Rejected",$G86="Withdrawn"),$H86-$F86,TODAY()-$F86))) -> 48 | Q86: =IF($A86="","",IF(OR($G86="Hired",$G86="Rejected",$G86="Withdrawn"),"Closed",IF($P86>30,"Stale","Active"))) -> Closed | R86: =IF($A86="","",IF($Q86="Closed","Closed",IF($P86<=14,"On Track",IF($P86<=30,"At Risk","Delayed")))) -> Closed | S86: =IF($A86="","",IF($G86="Hired",$M86-$F86,"")) | T86: =IFERROR(_xlfn.XLOOKUP(tblRecruitmentPipeline[[#This Row],[REQ_ID]],tblRequisitions[REQ_ID],tblRequisitions[DEPARTMENT],""),"") -> Finance | U86: =IF(tblRecruitmentPipeline[[#This Row],[REQ_DEPARTMENT]]="","No","Yes") -> Yes
A87: APP-00083 | B87: REQ-0016 | C87: CAND-00083 | D87: Maria Lopez | E87: Walk-in | F87: 45935 | G87: Screened | H87: 45984 | I87: RCR-004 Carlo Lim | J87: Hiring Manager | L87: Not Offered | P87: =IF($A87="","",IF($G87="Hired",$M87-$F87,IF(OR($G87="Rejected",$G87="Withdrawn"),$H87-$F87,TODAY()-$F87))) -> 210 | Q87: =IF($A87="","",IF(OR($G87="Hired",$G87="Rejected",$G87="Withdrawn"),"Closed",IF($P87>30,"Stale","Active"))) -> Stale | R87: =IF($A87="","",IF($Q87="Closed","Closed",IF($P87<=14,"On Track",IF($P87<=30,"At Risk","Delayed")))) -> Delayed | S87: =IF($A87="","",IF($G87="Hired",$M87-$F87,"")) | T87: =IFERROR(_xlfn.XLOOKUP(tblRecruitmentPipeline[[#This Row],[REQ_ID]],tblRequisitions[REQ_ID],tblRequisitions[DEPARTMENT],""),"") -> Finance | U87: =IF(tblRecruitmentPipeline[[#This Row],[REQ_DEPARTMENT]]="","No","Yes") -> Yes
A88: APP-00084 | B88: REQ-0016 | C88: CAND-00084 | D88: Janine Bautista | E88: Walk-in | F88: 45934 | G88: Interview | H88: 45944 | I88: RCR-004 Carlo Lim | J88: Department Head | L88: Not Offered | P88: =IF($A88="","",IF($G88="Hired",$M88-$F88,IF(OR($G88="Rejected",$G88="Withdrawn"),$H88-$F88,TODAY()-$F88))) -> 211 | Q88: =IF($A88="","",IF(OR($G88="Hired",$G88="Rejected",$G88="Withdrawn"),"Closed",IF($P88>30,"Stale","Active"))) -> Stale | R88: =IF($A88="","",IF($Q88="Closed","Closed",IF($P88<=14,"On Track",IF($P88<=30,"At Risk","Delayed")))) -> Delayed | S88: =IF($A88="","",IF($G88="Hired",$M88-$F88,"")) | T88: =IFERROR(_xlfn.XLOOKUP(tblRecruitmentPipeline[[#This Row],[REQ_ID]],tblRequisitions[REQ_ID],tblRequisitions[DEPARTMENT],""),"") -> Finance | U88: =IF(tblRecruitmentPipeline[[#This Row],[REQ_DEPARTMENT]]="","No","Yes") -> Yes
A89: APP-00085 | B89: REQ-0016 | C89: CAND-00085 | D89: Carlo Castillo | E89: JobStreet | F89: 45942 | G89: Screened | H89: 45980 | I89: RCR-004 Carlo Lim | J89: Panel Interview | L89: Not Offered | P89: =IF($A89="","",IF($G89="Hired",$M89-$F89,IF(OR($G89="Rejected",$G89="Withdrawn"),$H89-$F89,TODAY()-$F89))) -> 203 | Q89: =IF($A89="","",IF(OR($G89="Hired",$G89="Rejected",$G89="Withdrawn"),"Closed",IF($P89>30,"Stale","Active"))) -> Stale | R89: =IF($A89="","",IF($Q89="Closed","Closed",IF($P89<=14,"On Track",IF($P89<=30,"At Risk","Delayed")))) -> Delayed | S89: =IF($A89="","",IF($G89="Hired",$M89-$F89,"")) | T89: =IFERROR(_xlfn.XLOOKUP(tblRecruitmentPipeline[[#This Row],[REQ_ID]],tblRequisitions[REQ_ID],tblRequisitions[DEPARTMENT],""),"") -> Finance | U89: =IF(tblRecruitmentPipeline[[#This Row],[REQ_DEPARTMENT]]="","No","Yes") -> Yes
A90: APP-00086 | B90: REQ-0016 | C90: CAND-00086 | D90: Julius Garcia | E90: Facebook | F90: 45933 | G90: Applied | H90: 45951 | I90: RCR-004 Carlo Lim | J90: Panel Interview | L90: Not Offered | P90: =IF($A90="","",IF($G90="Hired",$M90-$F90,IF(OR($G90="Rejected",$G90="Withdrawn"),$H90-$F90,TODAY()-$F90))) -> 212 | Q90: =IF($A90="","",IF(OR($G90="Hired",$G90="Rejected",$G90="Withdrawn"),"Closed",IF($P90>30,"Stale","Active"))) -> Stale | R90: =IF($A90="","",IF($Q90="Closed","Closed",IF($P90<=14,"On Track",IF($P90<=30,"At Risk","Delayed")))) -> Delayed | S90: =IF($A90="","",IF($G90="Hired",$M90-$F90,"")) | T90: =IFERROR(_xlfn.XLOOKUP(tblRecruitmentPipeline[[#This Row],[REQ_ID]],tblRequisitions[REQ_ID],tblRequisitions[DEPARTMENT],""),"") -> Finance | U90: =IF(tblRecruitmentPipeline[[#This Row],[REQ_DEPARTMENT]]="","No","Yes") -> Yes
A91: APP-00087 | B91: REQ-0016 | C91: CAND-00087 | D91: Ethan Aquino | E91: Employee Referral | F91: 45944 | G91: Screened | H91: 45969 | I91: RCR-004 Carlo Lim | J91: Hiring Manager | L91: Not Offered | P91: =IF($A91="","",IF($G91="Hired",$M91-$F91,IF(OR($G91="Rejected",$G91="Withdrawn"),$H91-$F91,TODAY()-$F91))) -> 201 | Q91: =IF($A91="","",IF(OR($G91="Hired",$G91="Rejected",$G91="Withdrawn"),"Closed",IF($P91>30,"Stale","Active"))) -> Stale | R91: =IF($A91="","",IF($Q91="Closed","Closed",IF($P91<=14,"On Track",IF($P91<=30,"At Risk","Delayed")))) -> Delayed | S91: =IF($A91="","",IF($G91="Hired",$M91-$F91,"")) | T91: =IFERROR(_xlfn.XLOOKUP(tblRecruitmentPipeline[[#This Row],[REQ_ID]],tblRequisitions[REQ_ID],tblRequisitions[DEPARTMENT],""),"") -> Finance | U91: =IF(tblRecruitmentPipeline[[#This Row],[REQ_DEPARTMENT]]="","No","Yes") -> Yes
A92: APP-00088 | B92: REQ-0016 | C92: CAND-00088 | D92: Gabriel Ramos | E92: Agency | F92: 45949 | G92: Screened | H92: 45994 | I92: RCR-004 Carlo Lim | J92: Panel Interview | L92: Not Offered | P92: =IF($A92="","",IF($G92="Hired",$M92-$F92,IF(OR($G92="Rejected",$G92="Withdrawn"),$H92-$F92,TODAY()-$F92))) -> 196 | Q92: =IF($A92="","",IF(OR($G92="Hired",$G92="Rejected",$G92="Withdrawn"),"Closed",IF($P92>30,"Stale","Active"))) -> Stale | R92: =IF($A92="","",IF($Q92="Closed","Closed",IF($P92<=14,"On Track",IF($P92<=30,"At Risk","Delayed")))) -> Delayed | S92: =IF($A92="","",IF($G92="Hired",$M92-$F92,"")) | T92: =IFERROR(_xlfn.XLOOKUP(tblRecruitmentPipeline[[#This Row],[REQ_ID]],tblRequisitions[REQ_ID],tblRequisitions[DEPARTMENT],""),"") -> Finance | U92: =IF(tblRecruitmentPipeline[[#This Row],[REQ_DEPARTMENT]]="","No","Yes") -> Yes
A93: APP-00089 | B93: REQ-0016 | C93: CAND-00089 | D93: Rafael Bautista | E93: Company Website | F93: 45957 | G93: Screened | H93: 45977 | I93: RCR-004 Carlo Lim | J93: Panel Interview | L93: Not Offered | P93: =IF($A93="","",IF($G93="Hired",$M93-$F93,IF(OR($G93="Rejected",$G93="Withdrawn"),$H93-$F93,TODAY()-$F93))) -> 188 | Q93: =IF($A93="","",IF(OR($G93="Hired",$G93="Rejected",$G93="Withdrawn"),"Closed",IF($P93>30,"Stale","Active"))) -> Stale | R93: =IF($A93="","",IF($Q93="Closed","Closed",IF($P93<=14,"On Track",IF($P93<=30,"At Risk","Delayed")))) -> Delayed | S93: =IF($A93="","",IF($G93="Hired",$M93-$F93,"")) | T93: =IFERROR(_xlfn.XLOOKUP(tblRecruitmentPipeline[[#This Row],[REQ_ID]],tblRequisitions[REQ_ID],tblRequisitions[DEPARTMENT],""),"") -> Finance | U93: =IF(tblRecruitmentPipeline[[#This Row],[REQ_DEPARTMENT]]="","No","Yes") -> Yes
A94: APP-00090 | B94: REQ-0017 | C94: CAND-00090 | D94: Sofia Lim | E94: Walk-in | F94: 45784 | G94: Rejected | H94: 45810 | I94: RCR-003 Leah Cruz | J94: Hiring Manager | L94: Not Offered | N94: Failed assessment | P94: =IF($A94="","",IF($G94="Hired",$M94-$F94,IF(OR($G94="Rejected",$G94="Withdrawn"),$H94-$F94,TODAY()-$F94))) -> 26 | Q94: =IF($A94="","",IF(OR($G94="Hired",$G94="Rejected",$G94="Withdrawn"),"Closed",IF($P94>30,"Stale","Active"))) -> Closed | R94: =IF($A94="","",IF($Q94="Closed","Closed",IF($P94<=14,"On Track",IF($P94<=30,"At Risk","Delayed")))) -> Closed | S94: =IF($A94="","",IF($G94="Hired",$M94-$F94,"")) | T94: =IFERROR(_xlfn.XLOOKUP(tblRecruitmentPipeline[[#This Row],[REQ_ID]],tblRequisitions[REQ_ID],tblRequisitions[DEPARTMENT],""),"") -> Customer Service | U94: =IF(tblRecruitmentPipeline[[#This Row],[REQ_DEPARTMENT]]="","No","Yes") -> Yes
